Workbook

Sheet Intructivo
B2: Matriz Mapa de Riesgos
B4: Teniendo en cuenta que con la expedición del Decreto 1499 de 2017 “Por medio del cual se modifica el Decreto 1083 de 2015, Decreto Único Reglamentario del Sector Función Pública, en lo relacionado con el Sistema de Gestión establecido en el artículo 133 de la Ley 1753 de 2015”, se crea un solo Sistema de Gestión y se alinea con el Sistema de Control Interno, hoy todas las entidades públicas requieren actualizar y/o implementar el Modelo Integrado de Planeación y Gestión MIPG, modelo que incorpora el Modelo Estándar de Control Interno MECI a través de la 7a dimensión del mismo. En este marco general, el proceso de administración del riesgo es un esfuerzo conjunto entre la Alta Dirección y los servidores en todos sus niveles, ejercicio que inicia con la formulación de la política de Administración del Riesgo, la cual incluye los niveles de responsabilidad frente al seguimiento y evaluación, aspectos que deberán definirse acorde con el Esquema de Líneas de Defensa vinculado a la Dimensión 7. Teniendo en cuenta lo anterior y dada la necesidad de las entidades frente a la estructuración de los mapas de riesgos, como herramienta fundamental frente a la gestión del riesgo, el presente formato desarrolla un esquema completo acorde con los contenidos metodológicos de la Guía para la Administración del Riesgo y el diseño de controles V5. El formato cuenta con celdas parametrizadas y permite contar con los respectivos mapas de calor para riesgo inherente y riesgo residual.
B6: Orientaciones Generales
B7: Antes de iniciar con el diligenciamiento de la información en la matriz, se requiere haber avanzado en el análisis del proceso, su objetivo, alcance, actividades clave, considere los lineamientos establecidos en el Paso 2: identificación del riesgo, donde se explica ampliamente las bases para adelanter este análisis. Así mismo, considere en el Paso 3: valoración del riesgo los lineamientos para definir el No. de veces que se hace la actividad con la cual se relaciona el riesgo y su impacto en términos económicos o reputacionales. En este mismo paso se analizan los controles que deben responder a los atributos de eficiencia e informativos. NOTA: Si lo considera pertinente, es posible agregar hojas de trabajo adicionales al presente formato que permitan incluir la traza de estos análisis.
B9: El archivo contiene las siguientes hojas: - Hoja 1 Instructivo - Hoja 2 Mapa Final: Encontrará la totalidad de la estructura para la identificación y valoración de los riesgos por proceso, programa o proyecto, acorde con el nivel de desagregación que la entidad considere necesaria.
C12: Columna | E12: Descripción - Lineamientos para el diligenciamiento
C13: Proceso | E13: Diligencie el nombre del proceso al cual se le identificarán y valorarán los riesgos.
C14: Objetivo | E14: Diligencie el objetivo del proceso.
C15: Alcance | E15: Diligencie el alcance del proceso.
C16: Referencia | E16: Permite definir unl consecutivo de riesgos. Una entidad puede ir en el riesgo 150, pero tener 70 riesgos, lo que permite llevar una traza de los riesgos. Esta información la debe administrar la oficina asesora de planeación o gerencia de riesgos. Cuando un el riesgo salga del mapa no existirá otro riesgo con el mismo número.
C17: Impacto | E17: Analice las consecuencias que puede ocasionar a la organización la materialización del riesgo, redacte de la forma más concreta posible.
C18: Causa Inmediata | E18: Circunstancias bajo las cuales se presenta el riesgo, es la situación más evidente frente al riesgo, redacte de la forma más concreta posible.
C19: Causa Raíz | E19: Causa principal o básica, corresponde a las razones por la cuales se puede presentar el riesgo, redacte de la forma más concreta posible.
C20: Descripción del Riesgo | E20: Consolida o resume los análisis sobre impacto + causa inmediata + causa raíz, permitiendo contar con una redacción clara y concreta del riesgo indentificado. Tenga en cuenta la estructura de alto nivel establecida en al guía, inicia con POSIBILIDAD DE + Impacto para la entidad (Qué) + Causa Inmediata (Cómo) + Causa Raíz (Por qué)
C21: Clasificación del Riesgo | E21: Utilice la lista de despligue que se encuentra parametrizada, le aparecerán las opciones: i)Daños Activos Fisicos, ii)Ejecucion y Administracion de procesos, iii)Fallas Tecnologicas, iv)Fraude Externo, v)Fraude Interno, vi)Relaciones Laborales, vii)Usuarios, productos y practicas organizacionales.
C22: Frecuencia con la cual se lleva a cabo la actividad | E22: Defina el # de veces que se ejecuta la actividad durante el año, (Recuerde la probabilidad e ocurrencia del riesgo se defien como el No. de veces que se pasa por el punto de riesgo en el periodo de 1 año). La matriz automáticamente hará el cálculo para el nivel de probabilidad inherente (Columnas H-I)
C23: Criterios de Impacto | E23: Utilice la lista de despligue que se encuentra parametrizada, le aparecerán las opciones de la tabla de Impacto en la Hoja 6 del presente documento. La matriz automáticamente hará el cálculo para el nivel de impacto inherente (Columnas L-M)
... C37: Estado | E37: Utilice la lista de despligue que se encuentra parametrizada, le aparecerán las opciones: i)Finalizado, ii)En curso, la selección en este caso dependerá de las acciones del plan que se hayan establecido en cada caso.
B40: - Hoja 3 Matriz de Calor Inherente: En esta hoja, en la medida en que ese diligencia el Mapa Final, se verán reflejados los riesgos en su zona correspondiente. Esta hoja no se diligencia se genera de manera automática.
B41: - Hoja 4 Matriz de Calor Residual: En esta hoja, en la medida en que ese diligencia el Mapa Final, se verán reflejados los riesgos en su zona correspondiente. Esta hoja no se diligencia se genera de manera automática.
B42: - Hoja 5 Tabla de probabilidad: Tabla referente para todos los cálculos (no se diligencia)
B43: - Hoja 6 Tabla de Impacto: Tabla referente para todos los cálculos (no se diligencia)
B44: - Hoja 7 Tabla de Valoración de Controles: Tabla referente para todos los cálculos (no se diligencia)

Sheet Mapa final
D1: SISTEMA DE GESTIÓN DE CALIDAD
D3: GESTIÓN DE CALIDAD
D4: MAPA DE RIESGOS
D5: VERSIÓN: 05 | G5: FECHA: 07-05-2025 | J5: Página 1 de 1
A7: Proceso: | C7: Gestion de Evaluación Independiente
A8: Objetivo: | C8: Mejorar y proteger el valor de la organización a través de la ejecución del programa de auditorías, de manera independiente y objetiva en el marco del sistema de control interno con el fin de ofrecer una seguridad razonable respecto al logro de los objetivos institucionales
A9: Alcance: | C9: Inicia desde la definición de la estrategia y métodos para evaluar la gestión institucional con enfoque preventivo hasta la revisión de la estrategia y metodología para la evaluación de la gestión institucional
A10: Identificación del riesgo | H10: Análisis del riesgo inherente | O10: Evaluación del riesgo - Valoración de los controles | X10: Evaluación del riesgo - Nivel del riesgo residual | AE10: Plan de Acción | AH10: I SEGUIMIENTO 2025 Corte: 30 de abril 2025 | AK10: III SEGUIMIENTO 2025 Corte: 31 de agosto 2025 | AN10: III SEGUIMIENTO 2025 Corte: 31 diciembre 2025
A11: Referencia | B11: Impacto | C11: Causa Inmediata | D11: Causa Raíz | E11: Descripción del Riesgo | F11: Clasificación del Riesgo | G11: Frecuencia con la cual se realiza la actividad | H11: Probabilidad Inherente | I11: % | J11: Criterios de impacto | K11: Observación de criterio | L11: Impacto Inherente | M11: % | N11: Zona de Riesgo Inherente | O11: No. Control | P11: Descripción del Control | Q11: Afectación | R11: Atributos | X11: Probabilidad Residual | Y11: Probabilidad Residual Final | Z11: % | AA11: Impacto Residual Final | AB11: % | AC11: Zona de Riesgo Final | AD11: Tratamiento | AE11: Plan de Acción | AF11: Responsable | AG11: Fecha Implementación | AH11: Fecha Seguimiento | AI11: Seguimiento | AJ11: Estado del Plan de Acción | AK11: Fecha Seguimiento | AL11: Seguimiento | AM11: Estado del Plan de Acción | AN11: Fecha Seguimiento | AO11: Seguimiento | AP11: Estado del Plan de Acción
R12: Tipo | S12: Implementación | T12: Calificación | U12: Documentación | V12: Frecuencia | W12: Evidencia
A13: 1 | B13: Reputacional | C13: Falta de mejora de los procesos de la Corporacion y perdida de credibilidad por parte de la ciudadania | D13: Incumplimiento de Plan Anual de Auditoria aprobado por el comité Insttitucional de Coordinación de Control Interno, por aspectos internos y externos. | E13: Posibilidad de afectación reputaciones por la falta de mejora de los procesos de la Corporacion y perdida de credibilidad por parte de la ciudadania por incumplimiento del Plan Anual de Auditoria aprobado por el comité Insttitucional de Coordinación de Control Interno | F13: Ejecucion y Administracion de procesos | G13: 27 | H13: =IF(G13<=0,"",IF(G13<=2,"Muy Baja",IF(G13<=24,"Baja",IF(G13<=500,"Media",IF(G13<=5000,"Alta","Muy Alta"))))) -> Media | I13: =IF(H13="","",IF(H13="Muy Baja",0.2,IF(H13="Baja",0.4,IF(H13="Media",0.6,IF(H13="Alta",0.8,IF(H13="Muy Alta",1,)))))) -> 0.6 | J13: El riesgo afecta la imagen de la entidad internamente, de conocimiento general, nivel interno, de junta dircetiva y accionistas y/o de provedores | K13: =IF(NOT(ISERROR(MATCH(J13,#REF!,0))),#REF!&"Por favor no seleccionar los criterios de impacto(Afectación Económica o presupuestal y Pérdida Reputacional)",J13) -> El riesgo afecta la imagen de la entidad internamente, de conocimiento general, nivel interno, de junta dircetiva y accionistas y/o de provedores | L13: Bajo | N13: Bajo | O13: 1 | P13: El Jefe de la Oficina de Control Interno realiza seguimiento trimestral al cumplimiento del Plan Anual de Auditorias, en caso de no cumplimiento se lleva reporte o informes al Comité Institucional de Coordinación de Control Interno, para que se tomen las acciones correspondientes | Q13: =IF(OR(R13="Preventivo",R13="Detectivo"),"Probabilidad",IF(R13="Correctivo","Impacto","")) -> Probabilidad | R13: Preventivo | S13: Manual | T13: =IF(AND(R13="Preventivo",S13="Automático"),"50%",IF(AND(R13="Preventivo",S13="Manual"),"40%",IF(AND(R13="Detectivo",S13="Automático"),"40%",IF(AND(R13="Detectivo",S13="Manual"),"30%",IF(AND(R13="Correctivo",S13="Automático"),"35%",IF(AND(R13="Correctivo",S13="Manual"),"25%","")))))) -> 40% | U13: Documentado | V13: Aleatoria | W13: Con Registro | X13: =IFERROR(IF(Q13="Probabilidad",(I13-(+I13*T13)),IF(Q13="Impacto",I13,"")),"") -> 0.36 | Y13: =IFERROR(IF(X13="","",IF(X13<=0.2,"Muy Baja",IF(X13<=0.4,"Baja",IF(X13<=0.6,"Media",IF(X13<=0.8,"Alta","Muy Alta"))))),"") -> Baja | Z13: =+X13 -> 0.36 | AA13: =IFERROR(IF(AB13="","",IF(AB13<=0.2,"Leve",IF(AB13<=0.4,"Menor",IF(AB13<=0.6,"Moderado",IF(AB13<=0.8,"Mayor","Catastrófico"))))),"") -> Leve | AB13: =IFERROR(IF(Q13="Impacto",(M13-(+M13*T13)),IF(Q13="Probabilidad",M13,"")),"") -> 0 | AC13: =IFERROR(IF(OR(AND(Y13="Muy Baja",AA13="Leve"),AND(Y13="Muy Baja",AA13="Menor"),AND(Y13="Baja",AA13="Leve")),"Bajo",IF(OR(AND(Y13="Muy baja",AA13="Moderado"),AND(Y13="Baja",AA13="Menor"),AND(Y13="Baja",AA13="Moderado"),AND(Y13="Media",AA13="Leve"),AND(Y13="Media",AA13="Menor"),AND(Y13="Media",AA13="Moderado"),AND(Y13="Alta",AA13="Leve"),AND(Y13="Alta",AA13="Menor")),"Moderado",IF(OR(AND(Y13="Muy Baja",AA13="Mayor"),AND(Y13="Baja",AA13="Mayor"),AND(Y13="Media",AA13="Mayor"),AND(Y13="Alta",AA13="Moderado"),AND(Y13="Alta",AA13="Mayor"),AND(Y13="Muy Alta",AA13="Leve"),AND(Y13="Muy Alta",AA13="Menor"),AND(Y13="Muy Alta",AA13="Moderado"),AND(Y13="Muy Alta",AA13="Mayor")),"Alto",IF(OR(AND(Y13="Muy Baja",AA13="Catastrófico"),AND(Y13="Baja",AA13="Catastrófico"),AND(Y13="Media",AA13="Catastrófico"),AND(Y13="Alta",AA13="Catastrófico"),AND(Y13="Muy Alta",AA13="Catastrófico")),"Extremo","")))),"") -> Bajo | AD13: Reducir (mitigar) | AE13: Realizar seguimiento cuatrimestral al cumplimiento de los términos establecidos para la auditoria interna elaborados y aprobados en el cronograma anual, por parte del Comité Institucional de Coordinación de Control Interno de la presente vigencia. | AF13: Control Interno | AG13: CUATRIMESTRAL
K14: =IF(NOT(ISERROR(MATCH(J14,_xlfn.ANCHORARRAY(E19),0))),I21&"Por favor no seleccionar los criterios de impacto",J14) -> 0 | O14: 2 | P14: El jefe de la Oficina de Control Interno, realiza seguimiento cuatrimestral a la presentación de los informes a los auditados, establecidos en la carta plan de auditoría interna, con el fin de asegurar su cumplimiento en las fechas establecidas. | Q14: =IF(OR(R14="Preventivo",R14="Detectivo"),"Probabilidad",IF(R14="Correctivo","Impacto","")) -> Probabilidad | R14: Preventivo | S14: Manual | T14: =IF(AND(R14="Preventivo",S14="Automático"),"50%",IF(AND(R14="Preventivo",S14="Manual"),"40%",IF(AND(R14="Detectivo",S14="Automático"),"40%",IF(AND(R14="Detectivo",S14="Manual"),"30%",IF(AND(R14="Correctivo",S14="Automático"),"35%",IF(AND(R14="Correctivo",S14="Manual"),"25%","")))))) -> 40% | U14: Sin Documentar | V14: Continua | W14: Sin Registro | X14: =IFERROR(IF(AND(Q13="Probabilidad",Q14="Probabilidad"),(Z13-(+Z13*T14)),IF(Q14="Probabilidad",(I13-(+I13*T14)),IF(Q14="Impacto",Z13,""))),"") -> 0.216 | Z14: =+X14 -> 0.216 | AB14: =IFERROR(IF(AND(Q13="Impacto",Q14="Impacto"),(AB7-(+AB7*T14)),IF(Q14="Impacto",(#REF!-(+#REF!*T14)),IF(Q14="Probabilidad",AB7,""))),"") -> 0 | AD14: Reducir (mitigar) | AE14: Realizar seguimiento a la presentación de los informes a los auditados, en carpeta física verificando la radicación y las fechas acordadas con los auditados. | AF14: Control Interno | AG14: CUATRIMESTRAL
K15: =IF(NOT(ISERROR(MATCH(J15,_xlfn.ANCHORARRAY(E20),0))),I22&"Por favor no seleccionar los criterios de impacto",J15) -> 0 | O15: 3 | P15: El jefe de Control interno lleva propuesta al comité de Control Interno sobre el ajuste del Plan de Auditorias, la situacion que se presento y explicar el porque se debera modificar el plan de Auditorias para que de esta forma se apruebe el nuevo plan . | Q15: =IF(OR(R15="Preventivo",R15="Detectivo"),"Probabilidad",IF(R15="Correctivo","Impacto","")) -> Probabilidad | R15: Preventivo | S15: Manual | T15: =IF(AND(R15="Preventivo",S15="Automático"),"50%",IF(AND(R15="Preventivo",S15="Manual"),"40%",IF(AND(R15="Detectivo",S15="Automático"),"40%",IF(AND(R15="Detectivo",S15="Manual"),"30%",IF(AND(R15="Correctivo",S15="Automático"),"35%",IF(AND(R15="Correctivo",S15="Manual"),"25%","")))))) -> 40% | U15: Sin Documentar | V15: Continua | W15: Sin Registro | X15: =IFERROR(IF(AND(Q14="Probabilidad",Q15="Probabilidad"),(Z14-(+Z14*T15)),IF(Q15="Probabilidad",(I14-(+I14*T15)),IF(Q15="Impacto",Z14,""))),"") -> 0.1296 | Z15: =+X15 -> 0.1296 | AB15: =IFERROR(IF(AND(Q14="Impacto",Q15="Impacto"),(AB8-(+AB8*T15)),IF(Q15="Impacto",(#REF!-(+#REF!*T15)),IF(Q15="Probabilidad",AB8,""))),"") -> 0 | AD15: Reducir (mitigar) | AE15: Rendir informe al Comité Institucional de Coordinación de Control sobre los cambios en el cronograma anual de auditorías internas, con su respectiva sustentación de cambio y nueva propuesta. | AF15: Control Interno | AG15: CUATRIMESTRAL
K16: =IF(NOT(ISERROR(MATCH(J16,_xlfn.ANCHORARRAY(E21),0))),I23&"Por favor no seleccionar los criterios de impacto",J16) -> 0 | X16: =IFERROR(IF(AND(Q15="Probabilidad",Q16="Probabilidad"),(Z15-(+Z15*T16)),IF(AND(Q15="Impacto",Q16="Probabilidad"),(Z14-(+Z14*T16)),IF(Q16="Impacto",Z15,""))),"")
K17: =IF(NOT(ISERROR(MATCH(J17,_xlfn.ANCHORARRAY(E22),0))),I24&"Por favor no seleccionar los criterios de impacto",J17) -> 0 | X17: =IFERROR(IF(AND(Q16="Probabilidad",Q17="Probabilidad"),(Z16-(+Z16*T17)),IF(AND(Q16="Impacto",Q17="Probabilidad"),(Z15-(+Z15*T17)),IF(Q17="Impacto",Z16,""))),"")
K18: =IF(NOT(ISERROR(MATCH(J18,_xlfn.ANCHORARRAY(E23),0))),I25&"Por favor no seleccionar los criterios de impacto",J18) -> 0 | X18: =IFERROR(IF(AND(Q17="Probabilidad",Q18="Probabilidad"),(Z17-(+Z17*T18)),IF(AND(Q17="Impacto",Q18="Probabilidad"),(Z16-(+Z16*T18)),IF(Q18="Impacto",Z17,""))),"")
B19: *Nota: La columna referencia se sugiere para mantener el consecutivo de riesgos, así el riesgo salga del mapa no existirá otro riesgo con el mismo número. Una entidad puede ir en el riesgo 150 pero tener 70 riesgos, lo que permite llevar una traza de los riesgos. Esta información la debe administrar la Oficina Asesora de Planeación o Gerencia de Riesgos.
B21: Fuente: Adaptado de Curso Riesgo Operativo Universidad del Rosario por Dirección de Gestión y Desempeño Institucional de Función Pública, 2020.

Sheet EJEMPLOS
A1: RECURSOS FISICOS Y TECNOLOGICOS
A3: 1 | B3: Económico | C3: multa y sanción del ente regulador | D3: manejo de inventarios de la entidad fuera de los lineamientos procedimientales y normativos | E3: Posibilidad de afectación económica por multa y sanción del ente regulador debido al manejo de iventarios de la entidad fuera de los lineamientos procedimientales y normativos | F3: Ejecucion y Administracion de procesos | G3: 12 | H3: Baja | I3: 0.4 | J3: Entre 10 y 50 SMLMV | K3: Entre 10 y 50 SMLMV | L3: Menor | M3: 0.4 | N3: Moderado | O3: 1 | P3: El tecnico, profesional , contratista efectua mensualmente la actualizacion de la carpeta compartida de los movimientos de ingresos, traslados y egresos de almacen dejando como evidencia los soportes respectivos.
K4: 0 | O4: 2 | P4: El profesional universitario efectua seguimiento mensual de verificacion y/o convalidacion de los movimientos de almacen por cada rubro contable con el detallado de inventario de bienes y el profesional especializado reviza y convalida la informacion dejando como evidencia los movimientos de inventarios.
K5: 0 | O5: 3
K6: 0 | O6: 4
K7: 0 | O7: 5
K8: 0 | O8: 6
A9: 2 | B9: Reputacional | C9: investigaciones de entes reguladores, quejas o requerimientos de servidores y usuarios | D9: realización de mantenimientos preventivos y correctivos en la infraestructura fuera de los tiempos y requerimientos normativos y procedimentales | E9: Posibilidad de afectación reputacional por investigaciones de entes reguladores, quejas o requerimientos de servidores y usuarios debido a la realización de mantenimientos preventivos y correctivos en la infraestructura fuera de los tiempos y requerimientos normativos y procedimentales | F9: Ejecucion y Administracion de procesos | G9: 19 | H9: Baja | I9: 0.4 | J9: El riesgo afecta la imagen de la entidad con algunos usuarios de relevancia frente al logro de los objetivos | K9: El riesgo afecta la imagen de la entidad con algunos usuarios de relevancia frente al logro de los objetivos | L9: Moderado | M9: 0.6 | N9: Moderado | O9: 1 | P9: El profesional del proceso identifica las necesidades y verfica semestralmente el cumplimiento del cronograma definido a través de la matriz de necesidades de infraestructura, dejando como evidencia el seguimiento semestral
K10: 0 | O10: 2 | P10: El Subdirector Administrativo deberá realizar un contrato de prestación de servicios de mantenimiento preventivo y correctivo con empresas que cuenten con capacidad técnica y experiencia suficiente en este tipo de actividades, dejando establecidos los requisitos en los pliegos de condiciones de los procesos de selección
K11: 0 | O11: 3 | P11: El Subdirector Administrativo debe contratar una firma interventora experta que realice el seguimiento técnico, jurídico, ambiental y financiero a las actividades a realizar por el contratista de mantenimiento locativo, quien presenta mensualmente como registro los informes de ejecución y gestión
K12: 0 | O12: 4
K13: 0 | O13: 5
K14: 0 | O14: 6
A15: 4 | B15: Reputacional | C15: perdida de imagen de usuarios internos, externos y directivos de la SDM | D15: prestación de los servicios generales y administrativos fuera de las necesidades requeridas. | E15: Posibilidad de afectación reputacional por perdida de imagen de usuarios internos, externos y directivos de la SDM, por la prestación de los servicios generales y administrativos fuera de las necesidades requeridas. | F15: Ejecucion y Administracion de procesos | G15: 9 | H15: Baja | I15: 0.4 | J15: El riesgo afecta la imagen de la entidad con algunos usuarios de relevancia frente al logro de los objetivos | K15: El riesgo afecta la imagen de la entidad con algunos usuarios de relevancia frente al logro de los objetivos | L15: Moderado | M15: 0.6 | N15: Moderado | O15: 1 | P15: El profesional del area hará seguimiento anual al tablero de control con semaforos de alertas que permira identificar las fechas de los vencimientos de los contratos y el flujo de proceso de los docuemntos en caso de adiciones, prorrogas y suscripcion de nuevos contratos, como evidencias se aportara el seguimiento del tablero de control.
K16: 0 | O16: 2
K17: 0 | O17: 3
K18: 0 | O18: 4
K19: 0 | O19: 5
K20: 0 | O20: 6
A23: GESTIÓN DOCUMENTAL
B26: Reputacional | C26: sanciones de la contraloria, archivo departanmentaly quejas de ususarios internos y externos | D26: ejecución del sistema de gestión documental fuera de los requerimiento normativos y procedimientales | E26: posibilidad de afectación reputacional por sanciones del archivo departamental y quejas de ususarios internos y externos debido a la ejecución del sistema de gestión documental fuera de los requerimiento normativos y procedimientales | F26: Ejecucion y Administracion de procesos | G26: 12 | H26: Baja | I26: 0.4 | J26: El riesgo afecta la imagen de de la entidad con efecto publicitario sostenido a nivel de sector administrativo, nivel departamental o municipal | K26: El riesgo afecta la imagen de de la entidad con efecto publicitario sostenido a nivel de sector administrativo, nivel departamental o municipal | L26: Mayor | M26: 0.8 | N26: Alto | O26: 1 | P26: El profesional debe asegurar la actualización y/o creación mensual de los instrumentos archivísticos de la Entidad dejando como evidencia cronograma e instrumentos actualizados
K27: 0 | O27: 2 | P27: El profesional del área deberá presentar los avances de la gestión documental en dos sesiones de Comité Interno de Archivo en el año, dejando como evidencia acta del comité
K28: 0 | O28: 3 | P28: El profesional del proceso verifica trimestralmente el cumplimiento de las transferencias documentales y las actividades contenidas en el PINAR dejando como evidencia las actas de transferencias primarias- suscritas.
K29: 0 | O29: 4 | P29: El supervisor del contrato hace segimiento mensual de los documentos del proceso, las sanciones y/o consecuencias del incumplimiento de alguna o algunas de las obligaciones contractuales asumidas por el contratista del contrato de almacenamiento y custodia, así como del arrendamiento de la bodega dejando como evidencia actas de seguimiento al contrato y compromisos allí pactados.
K30: 0 | O30: 5 | P30: El Subdirector administrativio hará seguimiento mensual al plan de contingencia para garantizar la continuidad del Sistema de Información Orfeo en caso de indisponibilidad
K31: 0 | O31: 6
A34: CONTROL INTERNO
A36: 1 | B36: Reputacional | C36: sanciones administrativas por entes gubernamentales | D36: presentación de informes de Ley,como producto de seguimientos fuera la normatividad vigente. | E36: Posibilidad de afectación reputacional por sanciones administrativas por entes gubernamentales debido a la presentación de informes de Ley,como producto de seguimientos fuera la normatividad vigente. | F36: Ejecucion y Administracion de procesos | G36: 39 | H36: Media | I36: 0.6 | J36: El riesgo afecta la imagen de la entidad con algunos usuarios de relevancia frente al logro de los objetivos | K36: El riesgo afecta la imagen de la entidad con algunos usuarios de relevancia frente al logro de los objetivos | L36: Moderado | M36: 0.6 | N36: Moderado | O36: 1 | P36: Los profesionales de control interno realizan mensualmente reuniones de seguimiento y autoevaluación del PAAI, a través de la verificación de la ejecución de actividades del mes en curso y las actividades programadas para el mes siguiente, teniendo como resultado el registro de actas de seguimiento.
K37: 0 | O37: 2 | P37: Jefe de la Oficina de Control Interno presenta en el CICI las fechas establecidas para la presentación de los informes de ley , con el fin de tomar acciones necesarias para cumplir con los lineamientos normativos.
K38: 0 | O38: 3
K39: 0 | O39: 4
K40: 0 | O40: 5
K41: 0 | O41: 6
A45: GESTIÓN FINANCIERA
A47: Referencia | B47: Impacto | C47: Causa Inmediata | D47: Causa Raíz | E47: Descripción del Riesgo | F47: Clasificación del Riesgo | G47: Frecuencia con la cual se realiza la actividad | H47: Probabilidad Inherente | I47: % | J47: Criterios de impacto | K47: Observación de criterio | L47: Impacto Inherente | M47: % | N47: Zona de Riesgo Inherente | O47: No. Control | P47: Descripción del Control
A49: 1 | B49: Reputacional | C49: requerimientos de los usuarios e incumplimiento del procedimiento en terminos procedimentales | D49: Realización del proceso de devolucion o Compensación de Pagos en Exceso y Pagos de lo no Debido por Conceptos no Tributarios y de lo no debido por inconsistencias y desactualizacion del sistema SICON fuera de los terminos procedimentales. | E49: Posibilidad de afectación reputacional por requerimientos de los usuarios e investigaciones administrativas,legales por entes de control por la realizacion del proceso de devoluciones fuera de los terminos procedimentales. | F49: Ejecucion y Administracion de procesos | G49: 670 | H49: Alta | I49: 0.8 | J49: El riesgo afecta la imagen de la entidad con algunos usuarios de relevancia frente al logro de los objetivos | K49: El riesgo afecta la imagen de la entidad con algunos usuarios de relevancia frente al logro de los objetivos | L49: Moderado | M49: 0.6 | N49: Alto | O49: 1 | P49: EL profesional Especializado del proceso verifica permanentemente que las devoluciones cargadas en la carpeta compartida STORAGE_ADMIN cumplan con los requisitos establecidos en el procedimiento dejando como registro la verificacion mediante-orden de devolucion
K50: 0 | O50: 2 | P50: El profesional especializado del proceso y el técnico verifican permanente que las devoluciones registradas en los sistema SICON y BOGDATA cumplan con los requisitos establecidos en el procedimiento dejando registrada la verificación en los aplicativos.
K51: 0 | O51: 3
K52: 0 | O52: 4
K53: 0 | O53: 5
K54: 0 | O54: 6
A55: 2 | B55: Reputacional | C55: Requerimientos de los usuarios e incumplimiento en terminos procedimentales por el no pago a tiempo | D55: Realización del proceso de pagos con incumplmiento de los requistos establecido fuera de los terminos procedimentales. | E55: Posibilidad de afectación reputacional por requerimientos de los usuarios e investigaciones administrativas, legales pon entes de control, debido a realización del proceso de pagos fuera de los requsitos establecidos en los terminos procedimentales. | F55: Ejecucion y Administracion de procesos | G55: 33000 | H55: Muy Alta | I55: 1 | J55: El riesgo afecta la imagen de la entidad con algunos usuarios de relevancia frente al logro de los objetivos | K55: El riesgo afecta la imagen de la entidad con algunos usuarios de relevancia frente al logro de los objetivos | L55: Moderado | M55: 0.6 | N55: Alto | O55: 1 | P55: El tecnico del proceso verifica permanentemente que los documentos cargados en la ventanilla vitual cumplan con los requisitos establecidos en el procedimiento dejando registrado la verificación mediante una plantila numerada en el sistema de radiacación del aplicativo SICAPITAL
K56: 0 | O56: 2 | P56: el profesional del proceso realiza la causación permanentemente del pago de contratitas y proveedores a través del aplicativo SICAPITAL, generando una plantilla de causación
K57: 0 | O57: 3 | P57: El profesional del proceso realiza la revision permenentemente de los documentos radicados por contratista y provedores para que cumplan con los requistos establecidos en el procedimiento dejando registrada la verificacion en el drive
K58: 0 | O58: 4
K59: 0 | O59: 5
K60: 0 | O60: 6
A61: 3 | B61: Reputacional | C61: Requerimientos internos e incumplimiento en terminos procedimentales por la afectacion de la contratacion de la Entidad | D61: realización del proceso de expedicion de certificados de disponibilidad presupuestal fuera de los requisitos procedimentales. | E61: Posibilidad de afectación reputacional por requerimientos internos e investigaciones administrativas, debido a realización del proceso de expedicion de certificados de disponibilidad presupuestal fuera de los requisitos procedimentales. | F61: Ejecucion y Administracion de procesos | G61: 4000 | H61: Alta | I61: 0.8 | J61: El riesgo afecta la imagen de la entidad internamente, de conocimiento general, nivel interno, de junta dircetiva y accionistas y/o de provedores | K61: El riesgo afecta la imagen de la entidad internamente, de conocimiento general, nivel interno, de junta dircetiva y accionistas y/o de provedores | L61: Menor | M61: 0.4 | N61: Moderado | O61: 1 | P61: El profesional Especializado del proceso verifica permanenemte el contenido de la solicitud de CDP efectuada por los ordenadores del gasto , para que cumpla con los requisitos establecidos en el procedimiento dejando registrada la verificacion mediante la expediciendo del CDP
K62: 0 | O62: 2 | P62: El responsable de presupuesto verifica permanentemente los certificados de disponibilidad expedidos, para que cumplam con los requisitos establecidos en el procedimiento dejando como registro los CDP firmados los cuales descarga en una carpeta compartida drive , para disposicion de los solicitandes
K63: 0 | O63: 3
K64: 0 | O64: 4
K65: 0 | O65: 5
K66: 0 | O66: 6
A67: 4 | B67: Reputacional | C67: Requerimientos internos e incumplimiento en terminos procedimentales por la afectacion de la contratacion de la Entidad. | D67: realización del proceso de expedicion de certificados de registros presupuestales fuera de los requisitos establecidos en los terminos procedimentales. | E67: Posibilidad de afectación reputacional por requerimientos internos e investigaciones administrativas, debido a realización del proceso de expedicion de certificados de registros presupuestales fuera de los requisitos establecidos en los terminos procedimentales. | F67: Ejecucion y Administracion de procesos | G67: 4000 | H67: Alta | I67: 0.8 | J67: El riesgo afecta la imagen de la entidad internamente, de conocimiento general, nivel interno, de junta dircetiva y accionistas y/o de provedores | K67: El riesgo afecta la imagen de la entidad internamente, de conocimiento general, nivel interno, de junta dircetiva y accionistas y/o de provedores | L67: Menor | M67: 0.4 | N67: Moderado | O67: 1 | P67: El profesional Especializado del proceso verifica permanentemente, los contratos, actos Adminitrativo, para que cumpla con los requisitos establecidos en el procedimiento dejando registrada la verificacion mediante la expedicion del CRP.en el aplicativo BOGDATA
K68: 0 | O68: 2 | P68: El responsable de presupuesto verifica permanentemente los certificados de registros presupuestal expedidos, para que cumplam con los requisitos establecidos en el procedimiento dejando como registro los CRP firmados los cuales descarga en una carpeta compartida drive , para disposicion de los solicitandes
K69: 0 | O69: 3
K70: 0 | O70: 4
K71: 0 | O71: 5
K72: 0 | O72: 6
A73: 5 | B73: Reputacional | C73: Requerimientos internos y externo e incumplimiento en terminos procedimentales por la afectacion de la informacion contable de la Entidad | D73: entrega de estados contables fuera de las fechas establecidas y de los terminos procedimientales | E73: Posibilidad de afectación reputacional por requerimientos internos externo e investigaciones administrativas, disciplinarias ,fiscales y penales debido a la entrega de estados contables fuera de las fechas establecidas y de los terminos procedimientales | F73: Ejecucion y Administracion de procesos | G73: 12 | H73: Baja | I73: 0.4 | J73: El riesgo afecta la imagen de la entidad internamente, de conocimiento general, nivel interno, de junta dircetiva y accionistas y/o de provedores | K73: El riesgo afecta la imagen de la entidad internamente, de conocimiento general, nivel interno, de junta dircetiva y accionistas y/o de provedores | L73: Menor | M73: 0.4 | N73: Moderado | O73: 1 | P73: El profesional Epecializado del proceso verifica permanentemente la informacion registrada, para que cumpla con los requisitos establecidos en el procedimiento dejando registrada la verificacion mediante los formatos anexos.
K74: 0 | O74: 2 | P74: El profesional Especializado( Contador) del Proceso, el Director(a) Administrativo y Financiero y el Secretario(a) Distrital de Movilidad verifican la informacion de los estados contable que cumpla con los requisitos establecidos en el procedimiento dejando registrada la verificacion mediante sus firmas en los formatos de los estados contables de la SDM.
K75: 0 | O75: 3
K76: 0 | O76: 4
K77: 0 | O77: 5
K78: 0 | O78: 6
A82: GESTIÓN JURIDICA
A84: Referencia | B84: Impacto | C84: Causa Inmediata | D84: Causa Raíz | E84: Descripción del Riesgo | F84: Clasificación del Riesgo | G84: Frecuencia con la cual se realiza la actividad | H84: Probabilidad Inherente | I84: % | J84: Criterios de impacto | K84: Observación de criterio | L84: Impacto Inherente | M84: % | N84: Zona de Riesgo Inherente | O84: No. Control | P84: Descripción del Control
A86: 1 | B86: Reputacional | C86: investigaciones administrativas, fiscales y judiciales | D86: expedición de actos administrativos fuera de los requisitos legales y procedimentales establecidos en la normatividad. | E86: Posibilidad de afectación reputacional por investigaciones administrativas, fiscales y judiciales,asi como,requerimientos de los usuarios debido a la expedición de actos administrativos fuera de los requisitos legales y procedimentales establecidos en la normatividad. | F86: Ejecucion y Administracion de procesos | G86: 84 | H86: Media | I86: 0.6 | J86: El riesgo afecta la imagen de de la entidad con efecto publicitario sostenido a nivel de sector administrativo, nivel departamental o municipal | K86: El riesgo afecta la imagen de de la entidad con efecto publicitario sostenido a nivel de sector administrativo, nivel departamental o municipal | L86: Mayor | M86: 0.8 | N86: Alto | O86: 1 | P86: El jefe de area realiza permanentemente la revisiòn de los proyectos de actos administrativos que son proyectados o revisados por los profesionales de la Direccion con el fin de que cumplan los requisitos establecidos en la Norma,a traves de los procedimientos y las normas aplicables a cada caso particular;los actos administrativos de caracter general seran publicados en la Pagina web y Intranet, a traves de la Matriz de cumplimiento Legal.
K87: 0 | O87: 2 | P87: El profesional de la Direcciòn de Nomatividad y conceptos realiza permanentemente la publicacion de los acto administrativo para observaciones, opiniones o sugerencias,en la pagina web de la entidad donde queda el registro correspondiente de la Publicacion.
K88: 0 | O88: 3 | P88: El profesional del area efectuara cada vez que se requiera las actualizaciones al instructivo de Normatividad y Conceptos en la intranet, quedando el registro de las actualizaciones en el control de cambios del documento.
K89: 0 | O89: 4
K90: 0 | O90: 5
K91: 0 | O91: 6
A92: 2 | B92: Económico y Reputacional | C92: sancion del ente correspondiente | D92: inadecuada gestion del proceso administrativo y de defensa | E92: Posibilidad de afectacion ecomica y reputacional por sancion del ente correspondiente, debido a la gestion del proceso administrativo y de defensa fuera de los terminos legales establecidos. | F92: Ejecucion y Administracion de procesos | G92: 7000 | H92: Muy Alta | I92: 1 | J92: Afectación menor a 10 SMLMV . | K92: Afectación menor a 10 SMLMV . | L92: Leve | M92: 0.2 | N92: Alto | O92: 1 | P92: El profesional de la Direccion de Representacion judicial permanentemente analiza,evalua y realiza seguimiento a la gestion de defensa y los procesos activos,a traves de bases de datos y registros de procesos en el sistema Siprojweb.
K93: 0 | O93: 2 | P93: El comité de conciliacion de la Direccion de Representacion Judicial realizaran seguimiento trimestral a las politicas de prevencion del daño antijurico a traves de los informes que presenta las areas .
K94: 0 | O94: 3 | P94: El jefe area realiza seguimiento permanente a la gestion adecuada de los procesos a cargo de los profesionales de la Direccion de respresentacion Judicial
K95: 0 | O95: 4
K96: 0 | O96: 5
K97: 0 | O97: 6
A98: 3 | B98: Reputacional | C98: perdida de imagen institucional ante la comunidad | D98: consecusión de contratos sin el lleno de los requisitos contemplados en la norma | E98: Posibilidad de afectación reputacional por perdida de imagen institucional ante la comunidad, debido a la consecusión de contratos sin el lleno de los requisitos contemplados en la norma. | F98: Ejecucion y Administracion de procesos | G98: 2020 | H98: Alta | I98: 0.8 | J98: El riesgo afecta la imagen de de la entidad con efecto publicitario sostenido a nivel de sector administrativo, nivel departamental o municipal | K98: El riesgo afecta la imagen de de la entidad con efecto publicitario sostenido a nivel de sector administrativo, nivel departamental o municipal | L98: Mayor | M98: 0.8 | N98: Alto | O98: 1 | P98: El profesional de contratación verifica PERMANENTE, que la información suministrada por el posible proveedor o contratista, corresponda a los requisitos establecidos en el estudio previo y la norma aplicable según el proceso de seleccion empleado. Esta verificación se realiza a través de la lista de chequeo y los requisitos habilitantes establecidos en el pliego de condiciones, verificando los documentos a travez de las plataformas destinadas para tal fin. los contratos que cumplen los requisitos, continúan con el proceso contractual a traves de los sistemas de información de contratación (SECOP).
K99: 0 | O99: 2 | P99: El profesional de contratacion con el rol de revisor y la Directora de Contratación verifican permanentemente en el sistema de información de contratación (SECOP) la información registrada por el profesional asignado y aprueba el proceso para firma del ordenador del gasto. En el sistema de información queda el registro correspondient; en caso de encontrar inconsistencias o no concordancias , devuelve el proceso al profesional de contratos asignado.
K100: 0 | O100: 3
K101: 0 | O101: 4
K102: 0 | O102: 5
K103: 0 | O103: 6
A104: 4 | B104: Económico y Reputacional | C104: multa y sancion del ente regulador | D104: debido a adquisición de bienes y servicios sin identificar la necesidad real. | E104: Posibilidad de afectación económica y reputacional por multa y sanción del ente regulador, debido a adquisición de bienes y servicios sin identificar la necesidad real | F104: Ejecucion y Administracion de procesos | G104: 2020 | H104: Alta | I104: 0.8 | J104: El riesgo afecta la imagen de de la entidad con efecto publicitario sostenido a nivel de sector administrativo, nivel departamental o municipal | K104: El riesgo afecta la imagen de de la entidad con efecto publicitario sostenido a nivel de sector administrativo, nivel departamental o municipal | L104: Mayor | M104: 0.8 | N104: Alto | O104: 1 | P104: El profesional de la Direccion de contratacion verifica permanente que los estudios previos,prepliegos y pliegos de condiciones corresponda a la necesidad establecida por el area solicitante del contrato a traves de una lista de chequeo donde estan los requisitos de la informacion solicitada y la revisa con la informacion digital aportada por el ordenador del gasto,una vez aprobados seran cargados en secop.
K105: 0 | O105: 2 | P105: el jefe del área de contratos verifica en el sistema de información de contratación la información registrada por el profesional asignado y aprueba el proceso para firma del ordenador del gasto, en el sistema de información queda el registro correspondiente, en caso de encontrar inconsistencias , devuelve el proceso al profesional de contratos asignado
K106: 0 | O106: 3
K107: 0 | O107: 4
K108: 0 | O108: 5
K109: 0 | O109: 6
A110: 5 | B110: Económico y Reputacional | C110: multa y sancion del ente regulador | D110: liquidacion de contratos fuera de los terminos normativos. | E110: Posibilidad de afectación económica y reputacional por multa y sancion del ente regulador,debido a la liquidacion de contratos fuera de los terminos normativos. | F110: Ejecucion y Administracion de procesos | G110: 928 | H110: Alta | I110: 0.8 | J110: Entre 100 y 500 SMLMV | K110: Entre 100 y 500 SMLMV | L110: Mayor | M110: 0.8 | N110: Alto | O110: 1 | P110: El jefe de area hara seguimiento permanente a los procesos que requieran liquidcion y remitira mediante circular o memorando a los ordenadores del gasto solicitud para el envio de los documentos necesarios para tal fin en los terminos estabecidos por el proceso.
K111: 0 | O111: 2 | P111: El jefe de area realiza seguimiento PERMANENTE al profesional designado por la direccion para el estudio y apoyo de la liquidación del contrato , atraves de una alerta que se remite por correo electronico.
K112: 0 | O112: 3
K113: 0 | O113: 4
K114: 0 | O114: 5
K115: 0 | O115: 6
A116: 6 | B116: Económico y Reputacional | C116: multa y sancion del ente regulador | D116: inicio del proceso administrativo sancionatorio fuera de los terminos establecidos por la norma o sin el acompañamiento en el desarrollo del proceso. | E116: Posible afectación económica y reputacional por multa y sancion del ente regulador, debido al inicio del proceso administrativo sancionatorio fuera de los terminos establecidos por la norma o sin el acompañamiento en el desarrollo del proceso. | F116: Ejecucion y Administracion de procesos | G116: 18 | H116: Baja | I116: 0.4 | J116: Entre 100 y 500 SMLMV | K116: Entre 100 y 500 SMLMV | L116: Mayor | M116: 0.8 | N116: Alto | O116: 1 | P116: El pofesional de la Direccion de Contratacion verifica permanentemente que los documentos aportados por el ordenador del gasto para el inicio del proceso sancionatorio corresponda con los lineamientos establecidos en el procedimiento sancionatorio ; si cumple o no cumple los requisitos sera informado mediante correo electronico .
K117: 0 | O117: 2
K118: 0 | O118: 3
...

Sheet Matriz Calor Inherente
B2: Matriz de Calor Inherente | J2: Impacto
B6: Probabilidad | E6: Muy Alta 100% | J6: =IF(AND('Mapa final'!$H$13="Muy Alta",'Mapa final'!$L$13="Leve"),CONCATENATE("R",'Mapa final'!$A$13),"") | L6: =IF(AND('Mapa final'!#REF!="Muy Alta",'Mapa final'!#REF!="Leve"),CONCATENATE("R",'Mapa final'!#REF!),"") -> #REF! | N6: =IF(AND('Mapa final'!#REF!="Muy Alta",'Mapa final'!#REF!="Leve"),CONCATENATE("R",'Mapa final'!#REF!),"") -> #REF! | P6: =IF(AND('Mapa final'!$H$13="Muy Alta",'Mapa final'!$L$13="Menor"),CONCATENATE("R",'Mapa final'!$A$13),"") | R6: =IF(AND('Mapa final'!#REF!="Muy Alta",'Mapa final'!#REF!="Menor"),CONCATENATE("R",'Mapa final'!#REF!),"") -> #REF! | T6: =IF(AND('Mapa final'!#REF!="Muy Alta",'Mapa final'!#REF!="Menor"),CONCATENATE("R",'Mapa final'!#REF!),"") -> #REF! | V6: =IF(AND('Mapa final'!$H$13="Muy Alta",'Mapa final'!$L$13="Moderado"),CONCATENATE("R",'Mapa final'!$A$13),"") | X6: =IF(AND('Mapa final'!#REF!="Muy Alta",'Mapa final'!#REF!="Moderado"),CONCATENATE("R",'Mapa final'!#REF!),"") -> #REF! | Z6: =IF(AND('Mapa final'!#REF!="Muy Alta",'Mapa final'!#REF!="Moderado"),CONCATENATE("R",'Mapa final'!#REF!),"") -> #REF! | AB6: =IF(AND('Mapa final'!$H$13="Muy Alta",'Mapa final'!$L$13="Mayor"),CONCATENATE("R",'Mapa final'!$A$13),"") | AD6: =IF(AND('Mapa final'!#REF!="Muy Alta",'Mapa final'!#REF!="Mayor"),CONCATENATE("R",'Mapa final'!#REF!),"") -> #REF! | AF6: =IF(AND('Mapa final'!#REF!="Muy Alta",'Mapa final'!#REF!="Mayor"),CONCATENATE("R",'Mapa final'!#REF!),"") -> #REF! | AH6: =IF(AND('Mapa final'!$H$13="Muy Alta",'Mapa final'!$L$13="Catastrófico"),CONCATENATE("R",'Mapa final'!$A$13),"") | AJ6: =IF(AND('Mapa final'!#REF!="Muy Alta",'Mapa final'!#REF!="Catastrófico"),CONCATENATE("R",'Mapa final'!#REF!),"") -> #REF! | AL6: =IF(AND('Mapa final'!#REF!="Muy Alta",'Mapa final'!#REF!="Catastrófico"),CONCATENATE("R",'Mapa final'!#REF!),"") -> #REF! | AO6: Extremo
J8: =IF(AND('Mapa final'!#REF!="Muy Alta",'Mapa final'!#REF!="Leve"),CONCATENATE("R",'Mapa final'!#REF!),"") -> #REF! | L8: =IF(AND('Mapa final'!#REF!="Muy Alta",'Mapa final'!#REF!="Leve"),CONCATENATE("R",'Mapa final'!#REF!),"") -> #REF! | N8: =IF(AND('Mapa final'!#REF!="Muy Alta",'Mapa final'!#REF!="Leve"),CONCATENATE("R",'Mapa final'!#REF!),"") -> #REF! | P8: =IF(AND('Mapa final'!#REF!="Muy Alta",'Mapa final'!#REF!="Menor"),CONCATENATE("R",'Mapa final'!#REF!),"") -> #REF! | R8: =IF(AND('Mapa final'!#REF!="Muy Alta",'Mapa final'!#REF!="Menor"),CONCATENATE("R",'Mapa final'!#REF!),"") -> #REF! | T8: =IF(AND('Mapa final'!#REF!="Muy Alta",'Mapa final'!#REF!="Menor"),CONCATENATE("R",'Mapa final'!#REF!),"") -> #REF! | V8: =IF(AND('Mapa final'!#REF!="Muy Alta",'Mapa final'!#REF!="Moderado"),CONCATENATE("R",'Mapa final'!#REF!),"") -> #REF! | X8: =IF(AND('Mapa final'!#REF!="Muy Alta",'Mapa final'!#REF!="Moderado"),CONCATENATE("R",'Mapa final'!#REF!),"") -> #REF! | Z8: =IF(AND('Mapa final'!#REF!="Muy Alta",'Mapa final'!#REF!="Moderado"),CONCATENATE("R",'Mapa final'!#REF!),"") -> #REF! | AB8: =IF(AND('Mapa final'!#REF!="Muy Alta",'Mapa final'!#REF!="Mayor"),CONCATENATE("R",'Mapa final'!#REF!),"") -> #REF! | AD8: =IF(AND('Mapa final'!#REF!="Muy Alta",'Mapa final'!#REF!="Mayor"),CONCATENATE("R",'Mapa final'!#REF!),"") -> #REF! | AF8: =IF(AND('Mapa final'!#REF!="Muy Alta",'Mapa final'!#REF!="Mayor"),CONCATENATE("R",'Mapa final'!#REF!),"") -> #REF! | AH8: =IF(AND('Mapa final'!#REF!="Muy Alta",'Mapa final'!#REF!="Catastrófico"),CONCATENATE("R",'Mapa final'!#REF!),"") -> #REF! | AJ8: =IF(AND('Mapa final'!#REF!="Muy Alta",'Mapa final'!#REF!="Catastrófico"),CONCATENATE("R",'Mapa final'!#REF!),"") -> #REF! | AL8: =IF(AND('Mapa final'!#REF!="Muy Alta",'Mapa final'!#REF!="Catastrófico"),CONCATENATE("R",'Mapa final'!#REF!),"") -> #REF!
J10: =IF(AND('Mapa final'!#REF!="Muy Alta",'Mapa final'!#REF!="Leve"),CONCATENATE("R",'Mapa final'!#REF!),"") -> #REF! | L10: =IF(AND('Mapa final'!#REF!="Muy Alta",'Mapa final'!#REF!="Leve"),CONCATENATE("R",'Mapa final'!#REF!),"") -> #REF! | N10: =IF(AND('Mapa final'!#REF!="Muy Alta",'Mapa final'!#REF!="Leve"),CONCATENATE("R",'Mapa final'!#REF!),"") -> #REF! | P10: =IF(AND('Mapa final'!#REF!="Muy Alta",'Mapa final'!#REF!="Menor"),CONCATENATE("R",'Mapa final'!#REF!),"") -> #REF! | R10: =IF(AND('Mapa final'!#REF!="Muy Alta",'Mapa final'!#REF!="Menor"),CONCATENATE("R",'Mapa final'!#REF!),"") -> #REF! | T10: =IF(AND('Mapa final'!#REF!="Muy Alta",'Mapa final'!#REF!="Menor"),CONCATENATE("R",'Mapa final'!#REF!),"") -> #REF! | V10: =IF(AND('Mapa final'!#REF!="Muy Alta",'Mapa final'!#REF!="Moderado"),CONCATENATE("R",'Mapa final'!#REF!),"") -> #REF! | X10: =IF(AND('Mapa final'!#REF!="Muy Alta",'Mapa final'!#REF!="Moderado"),CONCATENATE("R",'Mapa final'!#REF!),"") -> #REF! | Z10: =IF(AND('Mapa final'!#REF!="Muy Alta",'Mapa final'!#REF!="Moderado"),CONCATENATE("R",'Mapa final'!#REF!),"") -> #REF! | AB10: =IF(AND('Mapa final'!#REF!="Muy Alta",'Mapa final'!#REF!="Mayor"),CONCATENATE("R",'Mapa final'!#REF!),"") -> #REF! | AD10: =IF(AND('Mapa final'!#REF!="Muy Alta",'Mapa final'!#REF!="Mayor"),CONCATENATE("R",'Mapa final'!#REF!),"") -> #REF! | AF10: =IF(AND('Mapa final'!#REF!="Muy Alta",'Mapa final'!#REF!="Mayor"),CONCATENATE("R",'Mapa final'!#REF!),"") -> #REF! | AH10: =IF(AND('Mapa final'!#REF!="Muy Alta",'Mapa final'!#REF!="Catastrófico"),CONCATENATE("R",'Mapa final'!#REF!),"") -> #REF! | AJ10: =IF(AND('Mapa final'!#REF!="Muy Alta",'Mapa final'!#REF!="Catastrófico"),CONCATENATE("R",'Mapa final'!#REF!),"") -> #REF! | AL10: =IF(AND('Mapa final'!#REF!="Muy Alta",'Mapa final'!#REF!="Catastrófico"),CONCATENATE("R",'Mapa final'!#REF!),"") -> #REF!
J12: =IF(AND('Mapa final'!#REF!="Muy Alta",'Mapa final'!#REF!="Leve"),CONCATENATE("R",'Mapa final'!#REF!),"") -> #REF! | L12: =IF(AND('Mapa final'!$H$19="Muy Alta",'Mapa final'!$L$19="Leve"),CONCATENATE("R",'Mapa final'!$A$19),"") | N12: =IF(AND('Mapa final'!$H$25="Muy Alta",'Mapa final'!$L$25="Leve"),CONCATENATE("R",'Mapa final'!$A$25),"") | P12: =IF(AND('Mapa final'!#REF!="Muy Alta",'Mapa final'!#REF!="Menor"),CONCATENATE("R",'Mapa final'!#REF!),"") -> #REF! | R12: =IF(AND('Mapa final'!$H$19="Muy Alta",'Mapa final'!$L$19="Menor"),CONCATENATE("R",'Mapa final'!$A$19),"") | T12: =IF(AND('Mapa final'!$H$25="Muy Alta",'Mapa final'!$L$25="Menor"),CONCATENATE("R",'Mapa final'!$A$25),"") | V12: =IF(AND('Mapa final'!#REF!="Muy Alta",'Mapa final'!#REF!="Moderado"),CONCATENATE("R",'Mapa final'!#REF!),"") -> #REF! | X12: =IF(AND('Mapa final'!$H$19="Muy Alta",'Mapa final'!$L$19="Moderado"),CONCATENATE("R",'Mapa final'!$A$19),"") | Z12: =IF(AND('Mapa final'!$H$25="Muy Alta",'Mapa final'!$L$25="Moderado"),CONCATENATE("R",'Mapa final'!$A$25),"") | AB12: =IF(AND('Mapa final'!#REF!="Muy Alta",'Mapa final'!#REF!="Mayor"),CONCATENATE("R",'Mapa final'!#REF!),"") -> #REF! | AD12: =IF(AND('Mapa final'!$H$19="Muy Alta",'Mapa final'!$L$19="Mayor"),CONCATENATE("R",'Mapa final'!$A$19),"") | AF12: =IF(AND('Mapa final'!$H$25="Muy Alta",'Mapa final'!$L$25="Mayor"),CONCATENATE("R",'Mapa final'!$A$25),"") | AH12: =IF(AND('Mapa final'!#REF!="Muy Alta",'Mapa final'!#REF!="Catastrófico"),CONCATENATE("R",'Mapa final'!#REF!),"") -> #REF! | AJ12: =IF(AND('Mapa final'!$H$19="Muy Alta",'Mapa final'!$L$19="Catastrófico"),CONCATENATE("R",'Mapa final'!$A$19),"") | AL12: =IF(AND('Mapa final'!$H$25="Muy Alta",'Mapa final'!$L$25="Catastrófico"),CONCATENATE("R",'Mapa final'!$A$25),"")
E14: Alta 80% | J14: =IF(AND('Mapa final'!$H$13="Alta",'Mapa final'!$L$13="Leve"),CONCATENATE("R",'Mapa final'!$A$13),"") | L14: =IF(AND('Mapa final'!#REF!="Alta",'Mapa final'!#REF!="Leve"),CONCATENATE("R",'Mapa final'!#REF!),"") -> #REF! | N14: =IF(AND('Mapa final'!#REF!="Alta",'Mapa final'!#REF!="Leve"),CONCATENATE("R",'Mapa final'!#REF!),"") -> #REF! | P14: =IF(AND('Mapa final'!$H$13="Alta",'Mapa final'!$L$13="Menor"),CONCATENATE("R",'Mapa final'!$A$13),"") | R14: =IF(AND('Mapa final'!#REF!="Alta",'Mapa final'!#REF!="Menor"),CONCATENATE("R",'Mapa final'!#REF!),"") -> #REF! | T14: =IF(AND('Mapa final'!#REF!="Alta",'Mapa final'!#REF!="Menor"),CONCATENATE("R",'Mapa final'!#REF!),"") -> #REF! | V14: =IF(AND('Mapa final'!$H$13="Alta",'Mapa final'!$L$13="Moderado"),CONCATENATE("R",'Mapa final'!$A$13),"") | X14: =IF(AND('Mapa final'!#REF!="Alta",'Mapa final'!#REF!="Moderado"),CONCATENATE("R",'Mapa final'!#REF!),"") -> #REF! | Z14: =IF(AND('Mapa final'!#REF!="Alta",'Mapa final'!#REF!="Moderado"),CONCATENATE("R",'Mapa final'!#REF!),"") -> #REF! | AB14: =IF(AND('Mapa final'!$H$13="Alta",'Mapa final'!$L$13="Mayor"),CONCATENATE("R",'Mapa final'!$A$13),"") | AD14: =IF(AND('Mapa final'!#REF!="Alta",'Mapa final'!#REF!="Mayor"),CONCATENATE("R",'Mapa final'!#REF!),"") -> #REF! | AF14: =IF(AND('Mapa final'!#REF!="Alta",'Mapa final'!#REF!="Mayor"),CONCATENATE("R",'Mapa final'!#REF!),"") -> #REF! | AH14: =IF(AND('Mapa final'!$H$13="Alta",'Mapa final'!$L$13="Catastrófico"),CONCATENATE("R",'Mapa final'!$A$13),"") | AJ14: =IF(AND('Mapa final'!#REF!="Alta",'Mapa final'!#REF!="Catastrófico"),CONCATENATE("R",'Mapa final'!#REF!),"") -> #REF! | AL14: =IF(AND('Mapa final'!#REF!="Alta",'Mapa final'!#REF!="Catastrófico"),CONCATENATE("R",'Mapa final'!#REF!),"") -> #REF! | AO14: Alto
J16: =IF(AND('Mapa final'!#REF!="Alta",'Mapa final'!#REF!="Leve"),CONCATENATE("R",'Mapa final'!#REF!),"") -> #REF! | L16: =IF(AND('Mapa final'!#REF!="Alta",'Mapa final'!#REF!="Leve"),CONCATENATE("R",'Mapa final'!#REF!),"") -> #REF! | N16: =IF(AND('Mapa final'!#REF!="Alta",'Mapa final'!#REF!="Leve"),CONCATENATE("R",'Mapa final'!#REF!),"") -> #REF! | P16: =IF(AND('Mapa final'!#REF!="Alta",'Mapa final'!#REF!="Menor"),CONCATENATE("R",'Mapa final'!#REF!),"") -> #REF! | R16: =IF(AND('Mapa final'!#REF!="Alta",'Mapa final'!#REF!="Menor"),CONCATENATE("R",'Mapa final'!#REF!),"") -> #REF! | T16: =IF(AND('Mapa final'!#REF!="Alta",'Mapa final'!#REF!="Menor"),CONCATENATE("R",'Mapa final'!#REF!),"") -> #REF! | V16: =IF(AND('Mapa final'!#REF!="Alta",'Mapa final'!#REF!="Moderado"),CONCATENATE("R",'Mapa final'!#REF!),"") -> #REF! | X16: =IF(AND('Mapa final'!#REF!="Alta",'Mapa final'!#REF!="Moderado"),CONCATENATE("R",'Mapa final'!#REF!),"") -> #REF! | Z16: =IF(AND('Mapa final'!#REF!="Alta",'Mapa final'!#REF!="Moderado"),CONCATENATE("R",'Mapa final'!#REF!),"") -> #REF! | AB16: =IF(AND('Mapa final'!#REF!="Alta",'Mapa final'!#REF!="Mayor"),CONCATENATE("R",'Mapa final'!#REF!),"") -> #REF! | AD16: =IF(AND('Mapa final'!#REF!="Alta",'Mapa final'!#REF!="Mayor"),CONCATENATE("R",'Mapa final'!#REF!),"") -> #REF! | AF16: =IF(AND('Mapa final'!#REF!="Alta",'Mapa final'!#REF!="Mayor"),CONCATENATE("R",'Mapa final'!#REF!),"") -> #REF! | AH16: =IF(AND('Mapa final'!#REF!="Alta",'Mapa final'!#REF!="Catastrófico"),CONCATENATE("R",'Mapa final'!#REF!),"") -> #REF! | AJ16: =IF(AND('Mapa final'!#REF!="Alta",'Mapa final'!#REF!="Catastrófico"),CONCATENATE("R",'Mapa final'!#REF!),"") -> #REF! | AL16: =IF(AND('Mapa final'!#REF!="Alta",'Mapa final'!#REF!="Catastrófico"),CONCATENATE("R",'Mapa final'!#REF!),"") -> #REF!
J18: =IF(AND('Mapa final'!#REF!="Alta",'Mapa final'!#REF!="Leve"),CONCATENATE("R",'Mapa final'!#REF!),"") -> #REF! | L18: =IF(AND('Mapa final'!#REF!="Alta",'Mapa final'!#REF!="Leve"),CONCATENATE("R",'Mapa final'!#REF!),"") -> #REF! | N18: =IF(AND('Mapa final'!#REF!="Alta",'Mapa final'!#REF!="Leve"),CONCATENATE("R",'Mapa final'!#REF!),"") -> #REF! | P18: =IF(AND('Mapa final'!#REF!="Alta",'Mapa final'!#REF!="Menor"),CONCATENATE("R",'Mapa final'!#REF!),"") -> #REF! | R18: =IF(AND('Mapa final'!#REF!="Alta",'Mapa final'!#REF!="Menor"),CONCATENATE("R",'Mapa final'!#REF!),"") -> #REF! | T18: =IF(AND('Mapa final'!#REF!="Alta",'Mapa final'!#REF!="Menor"),CONCATENATE("R",'Mapa final'!#REF!),"") -> #REF! | V18: =IF(AND('Mapa final'!#REF!="Alta",'Mapa final'!#REF!="Moderado"),CONCATENATE("R",'Mapa final'!#REF!),"") -> #REF! | X18: =IF(AND('Mapa final'!#REF!="Alta",'Mapa final'!#REF!="Moderado"),CONCATENATE("R",'Mapa final'!#REF!),"") -> #REF! | Z18: =IF(AND('Mapa final'!#REF!="Alta",'Mapa final'!#REF!="Moderado"),CONCATENATE("R",'Mapa final'!#REF!),"") -> #REF! | AB18: =IF(AND('Mapa final'!#REF!="Alta",'Mapa final'!#REF!="Mayor"),CONCATENATE("R",'Mapa final'!#REF!),"") -> #REF! | AD18: =IF(AND('Mapa final'!#REF!="Alta",'Mapa final'!#REF!="Mayor"),CONCATENATE("R",'Mapa final'!#REF!),"") -> #REF! | AF18: =IF(AND('Mapa final'!#REF!="Alta",'Mapa final'!#REF!="Mayor"),CONCATENATE("R",'Mapa final'!#REF!),"") -> #REF! | AH18: =IF(AND('Mapa final'!#REF!="Alta",'Mapa final'!#REF!="Catastrófico"),CONCATENATE("R",'Mapa final'!#REF!),"") -> #REF! | AJ18: =IF(AND('Mapa final'!#REF!="Alta",'Mapa final'!#REF!="Catastrófico"),CONCATENATE("R",'Mapa final'!#REF!),"") -> #REF! | AL18: =IF(AND('Mapa final'!#REF!="Alta",'Mapa final'!#REF!="Catastrófico"),CONCATENATE("R",'Mapa final'!#REF!),"") -> #REF!
J20: =IF(AND('Mapa final'!#REF!="Alta",'Mapa final'!#REF!="Leve"),CONCATENATE("R",'Mapa final'!#REF!),"") -> #REF! | L20: =IF(AND('Mapa final'!$H$19="Alta",'Mapa final'!$L$19="Leve"),CONCATENATE("R",'Mapa final'!$A$19),"") | N20: =IF(AND('Mapa final'!$H$25="Alta",'Mapa final'!$L$25="Leve"),CONCATENATE("R",'Mapa final'!$A$25),"") | P20: =IF(AND('Mapa final'!#REF!="Alta",'Mapa final'!#REF!="Menor"),CONCATENATE("R",'Mapa final'!#REF!),"") -> #REF! | R20: =IF(AND('Mapa final'!$H$19="Alta",'Mapa final'!$L$19="Menor"),CONCATENATE("R",'Mapa final'!$A$19),"") | T20: =IF(AND('Mapa final'!$H$25="Alta",'Mapa final'!$L$25="Menor"),CONCATENATE("R",'Mapa final'!$A$25),"") | V20: =IF(AND('Mapa final'!#REF!="Alta",'Mapa final'!#REF!="Moderado"),CONCATENATE("R",'Mapa final'!#REF!),"") -> #REF! | X20: =IF(AND('Mapa final'!$H$19="Alta",'Mapa final'!$L$19="Moderado"),CONCATENATE("R",'Mapa final'!$A$19),"") | Z20: =IF(AND('Mapa final'!$H$25="Alta",'Mapa final'!$L$25="Moderado"),CONCATENATE("R",'Mapa final'!$A$25),"") | AB20: =IF(AND('Mapa final'!#REF!="Alta",'Mapa final'!#REF!="Mayor"),CONCATENATE("R",'Mapa final'!#REF!),"") -> #REF! | AD20: =IF(AND('Mapa final'!$H$19="Alta",'Mapa final'!$L$19="Mayor"),CONCATENATE("R",'Mapa final'!$A$19),"") | AF20: =IF(AND('Mapa final'!$H$25="Alta",'Mapa final'!$L$25="Mayor"),CONCATENATE("R",'Mapa final'!$A$25),"") | AH20: =IF(AND('Mapa final'!#REF!="Alta",'Mapa final'!#REF!="Catastrófico"),CONCATENATE("R",'Mapa final'!#REF!),"") -> #REF! | AJ20: =IF(AND('Mapa final'!$H$19="Alta",'Mapa final'!$L$19="Catastrófico"),CONCATENATE("R",'Mapa final'!$A$19),"") | AL20: =IF(AND('Mapa final'!$H$25="Alta",'Mapa final'!$L$25="Catastrófico"),CONCATENATE("R",'Mapa final'!$A$25),"")
E22: Media 60% | J22: =IF(AND('Mapa final'!$H$13="Media",'Mapa final'!$L$13="Leve"),CONCATENATE("R",'Mapa final'!$A$13),"") | L22: =IF(AND('Mapa final'!#REF!="Media",'Mapa final'!#REF!="Leve"),CONCATENATE("R",'Mapa final'!#REF!),"") -> #REF! | N22: =IF(AND('Mapa final'!#REF!="Media",'Mapa final'!#REF!="Leve"),CONCATENATE("R",'Mapa final'!#REF!),"") -> #REF! | P22: =IF(AND('Mapa final'!$H$13="Media",'Mapa final'!$L$13="Menor"),CONCATENATE("R",'Mapa final'!$A$13),"") | R22: =IF(AND('Mapa final'!#REF!="Media",'Mapa final'!#REF!="Menor"),CONCATENATE("R",'Mapa final'!#REF!),"") -> #REF! | T22: =IF(AND('Mapa final'!#REF!="Media",'Mapa final'!#REF!="Menor"),CONCATENATE("R",'Mapa final'!#REF!),"") -> #REF! | V22: =IF(AND('Mapa final'!$H$13="Media",'Mapa final'!$L$13="Moderado"),CONCATENATE("R",'Mapa final'!$A$13),"") | X22: =IF(AND('Mapa final'!#REF!="Media",'Mapa final'!#REF!="Moderado"),CONCATENATE("R",'Mapa final'!#REF!),"") -> #REF! | Z22: =IF(AND('Mapa final'!#REF!="Media",'Mapa final'!#REF!="Moderado"),CONCATENATE("R",'Mapa final'!#REF!),"") -> #REF! | AB22: =IF(AND('Mapa final'!$H$13="Media",'Mapa final'!$L$13="Mayor"),CONCATENATE("R",'Mapa final'!$A$13),"") | AD22: =IF(AND('Mapa final'!#REF!="Media",'Mapa final'!#REF!="Mayor"),CONCATENATE("R",'Mapa final'!#REF!),"") -> #REF! | AF22: =IF(AND('Mapa final'!#REF!="Media",'Mapa final'!#REF!="Mayor"),CONCATENATE("R",'Mapa final'!#REF!),"") -> #REF! | AH22: =IF(AND('Mapa final'!$H$13="Media",'Mapa final'!$L$13="Catastrófico"),CONCATENATE("R",'Mapa final'!$A$13),"") | AJ22: =IF(AND('Mapa final'!#REF!="Media",'Mapa final'!#REF!="Catastrófico"),CONCATENATE("R",'Mapa final'!#REF!),"") -> #REF! | AL22: =IF(AND('Mapa final'!#REF!="Media",'Mapa final'!#REF!="Catastrófico"),CONCATENATE("R",'Mapa final'!#REF!),"") -> #REF! | AO22: Moderado
J24: =IF(AND('Mapa final'!#REF!="Media",'Mapa final'!#REF!="Leve"),CONCATENATE("R",'Mapa final'!#REF!),"") -> #REF! | L24: =IF(AND('Mapa final'!#REF!="Media",'Mapa final'!#REF!="Leve"),CONCATENATE("R",'Mapa final'!#REF!),"") -> #REF! | N24: =IF(AND('Mapa final'!#REF!="Media",'Mapa final'!#REF!="Leve"),CONCATENATE("R",'Mapa final'!#REF!),"") -> #REF! | P24: =IF(AND('Mapa final'!#REF!="Media",'Mapa final'!#REF!="Menor"),CONCATENATE("R",'Mapa final'!#REF!),"") -> #REF! | R24: =IF(AND('Mapa final'!#REF!="Media",'Mapa final'!#REF!="Menor"),CONCATENATE("R",'Mapa final'!#REF!),"") -> #REF! | T24: =IF(AND('Mapa final'!#REF!="Media",'Mapa final'!#REF!="Menor"),CONCATENATE("R",'Mapa final'!#REF!),"") -> #REF! | V24: =IF(AND('Mapa final'!#REF!="Media",'Mapa final'!#REF!="Moderado"),CONCATENATE("R",'Mapa final'!#REF!),"") -> #REF! | X24: =IF(AND('Mapa final'!#REF!="Media",'Mapa final'!#REF!="Moderado"),CONCATENATE("R",'Mapa final'!#REF!),"") -> #REF! | Z24: =IF(AND('Mapa final'!#REF!="Media",'Mapa final'!#REF!="Moderado"),CONCATENATE("R",'Mapa final'!#REF!),"") -> #REF! | AB24: =IF(AND('Mapa final'!#REF!="Media",'Mapa final'!#REF!="Mayor"),CONCATENATE("R",'Mapa final'!#REF!),"") -> #REF! | AD24: =IF(AND('Mapa final'!#REF!="Media",'Mapa final'!#REF!="Mayor"),CONCATENATE("R",'Mapa final'!#REF!),"") -> #REF! | AF24: =IF(AND('Mapa final'!#REF!="Media",'Mapa final'!#REF!="Mayor"),CONCATENATE("R",'Mapa final'!#REF!),"") -> #REF! | AH24: =IF(AND('Mapa final'!#REF!="Media",'Mapa final'!#REF!="Catastrófico"),CONCATENATE("R",'Mapa final'!#REF!),"") -> #REF! | AJ24: =IF(AND('Mapa final'!#REF!="Media",'Mapa final'!#REF!="Catastrófico"),CONCATENATE("R",'Mapa final'!#REF!),"") -> #REF! | AL24: =IF(AND('Mapa final'!#REF!="Media",'Mapa final'!#REF!="Catastrófico"),CONCATENATE("R",'Mapa final'!#REF!),"") -> #REF!
J26: =IF(AND('Mapa final'!#REF!="Media",'Mapa final'!#REF!="Leve"),CONCATENATE("R",'Mapa final'!#REF!),"") -> #REF! | L26: =IF(AND('Mapa final'!#REF!="Media",'Mapa final'!#REF!="Leve"),CONCATENATE("R",'Mapa final'!#REF!),"") -> #REF! | N26: =IF(AND('Mapa final'!#REF!="Media",'Mapa final'!#REF!="Leve"),CONCATENATE("R",'Mapa final'!#REF!),"") -> #REF! | P26: =IF(AND('Mapa final'!#REF!="Media",'Mapa final'!#REF!="Menor"),CONCATENATE("R",'Mapa final'!#REF!),"") -> #REF! | R26: =IF(AND('Mapa final'!#REF!="Media",'Mapa final'!#REF!="Menor"),CONCATENATE("R",'Mapa final'!#REF!),"") -> #REF! | T26: =IF(AND('Mapa final'!#REF!="Media",'Mapa final'!#REF!="Menor"),CONCATENATE("R",'Mapa final'!#REF!),"") -> #REF! | V26: =IF(AND('Mapa final'!#REF!="Media",'Mapa final'!#REF!="Moderado"),CONCATENATE("R",'Mapa final'!#REF!),"") -> #REF! | X26: =IF(AND('Mapa final'!#REF!="Media",'Mapa final'!#REF!="Moderado"),CONCATENATE("R",'Mapa final'!#REF!),"") -> #REF! | Z26: =IF(AND('Mapa final'!#REF!="Media",'Mapa final'!#REF!="Moderado"),CONCATENATE("R",'Mapa final'!#REF!),"") -> #REF! | AB26: =IF(AND('Mapa final'!#REF!="Media",'Mapa final'!#REF!="Mayor"),CONCATENATE("R",'Mapa final'!#REF!),"") -> #REF! | AD26: =IF(AND('Mapa final'!#REF!="Media",'Mapa final'!#REF!="Mayor"),CONCATENATE("R",'Mapa final'!#REF!),"") -> #REF! | AF26: =IF(AND('Mapa final'!#REF!="Media",'Mapa final'!#REF!="Mayor"),CONCATENATE("R",'Mapa final'!#REF!),"") -> #REF! | AH26: =IF(AND('Mapa final'!#REF!="Media",'Mapa final'!#REF!="Catastrófico"),CONCATENATE("R",'Mapa final'!#REF!),"") -> #REF! | AJ26: =IF(AND('Mapa final'!#REF!="Media",'Mapa final'!#REF!="Catastrófico"),CONCATENATE("R",'Mapa final'!#REF!),"") -> #REF! | AL26: =IF(AND('Mapa final'!#REF!="Media",'Mapa final'!#REF!="Catastrófico"),CONCATENATE("R",'Mapa final'!#REF!),"") -> #REF!
J28: =IF(AND('Mapa final'!#REF!="Media",'Mapa final'!#REF!="Leve"),CONCATENATE("R",'Mapa final'!#REF!),"") -> #REF! | L28: =IF(AND('Mapa final'!$H$19="Media",'Mapa final'!$L$19="Leve"),CONCATENATE("R",'Mapa final'!$A$19),"") | N28: =IF(AND('Mapa final'!$H$25="Media",'Mapa final'!$L$25="Leve"),CONCATENATE("R",'Mapa final'!$A$25),"") | P28: =IF(AND('Mapa final'!#REF!="Media",'Mapa final'!#REF!="Menor"),CONCATENATE("R",'Mapa final'!#REF!),"") -> #REF! | R28: =IF(AND('Mapa final'!$H$19="Media",'Mapa final'!$L$19="Menor"),CONCATENATE("R",'Mapa final'!$A$19),"") | T28: =IF(AND('Mapa final'!$H$25="Media",'Mapa final'!$L$25="Menor"),CONCATENATE("R",'Mapa final'!$A$25),"") | V28: =IF(AND('Mapa final'!#REF!="Media",'Mapa final'!#REF!="Moderado"),CONCATENATE("R",'Mapa final'!#REF!),"") -> #REF! | X28: =IF(AND('Mapa final'!$H$19="Media",'Mapa final'!$L$19="Moderado"),CONCATENATE("R",'Mapa final'!$A$19),"") | Z28: =IF(AND('Mapa final'!$H$25="Media",'Mapa final'!$L$25="Moderado"),CONCATENATE("R",'Mapa final'!$A$25),"") | AB28: =IF(AND('Mapa final'!#REF!="Media",'Mapa final'!#REF!="Mayor"),CONCATENATE("R",'Mapa final'!#REF!),"") -> #REF! | AD28: =IF(AND('Mapa final'!$H$19="Media",'Mapa final'!$L$19="Mayor"),CONCATENATE("R",'Mapa final'!$A$19),"") | AF28: =IF(AND('Mapa final'!$H$25="Media",'Mapa final'!$L$25="Mayor"),CONCATENATE("R",'Mapa final'!$A$25),"") | AH28: =IF(AND('Mapa final'!#REF!="Media",'Mapa final'!#REF!="Catastrófico"),CONCATENATE("R",'Mapa final'!#REF!),"") -> #REF! | AJ28: =IF(AND('Mapa final'!$H$19="Media",'Mapa final'!$L$19="Catastrófico"),CONCATENATE("R",'Mapa final'!$A$19),"") | AL28: =IF(AND('Mapa final'!$H$25="Media",'Mapa final'!$L$25="Catastrófico"),CONCATENATE("R",'Mapa final'!$A$25),"")
E30: Baja 40% | J30: =IF(AND('Mapa final'!$H$13="Baja",'Mapa final'!$L$13="Leve"),CONCATENATE("R",'Mapa final'!$A$13),"") | L30: =IF(AND('Mapa final'!#REF!="Baja",'Mapa final'!#REF!="Leve"),CONCATENATE("R",'Mapa final'!#REF!),"") -> #REF! | N30: =IF(AND('Mapa final'!#REF!="Baja",'Mapa final'!#REF!="Leve"),CONCATENATE("R",'Mapa final'!#REF!),"") -> #REF! | P30: =IF(AND('Mapa final'!$H$13="Baja",'Mapa final'!$L$13="Menor"),CONCATENATE("R",'Mapa final'!$A$13),"") | R30: =IF(AND('Mapa final'!#REF!="Baja",'Mapa final'!#REF!="Menor"),CONCATENATE("R",'Mapa final'!#REF!),"") -> #REF! | T30: =IF(AND('Mapa final'!#REF!="Baja",'Mapa final'!#REF!="Menor"),CONCATENATE("R",'Mapa final'!#REF!),"") -> #REF! | V30: =IF(AND('Mapa final'!$H$13="Baja",'Mapa final'!$L$13="Moderado"),CONCATENATE("R",'Mapa final'!$A$13),"") | X30: =IF(AND('Mapa final'!#REF!="Baja",'Mapa final'!#REF!="Moderado"),CONCATENATE("R",'Mapa final'!#REF!),"") -> #REF! | Z30: =IF(AND('Mapa final'!#REF!="Baja",'Mapa final'!#REF!="Moderado"),CONCATENATE("R",'Mapa final'!#REF!),"") -> #REF! | AB30: =IF(AND('Mapa final'!$H$13="Baja",'Mapa final'!$L$13="Mayor"),CONCATENATE("R",'Mapa final'!$A$13),"") | AD30: =IF(AND('Mapa final'!#REF!="Baja",'Mapa final'!#REF!="Mayor"),CONCATENATE("R",'Mapa final'!#REF!),"") -> #REF! | AF30: =IF(AND('Mapa final'!#REF!="Baja",'Mapa final'!#REF!="Mayor"),CONCATENATE("R",'Mapa final'!#REF!),"") -> #REF! | AH30: =IF(AND('Mapa final'!$H$13="Baja",'Mapa final'!$L$13="Catastrófico"),CONCATENATE("R",'Mapa final'!$A$13),"") | AJ30: =IF(AND('Mapa final'!#REF!="Baja",'Mapa final'!#REF!="Catastrófico"),CONCATENATE("R",'Mapa final'!#REF!),"") -> #REF! | AL30: =IF(AND('Mapa final'!#REF!="Baja",'Mapa final'!#REF!="Catastrófico"),CONCATENATE("R",'Mapa final'!#REF!),"") -> #REF! | AO30: Bajo
J32: =IF(AND('Mapa final'!#REF!="Baja",'Mapa final'!#REF!="Leve"),CONCATENATE("R",'Mapa final'!#REF!),"") -> #REF! | L32: =IF(AND('Mapa final'!#REF!="Baja",'Mapa final'!#REF!="Leve"),CONCATENATE("R",'Mapa final'!#REF!),"") -> #REF! | N32: =IF(AND('Mapa final'!#REF!="Baja",'Mapa final'!#REF!="Leve"),CONCATENATE("R",'Mapa final'!#REF!),"") -> #REF! | P32: =IF(AND('Mapa final'!#REF!="Baja",'Mapa final'!#REF!="Menor"),CONCATENATE("R",'Mapa final'!#REF!),"") -> #REF! | R32: =IF(AND('Mapa final'!#REF!="Baja",'Mapa final'!#REF!="Menor"),CONCATENATE("R",'Mapa final'!#REF!),"") -> #REF! | T32: =IF(AND('Mapa final'!#REF!="Baja",'Mapa final'!#REF!="Menor"),CONCATENATE("R",'Mapa final'!#REF!),"") -> #REF! | V32: =IF(AND('Mapa final'!#REF!="Baja",'Mapa final'!#REF!="Moderado"),CONCATENATE("R",'Mapa final'!#REF!),"") -> #REF! | X32: =IF(AND('Mapa final'!#REF!="Baja",'Mapa final'!#REF!="Moderado"),CONCATENATE("R",'Mapa final'!#REF!),"") -> #REF! | Z32: =IF(AND('Mapa final'!#REF!="Baja",'Mapa final'!#REF!="Moderado"),CONCATENATE("R",'Mapa final'!#REF!),"") -> #REF! | AB32: =IF(AND('Mapa final'!#REF!="Baja",'Mapa final'!#REF!="Mayor"),CONCATENATE("R",'Mapa final'!#REF!),"") -> #REF! | AD32: =IF(AND('Mapa final'!#REF!="Baja",'Mapa final'!#REF!="Mayor"),CONCATENATE("R",'Mapa final'!#REF!),"") -> #REF! | AF32: =IF(AND('Mapa final'!#REF!="Baja",'Mapa final'!#REF!="Mayor"),CONCATENATE("R",'Mapa final'!#REF!),"") -> #REF! | AH32: =IF(AND('Mapa final'!#REF!="Baja",'Mapa final'!#REF!="Catastrófico"),CONCATENATE("R",'Mapa final'!#REF!),"") -> #REF! | AJ32: =IF(AND('Mapa final'!#REF!="Baja",'Mapa final'!#REF!="Catastrófico"),CONCATENATE("R",'Mapa final'!#REF!),"") -> #REF! | AL32: =IF(AND('Mapa final'!#REF!="Baja",'Mapa final'!#REF!="Catastrófico"),CONCATENATE("R",'Mapa final'!#REF!),"") -> #REF!
J34: =IF(AND('Mapa final'!#REF!="Baja",'Mapa final'!#REF!="Leve"),CONCATENATE("R",'Mapa final'!#REF!),"") -> #REF! | L34: =IF(AND('Mapa final'!#REF!="Baja",'Mapa final'!#REF!="Leve"),CONCATENATE("R",'Mapa final'!#REF!),"") -> #REF! | N34: =IF(AND('Mapa final'!#REF!="Baja",'Mapa final'!#REF!="Leve"),CONCATENATE("R",'Mapa final'!#REF!),"") -> #REF! | P34: =IF(AND('Mapa final'!#REF!="Baja",'Mapa final'!#REF!="Menor"),CONCATENATE("R",'Mapa final'!#REF!),"") -> #REF! | R34: =IF(AND('Mapa final'!#REF!="Baja",'Mapa final'!#REF!="Menor"),CONCATENATE("R",'Mapa final'!#REF!),"") -> #REF! | T34: =IF(AND('Mapa final'!#REF!="Baja",'Mapa final'!#REF!="Menor"),CONCATENATE("R",'Mapa final'!#REF!),"") -> #REF! | V34: =IF(AND('Mapa final'!#REF!="Baja",'Mapa final'!#REF!="Moderado"),CONCATENATE("R",'Mapa final'!#REF!),"") -> #REF! | X34: =IF(AND('Mapa final'!#REF!="Baja",'Mapa final'!#REF!="Moderado"),CONCATENATE("R",'Mapa final'!#REF!),"") -> #REF! | Z34: =IF(AND('Mapa final'!#REF!="Baja",'Mapa final'!#REF!="Moderado"),CONCATENATE("R",'Mapa final'!#REF!),"") -> #REF! | AB34: =IF(AND('Mapa final'!#REF!="Baja",'Mapa final'!#REF!="Mayor"),CONCATENATE("R",'Mapa final'!#REF!),"") -> #REF! | AD34: =IF(AND('Mapa final'!#REF!="Baja",'Mapa final'!#REF!="Mayor"),CONCATENATE("R",'Mapa final'!#REF!),"") -> #REF! | AF34: =IF(AND('Mapa final'!#REF!="Baja",'Mapa final'!#REF!="Mayor"),CONCATENATE("R",'Mapa final'!#REF!),"") -> #REF! | AH34: =IF(AND('Mapa final'!#REF!="Baja",'Mapa final'!#REF!="Catastrófico"),CONCATENATE("R",'Mapa final'!#REF!),"") -> #REF! | AJ34: =IF(AND('Mapa final'!#REF!="Baja",'Mapa final'!#REF!="Catastrófico"),CONCATENATE("R",'Mapa final'!#REF!),"") -> #REF! | AL34: =IF(AND('Mapa final'!#REF!="Baja",'Mapa final'!#REF!="Catastrófico"),CONCATENATE("R",'Mapa final'!#REF!),"") -> #REF!
J36: =IF(AND('Mapa final'!#REF!="Baja",'Mapa final'!#REF!="Leve"),CONCATENATE("R",'Mapa final'!#REF!),"") -> #REF! | L36: =IF(AND('Mapa final'!$H$19="Baja",'Mapa final'!$L$19="Leve"),CONCATENATE("R",'Mapa final'!$A$19),"") | N36: =IF(AND('Mapa final'!$H$25="Baja",'Mapa final'!$L$25="Leve"),CONCATENATE("R",'Mapa final'!$A$25),"") | P36: =IF(AND('Mapa final'!#REF!="Baja",'Mapa final'!#REF!="Menor"),CONCATENATE("R",'Mapa final'!#REF!),"") -> #REF! | R36: =IF(AND('Mapa final'!$H$19="Baja",'Mapa final'!$L$19="Menor"),CONCATENATE("R",'Mapa final'!$A$19),"") | T36: =IF(AND('Mapa final'!$H$25="Baja",'Mapa final'!$L$25="Menor"),CONCATENATE("R",'Mapa final'!$A$25),"") | V36: =IF(AND('Mapa final'!#REF!="Baja",'Mapa final'!#REF!="Moderado"),CONCATENATE("R",'Mapa final'!#REF!),"") -> #REF! | X36: =IF(AND('Mapa final'!$H$19="Baja",'Mapa final'!$L$19="Moderado"),CONCATENATE("R",'Mapa final'!$A$19),"") | Z36: =IF(AND('Mapa final'!$H$25="Baja",'Mapa final'!$L$25="Moderado"),CONCATENATE("R",'Mapa final'!$A$25),"") | AB36: =IF(AND('Mapa final'!#REF!="Baja",'Mapa final'!#REF!="Mayor"),CONCATENATE("R",'Mapa final'!#REF!),"") -> #REF! | AD36: =IF(AND('Mapa final'!$H$19="Baja",'Mapa final'!$L$19="Mayor"),CONCATENATE("R",'Mapa final'!$A$19),"") | AF36: =IF(AND('Mapa final'!$H$25="Baja",'Mapa final'!$L$25="Mayor"),CONCATENATE("R",'Mapa final'!$A$25),"") | AH36: =IF(AND('Mapa final'!#REF!="Baja",'Mapa final'!#REF!="Catastrófico"),CONCATENATE("R",'Mapa final'!#REF!),"") -> #REF! | AJ36: =IF(AND('Mapa final'!$H$19="Baja",'Mapa final'!$L$19="Catastrófico"),CONCATENATE("R",'Mapa final'!$A$19),"") | AL36: =IF(AND('Mapa final'!$H$25="Baja",'Mapa final'!$L$25="Catastrófico"),CONCATENATE("R",'Mapa final'!$A$25),"")
E38: Muy Baja 20% | J38: =IF(AND('Mapa final'!$H$13="Muy Baja",'Mapa final'!$L$13="Leve"),CONCATENATE("R",'Mapa final'!$A$13),"") | L38: =IF(AND('Mapa final'!#REF!="Muy Baja",'Mapa final'!#REF!="Leve"),CONCATENATE("R",'Mapa final'!#REF!),"") -> #REF! | N38: =IF(AND('Mapa final'!#REF!="Muy Baja",'Mapa final'!#REF!="Leve"),CONCATENATE("R",'Mapa final'!#REF!),"") -> #REF! | P38: =IF(AND('Mapa final'!$H$13="Muy Baja",'Mapa final'!$L$13="Menor"),CONCATENATE("R",'Mapa final'!$A$13),"") | R38: =IF(AND('Mapa final'!#REF!="Muy Baja",'Mapa final'!#REF!="Menor"),CONCATENATE("R",'Mapa final'!#REF!),"") -> #REF! | T38: =IF(AND('Mapa final'!#REF!="Muy Baja",'Mapa final'!#REF!="Menor"),CONCATENATE("R",'Mapa final'!#REF!),"") -> #REF! | V38: =IF(AND('Mapa final'!$H$13="Muy Baja",'Mapa final'!$L$13="Moderado"),CONCATENATE("R",'Mapa final'!$A$13),"") | X38: =IF(AND('Mapa final'!#REF!="Muy Baja",'Mapa final'!#REF!="Moderado"),CONCATENATE("R",'Mapa final'!#REF!),"") -> #REF! | Z38: =IF(AND('Mapa final'!#REF!="Muy Baja",'Mapa final'!#REF!="Moderado"),CONCATENATE("R",'Mapa final'!#REF!),"") -> #REF! | AB38: =IF(AND('Mapa final'!$H$13="Muy Baja",'Mapa final'!$L$13="Mayor"),CONCATENATE("R",'Mapa final'!$A$13),"") | AD38: =IF(AND('Mapa final'!#REF!="Muy Baja",'Mapa final'!#REF!="Mayor"),CONCATENATE("R",'Mapa final'!#REF!),"") -> #REF! | AF38: =IF(AND('Mapa final'!#REF!="Muy Baja",'Mapa final'!#REF!="Mayor"),CONCATENATE("R",'Mapa final'!#REF!),"") -> #REF! | AH38: =IF(AND('Mapa final'!$H$13="Muy Baja",'Mapa final'!$L$13="Catastrófico"),CONCATENATE("R",'Mapa final'!$A$13),"") | AJ38: =IF(AND('Mapa final'!#REF!="Muy Baja",'Mapa final'!#REF!="Catastrófico"),CONCATENATE("R",'Mapa final'!#REF!),"") -> #REF! | AL38: =IF(AND('Mapa final'!#REF!="Muy Baja",'Mapa final'!#REF!="Catastrófico"),CONCATENATE("R",'Mapa final'!#REF!),"") -> #REF!
J40: =IF(AND('Mapa final'!#REF!="Muy Baja",'Mapa final'!#REF!="Leve"),CONCATENATE("R",'Mapa final'!#REF!),"") -> #REF! | L40: =IF(AND('Mapa final'!#REF!="Muy Baja",'Mapa final'!#REF!="Leve"),CONCATENATE("R",'Mapa final'!#REF!),"") -> #REF! | N40: =IF(AND('Mapa final'!#REF!="Muy Baja",'Mapa final'!#REF!="Leve"),CONCATENATE("R",'Mapa final'!#REF!),"") -> #REF! | P40: =IF(AND('Mapa final'!#REF!="Muy Baja",'Mapa final'!#REF!="Menor"),CONCATENATE("R",'Mapa final'!#REF!),"") -> #REF! | R40: =IF(AND('Mapa final'!#REF!="Muy Baja",'Mapa final'!#REF!="Menor"),CONCATENATE("R",'Mapa final'!#REF!),"") -> #REF! | T40: =IF(AND('Mapa final'!#REF!="Muy Baja",'Mapa final'!#REF!="Menor"),CONCATENATE("R",'Mapa final'!#REF!),"") -> #REF! | V40: =IF(AND('Mapa final'!#REF!="Muy Baja",'Mapa final'!#REF!="Moderado"),CONCATENATE("R",'Mapa final'!#REF!),"") -> #REF! | X40: =IF(AND('Mapa final'!#REF!="Muy Baja",'Mapa final'!#REF!="Moderado"),CONCATENATE("R",'Mapa final'!#REF!),"") -> #REF! | Z40: =IF(AND('Mapa final'!#REF!="Muy Baja",'Mapa final'!#REF!="Moderado"),CONCATENATE("R",'Mapa final'!#REF!),"") -> #REF! | AB40: =IF(AND('Mapa final'!#REF!="Muy Baja",'Mapa final'!#REF!="Mayor"),CONCATENATE("R",'Mapa final'!#REF!),"") -> #REF! | AD40: =IF(AND('Mapa final'!#REF!="Muy Baja",'Mapa final'!#REF!="Mayor"),CONCATENATE("R",'Mapa final'!#REF!),"") -> #REF! | AF40: =IF(AND('Mapa final'!#REF!="Muy Baja",'Mapa final'!#REF!="Mayor"),CONCATENATE("R",'Mapa final'!#REF!),"") -> #REF! | AH40: =IF(AND('Mapa final'!#REF!="Muy Baja",'Mapa final'!#REF!="Catastrófico"),CONCATENATE("R",'Mapa final'!#REF!),"") -> #REF! | AJ40: =IF(AND('Mapa final'!#REF!="Muy Baja",'Mapa final'!#REF!="Catastrófico"),CONCATENATE("R",'Mapa final'!#REF!),"") -> #REF! | AL40: =IF(AND('Mapa final'!#REF!="Muy Baja",'Mapa final'!#REF!="Catastrófico"),CONCATENATE("R",'Mapa final'!#REF!),"") -> #REF!
J42: =IF(AND('Mapa final'!#REF!="Muy Baja",'Mapa final'!#REF!="Leve"),CONCATENATE("R",'Mapa final'!#REF!),"") -> #REF! | L42: =IF(AND('Mapa final'!#REF!="Muy Baja",'Mapa final'!#REF!="Leve"),CONCATENATE("R",'Mapa final'!#REF!),"") -> #REF! | N42: =IF(AND('Mapa final'!#REF!="Muy Baja",'Mapa final'!#REF!="Leve"),CONCATENATE("R",'Mapa final'!#REF!),"") -> #REF! | P42: =IF(AND('Mapa final'!#REF!="Muy Baja",'Mapa final'!#REF!="Menor"),CONCATENATE("R",'Mapa final'!#REF!),"") -> #REF! | R42: =IF(AND('Mapa final'!#REF!="Muy Baja",'Mapa final'!#REF!="Menor"),CONCATENATE("R",'Mapa final'!#REF!),"") -> #REF! | T42: =IF(AND('Mapa final'!#REF!="Muy Baja",'Mapa final'!#REF!="Menor"),CONCATENATE("R",'Mapa final'!#REF!),"") -> #REF! | V42: =IF(AND('Mapa final'!#REF!="Muy Baja",'Mapa final'!#REF!="Moderado"),CONCATENATE("R",'Mapa final'!#REF!),"") -> #REF! | X42: =IF(AND('Mapa final'!#REF!="Muy Baja",'Mapa final'!#REF!="Moderado"),CONCATENATE("R",'Mapa final'!#REF!),"") -> #REF! | Z42: =IF(AND('Mapa final'!#REF!="Muy Baja",'Mapa final'!#REF!="Moderado"),CONCATENATE("R",'Mapa final'!#REF!),"") -> #REF! | AB42: =IF(AND('Mapa final'!#REF!="Muy Baja",'Mapa final'!#REF!="Mayor"),CONCATENATE("R",'Mapa final'!#REF!),"") -> #REF! | AD42: =IF(AND('Mapa final'!#REF!="Muy Baja",'Mapa final'!#REF!="Mayor"),CONCATENATE("R",'Mapa final'!#REF!),"") -> #REF! | AF42: =IF(AND('Mapa final'!#REF!="Muy Baja",'Mapa final'!#REF!="Mayor"),CONCATENATE("R",'Mapa final'!#REF!),"") -> #REF! | AH42: =IF(AND('Mapa final'!#REF!="Muy Baja",'Mapa final'!#REF!="Catastrófico"),CONCATENATE("R",'Mapa final'!#REF!),"") -> #REF! | AJ42: =IF(AND('Mapa final'!#REF!="Muy Baja",'Mapa final'!#REF!="Catastrófico"),CONCATENATE("R",'Mapa final'!#REF!),"") -> #REF! | AL42: =IF(AND('Mapa final'!#REF!="Muy Baja",'Mapa final'!#REF!="Catastrófico"),CONCATENATE("R",'Mapa final'!#REF!),"") -> #REF!
J44: =IF(AND('Mapa final'!#REF!="Muy Baja",'Mapa final'!#REF!="Leve"),CONCATENATE("R",'Mapa final'!#REF!),"") -> #REF! | L44: =IF(AND('Mapa final'!$H$19="Muy Baja",'Mapa final'!$L$19="Leve"),CONCATENATE("R",'Mapa final'!$A$19),"") | N44: =IF(AND('Mapa final'!$H$25="Muy Baja",'Mapa final'!$L$25="Leve"),CONCATENATE("R",'Mapa final'!$A$25),"") | P44: =IF(AND('Mapa final'!#REF!="Muy Baja",'Mapa final'!#REF!="Menor"),CONCATENATE("R",'Mapa final'!#REF!),"") -> #REF! | R44: =IF(AND('Mapa final'!$H$19="Muy Baja",'Mapa final'!$L$19="Menor"),CONCATENATE("R",'Mapa final'!$A$19),"") | T44: =IF(AND('Mapa final'!$H$25="Muy Baja",'Mapa final'!$L$25="Menor"),CONCATENATE("R",'Mapa final'!$A$25),"") | V44: =IF(AND('Mapa final'!#REF!="Muy Baja",'Mapa final'!#REF!="Moderado"),CONCATENATE("R",'Mapa final'!#REF!),"") -> #REF! | X44: =IF(AND('Mapa final'!$H$19="Muy Baja",'Mapa final'!$L$19="Moderado"),CONCATENATE("R",'Mapa final'!$A$19),"") | Z44: =IF(AND('Mapa final'!$H$25="Muy Baja",'Mapa final'!$L$25="Moderado"),CONCATENATE("R",'Mapa final'!$A$25),"") | AB44: =IF(AND('Mapa final'!#REF!="Muy Baja",'Mapa final'!#REF!="Mayor"),CONCATENATE("R",'Mapa final'!#REF!),"") -> #REF! | AD44: =IF(AND('Mapa final'!$H$19="Muy Baja",'Mapa final'!$L$19="Mayor"),CONCATENATE("R",'Mapa final'!$A$19),"") | AF44: =IF(AND('Mapa final'!$H$25="Muy Baja",'Mapa final'!$L$25="Mayor"),CONCATENATE("R",'Mapa final'!$A$25),"") | AH44: =IF(AND('Mapa final'!#REF!="Muy Baja",'Mapa final'!#REF!="Catastrófico"),CONCATENATE("R",'Mapa final'!#REF!),"") -> #REF! | AJ44: =IF(AND('Mapa final'!$H$19="Muy Baja",'Mapa final'!$L$19="Catastrófico"),CONCATENATE("R",'Mapa final'!$A$19),"") | AL44: =IF(AND('Mapa final'!$H$25="Muy Baja",'Mapa final'!$L$25="Catastrófico"),CONCATENATE("R",'Mapa final'!$A$25),"")
J46: Leve 20% | P46: Menor 40% | V46: Moderado 60% | AB46: Mayor 80% | AH46: Catastrófico 100%

Sheet Matriz Calor Residual
B2: Matriz de Calor Residual | J2: Impacto
B6: Probabilidad | E6: Muy Alta 100% | J6: =IF(AND('Mapa final'!$Y$13="Muy Alta",'Mapa final'!$AA$13="Leve"),CONCATENATE("R1C",'Mapa final'!$O$13),"") | K6: =IF(AND('Mapa final'!$Y$14="Muy Alta",'Mapa final'!$AA$14="Leve"),CONCATENATE("R1C",'Mapa final'!$O$14),"") | L6: =IF(AND('Mapa final'!$Y$15="Muy Alta",'Mapa final'!$AA$15="Leve"),CONCATENATE("R1C",'Mapa final'!$O$15),"") | M6: =IF(AND('Mapa final'!$Y$16="Muy Alta",'Mapa final'!$AA$16="Leve"),CONCATENATE("R1C",'Mapa final'!$O$16),"") | N6: =IF(AND('Mapa final'!$Y$17="Muy Alta",'Mapa final'!$AA$17="Leve"),CONCATENATE("R1C",'Mapa final'!$O$17),"") | O6: =IF(AND('Mapa final'!$Y$18="Muy Alta",'Mapa final'!$AA$18="Leve"),CONCATENATE("R1C",'Mapa final'!$O$18),"") | P6: =IF(AND('Mapa final'!$Y$13="Muy Alta",'Mapa final'!$AA$13="Menor"),CONCATENATE("R1C",'Mapa final'!$O$13),"") | Q6: =IF(AND('Mapa final'!$Y$14="Muy Alta",'Mapa final'!$AA$14="Menor"),CONCATENATE("R1C",'Mapa final'!$O$14),"") | R6: =IF(AND('Mapa final'!$Y$15="Muy Alta",'Mapa final'!$AA$15="Menor"),CONCATENATE("R1C",'Mapa final'!$O$15),"") | S6: =IF(AND('Mapa final'!$Y$16="Muy Alta",'Mapa final'!$AA$16="Menor"),CONCATENATE("R1C",'Mapa final'!$O$16),"") | T6: =IF(AND('Mapa final'!$Y$17="Muy Alta",'Mapa final'!$AA$17="Menor"),CONCATENATE("R1C",'Mapa final'!$O$17),"") | U6: =IF(AND('Mapa final'!$Y$18="Muy Alta",'Mapa final'!$AA$18="Menor"),CONCATENATE("R1C",'Mapa final'!$O$18),"") | V6: =IF(AND('Mapa final'!$Y$13="Muy Alta",'Mapa final'!$AA$13="Moderado"),CONCATENATE("R1C",'Mapa final'!$O$13),"") | W6: =IF(AND('Mapa final'!$Y$14="Muy Alta",'Mapa final'!$AA$14="Moderado"),CONCATENATE("R1C",'Mapa final'!$O$14),"") | X6: =IF(AND('Mapa final'!$Y$15="Muy Alta",'Mapa final'!$AA$15="Moderado"),CONCATENATE("R1C",'Mapa final'!$O$15),"") | Y6: =IF(AND('Mapa final'!$Y$16="Muy Alta",'Mapa final'!$AA$16="Moderado"),CONCATENATE("R1C",'Mapa final'!$O$16),"") | Z6: =IF(AND('Mapa final'!$Y$17="Muy Alta",'Mapa final'!$AA$17="Moderado"),CONCATENATE("R1C",'Mapa final'!$O$17),"") | AA6: =IF(AND('Mapa final'!$Y$18="Muy Alta",'Mapa final'!$AA$18="Moderado"),CONCATENATE("R1C",'Mapa final'!$O$18),"") | AB6: =IF(AND('Mapa final'!$Y$13="Muy Alta",'Mapa final'!$AA$13="Mayor"),CONCATENATE("R1C",'Mapa final'!$O$13),"") | AC6: =IF(AND('Mapa final'!$Y$14="Muy Alta",'Mapa final'!$AA$14="Mayor"),CONCATENATE("R1C",'Mapa final'!$O$14),"") | AD6: =IF(AND('Mapa final'!$Y$15="Muy Alta",'Mapa final'!$AA$15="Mayor"),CONCATENATE("R1C",'Mapa final'!$O$15),"") | AE6: =IF(AND('Mapa final'!$Y$16="Muy Alta",'Mapa final'!$AA$16="Mayor"),CONCATENATE("R1C",'Mapa final'!$O$16),"") | AF6: =IF(AND('Mapa final'!$Y$17="Muy Alta",'Mapa final'!$AA$17="Mayor"),CONCATENATE("R1C",'Mapa final'!$O$17),"") | AG6: =IF(AND('Mapa final'!$Y$18="Muy Alta",'Mapa final'!$AA$18="Mayor"),CONCATENATE("R1C",'Mapa final'!$O$18),"") | AH6: =IF(AND('Mapa final'!$Y$13="Muy Alta",'Mapa final'!$AA$13="Catastrófico"),CONCATENATE("R1C",'Mapa final'!$O$13),"") | AI6: =IF(AND('Mapa final'!$Y$14="Muy Alta",'Mapa final'!$AA$14="Catastrófico"),CONCATENATE("R1C",'Mapa final'!$O$14),"") | AJ6: =IF(AND('Mapa final'!$Y$15="Muy Alta",'Mapa final'!$AA$15="Catastrófico"),CONCATENATE("R1C",'Mapa final'!$O$15),"") | AK6: =IF(AND('Mapa final'!$Y$16="Muy Alta",'Mapa final'!$AA$16="Catastrófico"),CONCATENATE("R1C",'Mapa final'!$O$16),"") | AL6: =IF(AND('Mapa final'!$Y$17="Muy Alta",'Mapa final'!$AA$17="Catastrófico"),CONCATENATE("R1C",'Mapa final'!$O$17),"") | AM6: =IF(AND('Mapa final'!$Y$18="Muy Alta",'Mapa final'!$AA$18="Catastrófico"),CONCATENATE("R1C",'Mapa final'!$O$18),"") | AO6: Extremo
J7: =IF(AND('Mapa final'!#REF!="Muy Alta",'Mapa final'!#REF!="Leve"),CONCATENATE("R2C",'Mapa final'!#REF!),"") -> #REF! | K7: =IF(AND('Mapa final'!#REF!="Muy Alta",'Mapa final'!#REF!="Leve"),CONCATENATE("R2C",'Mapa final'!#REF!),"") -> #REF! | L7: =IF(AND('Mapa final'!#REF!="Muy Alta",'Mapa final'!#REF!="Leve"),CONCATENATE("R2C",'Mapa final'!#REF!),"") -> #REF! | M7: =IF(AND('Mapa final'!#REF!="Muy Alta",'Mapa final'!#REF!="Leve"),CONCATENATE("R2C",'Mapa final'!#REF!),"") -> #REF! | N7: =IF(AND('Mapa final'!#REF!="Muy Alta",'Mapa final'!#REF!="Leve"),CONCATENATE("R2C",'Mapa final'!#REF!),"") -> #REF! | O7: =IF(AND('Mapa final'!#REF!="Muy Alta",'Mapa final'!#REF!="Leve"),CONCATENATE("R2C",'Mapa final'!#REF!),"") -> #REF! | P7: =IF(AND('Mapa final'!#REF!="Muy Alta",'Mapa final'!#REF!="Menor"),CONCATENATE("R2C",'Mapa final'!#REF!),"") -> #REF! | Q7: =IF(AND('Mapa final'!#REF!="Muy Alta",'Mapa final'!#REF!="Menor"),CONCATENATE("R2C",'Mapa final'!#REF!),"") -> #REF! | R7: =IF(AND('Mapa final'!#REF!="Muy Alta",'Mapa final'!#REF!="Menor"),CONCATENATE("R2C",'Mapa final'!#REF!),"") -> #REF! | S7: =IF(AND('Mapa final'!#REF!="Muy Alta",'Mapa final'!#REF!="Menor"),CONCATENATE("R2C",'Mapa final'!#REF!),"") -> #REF! | T7: =IF(AND('Mapa final'!#REF!="Muy Alta",'Mapa final'!#REF!="Menor"),CONCATENATE("R2C",'Mapa final'!#REF!),"") -> #REF! | U7: =IF(AND('Mapa final'!#REF!="Muy Alta",'Mapa final'!#REF!="Menor"),CONCATENATE("R2C",'Mapa final'!#REF!),"") -> #REF! | V7: =IF(AND('Mapa final'!#REF!="Muy Alta",'Mapa final'!#REF!="Moderado"),CONCATENATE("R2C",'Mapa final'!#REF!),"") -> #REF! | W7: =IF(AND('Mapa final'!#REF!="Muy Alta",'Mapa final'!#REF!="Moderado"),CONCATENATE("R2C",'Mapa final'!#REF!),"") -> #REF! | X7: =IF(AND('Mapa final'!#REF!="Muy Alta",'Mapa final'!#REF!="Moderado"),CONCATENATE("R2C",'Mapa final'!#REF!),"") -> #REF! | Y7: =IF(AND('Mapa final'!#REF!="Muy Alta",'Mapa final'!#REF!="Moderado"),CONCATENATE("R2C",'Mapa final'!#REF!),"") -> #REF! | Z7: =IF(AND('Mapa final'!#REF!="Muy Alta",'Mapa final'!#REF!="Moderado"),CONCATENATE("R2C",'Mapa final'!#REF!),"") -> #REF! | AA7: =IF(AND('Mapa final'!#REF!="Muy Alta",'Mapa final'!#REF!="Moderado"),CONCATENATE("R2C",'Mapa final'!#REF!),"") -> #REF! | AB7: =IF(AND('Mapa final'!#REF!="Muy Alta",'Mapa final'!#REF!="Mayor"),CONCATENATE("R2C",'Mapa final'!#REF!),"") -> #REF! | AC7: =IF(AND('Mapa final'!#REF!="Muy Alta",'Mapa final'!#REF!="Mayor"),CONCATENATE("R2C",'Mapa final'!#REF!),"") -> #REF! | AD7: =IF(AND('Mapa final'!#REF!="Muy Alta",'Mapa final'!#REF!="Mayor"),CONCATENATE("R2C",'Mapa final'!#REF!),"") -> #REF! | AE7: =IF(AND('Mapa final'!#REF!="Muy Alta",'Mapa final'!#REF!="Mayor"),CONCATENATE("R2C",'Mapa final'!#REF!),"") -> #REF! | AF7: =IF(AND('Mapa final'!#REF!="Muy Alta",'Mapa final'!#REF!="Mayor"),CONCATENATE("R2C",'Mapa final'!#REF!),"") -> #REF! | AG7: =IF(AND('Mapa final'!#REF!="Muy Alta",'Mapa final'!#REF!="Mayor"),CONCATENATE("R2C",'Mapa final'!#REF!),"") -> #REF! | AH7: =IF(AND('Mapa final'!#REF!="Muy Alta",'Mapa final'!#REF!="Catastrófico"),CONCATENATE("R2C",'Mapa final'!#REF!),"") -> #REF! | AI7: =IF(AND('Mapa final'!#REF!="Muy Alta",'Mapa final'!#REF!="Catastrófico"),CONCATENATE("R2C",'Mapa final'!#REF!),"") -> #REF! | AJ7: =IF(AND('Mapa final'!#REF!="Muy Alta",'Mapa final'!#REF!="Catastrófico"),CONCATENATE("R2C",'Mapa final'!#REF!),"") -> #REF! | AK7: =IF(AND('Mapa final'!#REF!="Muy Alta",'Mapa final'!#REF!="Catastrófico"),CONCATENATE("R2C",'Mapa final'!#REF!),"") -> #REF! | AL7: =IF(AND('Mapa final'!#REF!="Muy Alta",'Mapa final'!#REF!="Catastrófico"),CONCATENATE("R2C",'Mapa final'!#REF!),"") -> #REF! | AM7: =IF(AND('Mapa final'!#REF!="Muy Alta",'Mapa final'!#REF!="Catastrófico"),CONCATENATE("R2C",'Mapa final'!#REF!),"") -> #REF!
J8: =IF(AND('Mapa final'!#REF!="Muy Alta",'Mapa final'!#REF!="Leve"),CONCATENATE("R3C",'Mapa final'!#REF!),"") -> #REF! | K8: =IF(AND('Mapa final'!#REF!="Muy Alta",'Mapa final'!#REF!="Leve"),CONCATENATE("R3C",'Mapa final'!#REF!),"") -> #REF! | L8: =IF(AND('Mapa final'!#REF!="Muy Alta",'Mapa final'!#REF!="Leve"),CONCATENATE("R3C",'Mapa final'!#REF!),"") -> #REF! | M8: =IF(AND('Mapa final'!#REF!="Muy Alta",'Mapa final'!#REF!="Leve"),CONCATENATE("R3C",'Mapa final'!#REF!),"") -> #REF! | N8: =IF(AND('Mapa final'!#REF!="Muy Alta",'Mapa final'!#REF!="Leve"),CONCATENATE("R3C",'Mapa final'!#REF!),"") -> #REF! | O8: =IF(AND('Mapa final'!#REF!="Muy Alta",'Mapa final'!#REF!="Leve"),CONCATENATE("R3C",'Mapa final'!#REF!),"") -> #REF! | P8: =IF(AND('Mapa final'!#REF!="Muy Alta",'Mapa final'!#REF!="Menor"),CONCATENATE("R3C",'Mapa final'!#REF!),"") -> #REF! | Q8: =IF(AND('Mapa final'!#REF!="Muy Alta",'Mapa final'!#REF!="Menor"),CONCATENATE("R3C",'Mapa final'!#REF!),"") -> #REF! | R8: =IF(AND('Mapa final'!#REF!="Muy Alta",'Mapa final'!#REF!="Menor"),CONCATENATE("R3C",'Mapa final'!#REF!),"") -> #REF! | S8: =IF(AND('Mapa final'!#REF!="Muy Alta",'Mapa final'!#REF!="Menor"),CONCATENATE("R3C",'Mapa final'!#REF!),"") -> #REF! | T8: =IF(AND('Mapa final'!#REF!="Muy Alta",'Mapa final'!#REF!="Menor"),CONCATENATE("R3C",'Mapa final'!#REF!),"") -> #REF! | U8: =IF(AND('Mapa final'!#REF!="Muy Alta",'Mapa final'!#REF!="Menor"),CONCATENATE("R3C",'Mapa final'!#REF!),"") -> #REF! | V8: =IF(AND('Mapa final'!#REF!="Muy Alta",'Mapa final'!#REF!="Moderado"),CONCATENATE("R3C",'Mapa final'!#REF!),"") -> #REF! | W8: =IF(AND('Mapa final'!#REF!="Muy Alta",'Mapa final'!#REF!="Moderado"),CONCATENATE("R3C",'Mapa final'!#REF!),"") -> #REF! | X8: =IF(AND('Mapa final'!#REF!="Muy Alta",'Mapa final'!#REF!="Moderado"),CONCATENATE("R3C",'Mapa final'!#REF!),"") -> #REF! | Y8: =IF(AND('Mapa final'!#REF!="Muy Alta",'Mapa final'!#REF!="Moderado"),CONCATENATE("R3C",'Mapa final'!#REF!),"") -> #REF! | Z8: =IF(AND('Mapa final'!#REF!="Muy Alta",'Mapa final'!#REF!="Moderado"),CONCATENATE("R3C",'Mapa final'!#REF!),"") -> #REF! | AA8: =IF(AND('Mapa final'!#REF!="Muy Alta",'Mapa final'!#REF!="Moderado"),CONCATENATE("R3C",'Mapa final'!#REF!),"") -> #REF! | AB8: =IF(AND('Mapa final'!#REF!="Muy Alta",'Mapa final'!#REF!="Mayor"),CONCATENATE("R3C",'Mapa final'!#REF!),"") -> #REF! | AC8: =IF(AND('Mapa final'!#REF!="Muy Alta",'Mapa final'!#REF!="Mayor"),CONCATENATE("R3C",'Mapa final'!#REF!),"") -> #REF! | AD8: =IF(AND('Mapa final'!#REF!="Muy Alta",'Mapa final'!#REF!="Mayor"),CONCATENATE("R3C",'Mapa final'!#REF!),"") -> #REF! | AE8: =IF(AND('Mapa final'!#REF!="Muy Alta",'Mapa final'!#REF!="Mayor"),CONCATENATE("R3C",'Mapa final'!#REF!),"") -> #REF! | AF8: =IF(AND('Mapa final'!#REF!="Muy Alta",'Mapa final'!#REF!="Mayor"),CONCATENATE("R3C",'Mapa final'!#REF!),"") -> #REF! | AG8: =IF(AND('Mapa final'!#REF!="Muy Alta",'Mapa final'!#REF!="Mayor"),CONCATENATE("R3C",'Mapa final'!#REF!),"") -> #REF! | AH8: =IF(AND('Mapa final'!#REF!="Muy Alta",'Mapa final'!#REF!="Catastrófico"),CONCATENATE("R3C",'Mapa final'!#REF!),"") -> #REF! | AI8: =IF(AND('Mapa final'!#REF!="Muy Alta",'Mapa final'!#REF!="Catastrófico"),CONCATENATE("R3C",'Mapa final'!#REF!),"") -> #REF! | AJ8: =IF(AND('Mapa final'!#REF!="Muy Alta",'Mapa final'!#REF!="Catastrófico"),CONCATENATE("R3C",'Mapa final'!#REF!),"") -> #REF! | AK8: =IF(AND('Mapa final'!#REF!="Muy Alta",'Mapa final'!#REF!="Catastrófico"),CONCATENATE("R3C",'Mapa final'!#REF!),"") -> #REF! | AL8: =IF(AND('Mapa final'!#REF!="Muy Alta",'Mapa final'!#REF!="Catastrófico"),CONCATENATE("R3C",'Mapa final'!#REF!),"") -> #REF! | AM8: =IF(AND('Mapa final'!#REF!="Muy Alta",'Mapa final'!#REF!="Catastrófico"),CONCATENATE("R3C",'Mapa final'!#REF!),"") -> #REF!
J9: =IF(AND('Mapa final'!#REF!="Muy Alta",'Mapa final'!#REF!="Leve"),CONCATENATE("R4C",'Mapa final'!#REF!),"") -> #REF! | K9: =IF(AND('Mapa final'!#REF!="Muy Alta",'Mapa final'!#REF!="Leve"),CONCATENATE("R4C",'Mapa final'!#REF!),"") -> #REF! | L9: =IF(AND('Mapa final'!#REF!="Muy Alta",'Mapa final'!#REF!="Leve"),CONCATENATE("R4C",'Mapa final'!#REF!),"") -> #REF! | M9: =IF(AND('Mapa final'!#REF!="Muy Alta",'Mapa final'!#REF!="Leve"),CONCATENATE("R4C",'Mapa final'!#REF!),"") -> #REF! | N9: =IF(AND('Mapa final'!#REF!="Muy Alta",'Mapa final'!#REF!="Leve"),CONCATENATE("R4C",'Mapa final'!#REF!),"") -> #REF! | O9: =IF(AND('Mapa final'!#REF!="Muy Alta",'Mapa final'!#REF!="Leve"),CONCATENATE("R4C",'Mapa final'!#REF!),"") -> #REF! | P9: =IF(AND('Mapa final'!#REF!="Muy Alta",'Mapa final'!#REF!="Menor"),CONCATENATE("R4C",'Mapa final'!#REF!),"") -> #REF! | Q9: =IF(AND('Mapa final'!#REF!="Muy Alta",'Mapa final'!#REF!="Menor"),CONCATENATE("R4C",'Mapa final'!#REF!),"") -> #REF! | R9: =IF(AND('Mapa final'!#REF!="Muy Alta",'Mapa final'!#REF!="Menor"),CONCATENATE("R4C",'Mapa final'!#REF!),"") -> #REF! | S9: =IF(AND('Mapa final'!#REF!="Muy Alta",'Mapa final'!#REF!="Menor"),CONCATENATE("R4C",'Mapa final'!#REF!),"") -> #REF! | T9: =IF(AND('Mapa final'!#REF!="Muy Alta",'Mapa final'!#REF!="Menor"),CONCATENATE("R4C",'Mapa final'!#REF!),"") -> #REF! | U9: =IF(AND('Mapa final'!#REF!="Muy Alta",'Mapa final'!#REF!="Menor"),CONCATENATE("R4C",'Mapa final'!#REF!),"") -> #REF! | V9: =IF(AND('Mapa final'!#REF!="Muy Alta",'Mapa final'!#REF!="Moderado"),CONCATENATE("R4C",'Mapa final'!#REF!),"") -> #REF! | W9: =IF(AND('Mapa final'!#REF!="Muy Alta",'Mapa final'!#REF!="Moderado"),CONCATENATE("R4C",'Mapa final'!#REF!),"") -> #REF! | X9: =IF(AND('Mapa final'!#REF!="Muy Alta",'Mapa final'!#REF!="Moderado"),CONCATENATE("R4C",'Mapa final'!#REF!),"") -> #REF! | Y9: =IF(AND('Mapa final'!#REF!="Muy Alta",'Mapa final'!#REF!="Moderado"),CONCATENATE("R4C",'Mapa final'!#REF!),"") -> #REF! | Z9: =IF(AND('Mapa final'!#REF!="Muy Alta",'Mapa final'!#REF!="Moderado"),CONCATENATE("R4C",'Mapa final'!#REF!),"") -> #REF! | AA9: =IF(AND('Mapa final'!#REF!="Muy Alta",'Mapa final'!#REF!="Moderado"),CONCATENATE("R4C",'Mapa final'!#REF!),"") -> #REF! | AB9: =IF(AND('Mapa final'!#REF!="Muy Alta",'Mapa final'!#REF!="Mayor"),CONCATENATE("R4C",'Mapa final'!#REF!),"") -> #REF! | AC9: =IF(AND('Mapa final'!#REF!="Muy Alta",'Mapa final'!#REF!="Mayor"),CONCATENATE("R4C",'Mapa final'!#REF!),"") -> #REF! | AD9: =IF(AND('Mapa final'!#REF!="Muy Alta",'Mapa final'!#REF!="Mayor"),CONCATENATE("R4C",'Mapa final'!#REF!),"") -> #REF! | AE9: =IF(AND('Mapa final'!#REF!="Muy Alta",'Mapa final'!#REF!="Mayor"),CONCATENATE("R4C",'Mapa final'!#REF!),"") -> #REF! | AF9: =IF(AND('Mapa final'!#REF!="Muy Alta",'Mapa final'!#REF!="Mayor"),CONCATENATE("R4C",'Mapa final'!#REF!),"") -> #REF! | AG9: =IF(AND('Mapa final'!#REF!="Muy Alta",'Mapa final'!#REF!="Mayor"),CONCATENATE("R4C",'Mapa final'!#REF!),"") -> #REF! | AH9: =IF(AND('Mapa final'!#REF!="Muy Alta",'Mapa final'!#REF!="Catastrófico"),CONCATENATE("R4C",'Mapa final'!#REF!),"") -> #REF! | AI9: =IF(AND('Mapa final'!#REF!="Muy Alta",'Mapa final'!#REF!="Catastrófico"),CONCATENATE("R4C",'Mapa final'!#REF!),"") -> #REF! | AJ9: =IF(AND('Mapa final'!#REF!="Muy Alta",'Mapa final'!#REF!="Catastrófico"),CONCATENATE("R4C",'Mapa final'!#REF!),"") -> #REF! | AK9: =IF(AND('Mapa final'!#REF!="Muy Alta",'Mapa final'!#REF!="Catastrófico"),CONCATENATE("R4C",'Mapa final'!#REF!),"") -> #REF! | AL9: =IF(AND('Mapa final'!#REF!="Muy Alta",'Mapa final'!#REF!="Catastrófico"),CONCATENATE("R4C",'Mapa final'!#REF!),"") -> #REF! | AM9: =IF(AND('Mapa final'!#REF!="Muy Alta",'Mapa final'!#REF!="Catastrófico"),CONCATENATE("R4C",'Mapa final'!#REF!),"") -> #REF!
J10: =IF(AND('Mapa final'!#REF!="Muy Alta",'Mapa final'!#REF!="Leve"),CONCATENATE("R5C",'Mapa final'!#REF!),"") -> #REF! | K10: =IF(AND('Mapa final'!#REF!="Muy Alta",'Mapa final'!#REF!="Leve"),CONCATENATE("R5C",'Mapa final'!#REF!),"") -> #REF! | L10: =IF(AND('Mapa final'!#REF!="Muy Alta",'Mapa final'!#REF!="Leve"),CONCATENATE("R5C",'Mapa final'!#REF!),"") -> #REF! | M10: =IF(AND('Mapa final'!#REF!="Muy Alta",'Mapa final'!#REF!="Leve"),CONCATENATE("R5C",'Mapa final'!#REF!),"") -> #REF! | N10: =IF(AND('Mapa final'!#REF!="Muy Alta",'Mapa final'!#REF!="Leve"),CONCATENATE("R5C",'Mapa final'!#REF!),"") -> #REF! | O10: =IF(AND('Mapa final'!#REF!="Muy Alta",'Mapa final'!#REF!="Leve"),CONCATENATE("R5C",'Mapa final'!#REF!),"") -> #REF! | P10: =IF(AND('Mapa final'!#REF!="Muy Alta",'Mapa final'!#REF!="Menor"),CONCATENATE("R5C",'Mapa final'!#REF!),"") -> #REF! | Q10: =IF(AND('Mapa final'!#REF!="Muy Alta",'Mapa final'!#REF!="Menor"),CONCATENATE("R5C",'Mapa final'!#REF!),"") -> #REF! | R10: =IF(AND('Mapa final'!#REF!="Muy Alta",'Mapa final'!#REF!="Menor"),CONCATENATE("R5C",'Mapa final'!#REF!),"") -> #REF! | S10: =IF(AND('Mapa final'!#REF!="Muy Alta",'Mapa final'!#REF!="Menor"),CONCATENATE("R5C",'Mapa final'!#REF!),"") -> #REF! | T10: =IF(AND('Mapa final'!#REF!="Muy Alta",'Mapa final'!#REF!="Menor"),CONCATENATE("R5C",'Mapa final'!#REF!),"") -> #REF! | U10: =IF(AND('Mapa final'!#REF!="Muy Alta",'Mapa final'!#REF!="Menor"),CONCATENATE("R5C",'Mapa final'!#REF!),"") -> #REF! | V10: =IF(AND('Mapa final'!#REF!="Muy Alta",'Mapa final'!#REF!="Moderado"),CONCATENATE("R5C",'Mapa final'!#REF!),"") -> #REF! | W10: =IF(AND('Mapa final'!#REF!="Muy Alta",'Mapa final'!#REF!="Moderado"),CONCATENATE("R5C",'Mapa final'!#REF!),"") -> #REF! | X10: =IF(AND('Mapa final'!#REF!="Muy Alta",'Mapa final'!#REF!="Moderado"),CONCATENATE("R5C",'Mapa final'!#REF!),"") -> #REF! | Y10: =IF(AND('Mapa final'!#REF!="Muy Alta",'Mapa final'!#REF!="Moderado"),CONCATENATE("R5C",'Mapa final'!#REF!),"") -> #REF! | Z10: =IF(AND('Mapa final'!#REF!="Muy Alta",'Mapa final'!#REF!="Moderado"),CONCATENATE("R5C",'Mapa final'!#REF!),"") -> #REF! | AA10: =IF(AND('Mapa final'!#REF!="Muy Alta",'Mapa final'!#REF!="Moderado"),CONCATENATE("R5C",'Mapa final'!#REF!),"") -> #REF! | AB10: =IF(AND('Mapa final'!#REF!="Muy Alta",'Mapa final'!#REF!="Mayor"),CONCATENATE("R5C",'Mapa final'!#REF!),"") -> #REF! | AC10: =IF(AND('Mapa final'!#REF!="Muy Alta",'Mapa final'!#REF!="Mayor"),CONCATENATE("R5C",'Mapa final'!#REF!),"") -> #REF! | AD10: =IF(AND('Mapa final'!#REF!="Muy Alta",'Mapa final'!#REF!="Mayor"),CONCATENATE("R5C",'Mapa final'!#REF!),"") -> #REF! | AE10: =IF(AND('Mapa final'!#REF!="Muy Alta",'Mapa final'!#REF!="Mayor"),CONCATENATE("R5C",'Mapa final'!#REF!),"") -> #REF! | AF10: =IF(AND('Mapa final'!#REF!="Muy Alta",'Mapa final'!#REF!="Mayor"),CONCATENATE("R5C",'Mapa final'!#REF!),"") -> #REF! | AG10: =IF(AND('Mapa final'!#REF!="Muy Alta",'Mapa final'!#REF!="Mayor"),CONCATENATE("R5C",'Mapa final'!#REF!),"") -> #REF! | AH10: =IF(AND('Mapa final'!#REF!="Muy Alta",'Mapa final'!#REF!="Catastrófico"),CONCATENATE("R5C",'Mapa final'!#REF!),"") -> #REF! | AI10: =IF(AND('Mapa final'!#REF!="Muy Alta",'Mapa final'!#REF!="Catastrófico"),CONCATENATE("R5C",'Mapa final'!#REF!),"") -> #REF! | AJ10: =IF(AND('Mapa final'!#REF!="Muy Alta",'Mapa final'!#REF!="Catastrófico"),CONCATENATE("R5C",'Mapa final'!#REF!),"") -> #REF! | AK10: =IF(AND('Mapa final'!#REF!="Muy Alta",'Mapa final'!#REF!="Catastrófico"),CONCATENATE("R5C",'Mapa final'!#REF!),"") -> #REF! | AL10: =IF(AND('Mapa final'!#REF!="Muy Alta",'Mapa final'!#REF!="Catastrófico"),CONCATENATE("R5C",'Mapa final'!#REF!),"") -> #REF! | AM10: =IF(AND('Mapa final'!#REF!="Muy Alta",'Mapa final'!#REF!="Catastrófico"),CONCATENATE("R5C",'Mapa final'!#REF!),"") -> #REF!
J11: =IF(AND('Mapa final'!#REF!="Muy Alta",'Mapa final'!#REF!="Leve"),CONCATENATE("R6C",'Mapa final'!#REF!),"") -> #REF! | K11: =IF(AND('Mapa final'!#REF!="Muy Alta",'Mapa final'!#REF!="Leve"),CONCATENATE("R6C",'Mapa final'!#REF!),"") -> #REF! | L11: =IF(AND('Mapa final'!#REF!="Muy Alta",'Mapa final'!#REF!="Leve"),CONCATENATE("R6C",'Mapa final'!#REF!),"") -> #REF! | M11: =IF(AND('Mapa final'!#REF!="Muy Alta",'Mapa final'!#REF!="Leve"),CONCATENATE("R6C",'Mapa final'!#REF!),"") -> #REF! | N11: =IF(AND('Mapa final'!#REF!="Muy Alta",'Mapa final'!#REF!="Leve"),CONCATENATE("R6C",'Mapa final'!#REF!),"") -> #REF! | O11: =IF(AND('Mapa final'!#REF!="Muy Alta",'Mapa final'!#REF!="Leve"),CONCATENATE("R6C",'Mapa final'!#REF!),"") -> #REF! | P11: =IF(AND('Mapa final'!#REF!="Muy Alta",'Mapa final'!#REF!="Menor"),CONCATENATE("R6C",'Mapa final'!#REF!),"") -> #REF! | Q11: =IF(AND('Mapa final'!#REF!="Muy Alta",'Mapa final'!#REF!="Menor"),CONCATENATE("R6C",'Mapa final'!#REF!),"") -> #REF! | R11: =IF(AND('Mapa final'!#REF!="Muy Alta",'Mapa final'!#REF!="Menor"),CONCATENATE("R6C",'Mapa final'!#REF!),"") -> #REF! | S11: =IF(AND('Mapa final'!#REF!="Muy Alta",'Mapa final'!#REF!="Menor"),CONCATENATE("R6C",'Mapa final'!#REF!),"") -> #REF! | T11: =IF(AND('Mapa final'!#REF!="Muy Alta",'Mapa final'!#REF!="Menor"),CONCATENATE("R6C",'Mapa final'!#REF!),"") -> #REF! | U11: =IF(AND('Mapa final'!#REF!="Muy Alta",'Mapa final'!#REF!="Menor"),CONCATENATE("R6C",'Mapa final'!#REF!),"") -> #REF! | V11: =IF(AND('Mapa final'!#REF!="Muy Alta",'Mapa final'!#REF!="Moderado"),CONCATENATE("R6C",'Mapa final'!#REF!),"") -> #REF! | W11: =IF(AND('Mapa final'!#REF!="Muy Alta",'Mapa final'!#REF!="Moderado"),CONCATENATE("R6C",'Mapa final'!#REF!),"") -> #REF! | X11: =IF(AND('Mapa final'!#REF!="Muy Alta",'Mapa final'!#REF!="Moderado"),CONCATENATE("R6C",'Mapa final'!#REF!),"") -> #REF! | Y11: =IF(AND('Mapa final'!#REF!="Muy Alta",'Mapa final'!#REF!="Moderado"),CONCATENATE("R6C",'Mapa final'!#REF!),"") -> #REF! | Z11: =IF(AND('Mapa final'!#REF!="Muy Alta",'Mapa final'!#REF!="Moderado"),CONCATENATE("R6C",'Mapa final'!#REF!),"") -> #REF! | AA11: =IF(AND('Mapa final'!#REF!="Muy Alta",'Mapa final'!#REF!="Moderado"),CONCATENATE("R6C",'Mapa final'!#REF!),"") -> #REF! | AB11: =IF(AND('Mapa final'!#REF!="Muy Alta",'Mapa final'!#REF!="Mayor"),CONCATENATE("R6C",'Mapa final'!#REF!),"") -> #REF! | AC11: =IF(AND('Mapa final'!#REF!="Muy Alta",'Mapa final'!#REF!="Mayor"),CONCATENATE("R6C",'Mapa final'!#REF!),"") -> #REF! | AD11: =IF(AND('Mapa final'!#REF!="Muy Alta",'Mapa final'!#REF!="Mayor"),CONCATENATE("R6C",'Mapa final'!#REF!),"") -> #REF! | AE11: =IF(AND('Mapa final'!#REF!="Muy Alta",'Mapa final'!#REF!="Mayor"),CONCATENATE("R6C",'Mapa final'!#REF!),"") -> #REF! | AF11: =IF(AND('Mapa final'!#REF!="Muy Alta",'Mapa final'!#REF!="Mayor"),CONCATENATE("R6C",'Mapa final'!#REF!),"") -> #REF! | AG11: =IF(AND('Mapa final'!#REF!="Muy Alta",'Mapa final'!#REF!="Mayor"),CONCATENATE("R6C",'Mapa final'!#REF!),"") -> #REF! | AH11: =IF(AND('Mapa final'!#REF!="Muy Alta",'Mapa final'!#REF!="Catastrófico"),CONCATENATE("R6C",'Mapa final'!#REF!),"") -> #REF! | AI11: =IF(AND('Mapa final'!#REF!="Muy Alta",'Mapa final'!#REF!="Catastrófico"),CONCATENATE("R6C",'Mapa final'!#REF!),"") -> #REF! | AJ11: =IF(AND('Mapa final'!#REF!="Muy Alta",'Mapa final'!#REF!="Catastrófico"),CONCATENATE("R6C",'Mapa final'!#REF!),"") -> #REF! | AK11: =IF(AND('Mapa final'!#REF!="Muy Alta",'Mapa final'!#REF!="Catastrófico"),CONCATENATE("R6C",'Mapa final'!#REF!),"") -> #REF! | AL11: =IF(AND('Mapa final'!#REF!="Muy Alta",'Mapa final'!#REF!="Catastrófico"),CONCATENATE("R6C",'Mapa final'!#REF!),"") -> #REF! | AM11: =IF(AND('Mapa final'!#REF!="Muy Alta",'Mapa final'!#REF!="Catastrófico"),CONCATENATE("R6C",'Mapa final'!#REF!),"") -> #REF!
J12: =IF(AND('Mapa final'!#REF!="Muy Alta",'Mapa final'!#REF!="Leve"),CONCATENATE("R7C",'Mapa final'!#REF!),"") -> #REF! | K12: =IF(AND('Mapa final'!#REF!="Muy Alta",'Mapa final'!#REF!="Leve"),CONCATENATE("R7C",'Mapa final'!#REF!),"") -> #REF! | L12: =IF(AND('Mapa final'!#REF!="Muy Alta",'Mapa final'!#REF!="Leve"),CONCATENATE("R7C",'Mapa final'!#REF!),"") -> #REF! | M12: =IF(AND('Mapa final'!#REF!="Muy Alta",'Mapa final'!#REF!="Leve"),CONCATENATE("R7C",'Mapa final'!#REF!),"") -> #REF! | N12: =IF(AND('Mapa final'!#REF!="Muy Alta",'Mapa final'!#REF!="Leve"),CONCATENATE("R7C",'Mapa final'!#REF!),"") -> #REF! | O12: =IF(AND('Mapa final'!#REF!="Muy Alta",'Mapa final'!#REF!="Leve"),CONCATENATE("R7C",'Mapa final'!#REF!),"") -> #REF! | P12: =IF(AND('Mapa final'!#REF!="Muy Alta",'Mapa final'!#REF!="Menor"),CONCATENATE("R7C",'Mapa final'!#REF!),"") -> #REF! | Q12: =IF(AND('Mapa final'!#REF!="Muy Alta",'Mapa final'!#REF!="Menor"),CONCATENATE("R7C",'Mapa final'!#REF!),"") -> #REF! | R12: =IF(AND('Mapa final'!#REF!="Muy Alta",'Mapa final'!#REF!="Menor"),CONCATENATE("R7C",'Mapa final'!#REF!),"") -> #REF! | S12: =IF(AND('Mapa final'!#REF!="Muy Alta",'Mapa final'!#REF!="Menor"),CONCATENATE("R7C",'Mapa final'!#REF!),"") -> #REF! | T12: =IF(AND('Mapa final'!#REF!="Muy Alta",'Mapa final'!#REF!="Menor"),CONCATENATE("R7C",'Mapa final'!#REF!),"") -> #REF! | U12: =IF(AND('Mapa final'!#REF!="Muy Alta",'Mapa final'!#REF!="Menor"),CONCATENATE("R7C",'Mapa final'!#REF!),"") -> #REF! | V12: =IF(AND('Mapa final'!#REF!="Muy Alta",'Mapa final'!#REF!="Moderado"),CONCATENATE("R7C",'Mapa final'!#REF!),"") -> #REF! | W12: =IF(AND('Mapa final'!#REF!="Muy Alta",'Mapa final'!#REF!="Moderado"),CONCATENATE("R7C",'Mapa final'!#REF!),"") -> #REF! | X12: =IF(AND('Mapa final'!#REF!="Muy Alta",'Mapa final'!#REF!="Moderado"),CONCATENATE("R7C",'Mapa final'!#REF!),"") -> #REF! | Y12: =IF(AND('Mapa final'!#REF!="Muy Alta",'Mapa final'!#REF!="Moderado"),CONCATENATE("R7C",'Mapa final'!#REF!),"") -> #REF! | Z12: =IF(AND('Mapa final'!#REF!="Muy Alta",'Mapa final'!#REF!="Moderado"),CONCATENATE("R7C",'Mapa final'!#REF!),"") -> #REF! | AA12: =IF(AND('Mapa final'!#REF!="Muy Alta",'Mapa final'!#REF!="Moderado"),CONCATENATE("R7C",'Mapa final'!#REF!),"") -> #REF! | AB12: =IF(AND('Mapa final'!#REF!="Muy Alta",'Mapa final'!#REF!="Mayor"),CONCATENATE("R7C",'Mapa final'!#REF!),"") -> #REF! | AC12: =IF(AND('Mapa final'!#REF!="Muy Alta",'Mapa final'!#REF!="Mayor"),CONCATENATE("R7C",'Mapa final'!#REF!),"") -> #REF! | AD12: =IF(AND('Mapa final'!#REF!="Muy Alta",'Mapa final'!#REF!="Mayor"),CONCATENATE("R7C",'Mapa final'!#REF!),"") -> #REF! | AE12: =IF(AND('Mapa final'!#REF!="Muy Alta",'Mapa final'!#REF!="Mayor"),CONCATENATE("R7C",'Mapa final'!#REF!),"") -> #REF! | AF12: =IF(AND('Mapa final'!#REF!="Muy Alta",'Mapa final'!#REF!="Mayor"),CONCATENATE("R7C",'Mapa final'!#REF!),"") -> #REF! | AG12: =IF(AND('Mapa final'!#REF!="Muy Alta",'Mapa final'!#REF!="Mayor"),CONCATENATE("R7C",'Mapa final'!#REF!),"") -> #REF! | AH12: =IF(AND('Mapa final'!#REF!="Muy Alta",'Mapa final'!#REF!="Catastrófico"),CONCATENATE("R7C",'Mapa final'!#REF!),"") -> #REF! | AI12: =IF(AND('Mapa final'!#REF!="Muy Alta",'Mapa final'!#REF!="Catastrófico"),CONCATENATE("R7C",'Mapa final'!#REF!),"") -> #REF! | AJ12: =IF(AND('Mapa final'!#REF!="Muy Alta",'Mapa final'!#REF!="Catastrófico"),CONCATENATE("R7C",'Mapa final'!#REF!),"") -> #REF! | AK12: =IF(AND('Mapa final'!#REF!="Muy Alta",'Mapa final'!#REF!="Catastrófico"),CONCATENATE("R7C",'Mapa final'!#REF!),"") -> #REF! | AL12: =IF(AND('Mapa final'!#REF!="Muy Alta",'Mapa final'!#REF!="Catastrófico"),CONCATENATE("R7C",'Mapa final'!#REF!),"") -> #REF! | AM12: =IF(AND('Mapa final'!#REF!="Muy Alta",'Mapa final'!#REF!="Catastrófico"),CONCATENATE("R7C",'Mapa final'!#REF!),"") -> #REF!
J13: =IF(AND('Mapa final'!#REF!="Muy Alta",'Mapa final'!#REF!="Leve"),CONCATENATE("R8C",'Mapa final'!#REF!),"") -> #REF! | K13: =IF(AND('Mapa final'!#REF!="Muy Alta",'Mapa final'!#REF!="Leve"),CONCATENATE("R8C",'Mapa final'!#REF!),"") -> #REF! | L13: =IF(AND('Mapa final'!#REF!="Muy Alta",'Mapa final'!#REF!="Leve"),CONCATENATE("R8C",'Mapa final'!#REF!),"") -> #REF! | M13: =IF(AND('Mapa final'!#REF!="Muy Alta",'Mapa final'!#REF!="Leve"),CONCATENATE("R8C",'Mapa final'!#REF!),"") -> #REF! | N13: =IF(AND('Mapa final'!#REF!="Muy Alta",'Mapa final'!#REF!="Leve"),CONCATENATE("R8C",'Mapa final'!#REF!),"") -> #REF! | O13: =IF(AND('Mapa final'!#REF!="Muy Alta",'Mapa final'!#REF!="Leve"),CONCATENATE("R8C",'Mapa final'!#REF!),"") -> #REF! | P13: =IF(AND('Mapa final'!#REF!="Muy Alta",'Mapa final'!#REF!="Menor"),CONCATENATE("R8C",'Mapa final'!#REF!),"") -> #REF! | Q13: =IF(AND('Mapa final'!#REF!="Muy Alta",'Mapa final'!#REF!="Menor"),CONCATENATE("R8C",'Mapa final'!#REF!),"") -> #REF! | R13: =IF(AND('Mapa final'!#REF!="Muy Alta",'Mapa final'!#REF!="Menor"),CONCATENATE("R8C",'Mapa final'!#REF!),"") -> #REF! | S13: =IF(AND('Mapa final'!#REF!="Muy Alta",'Mapa final'!#REF!="Menor"),CONCATENATE("R8C",'Mapa final'!#REF!),"") -> #REF! | T13: =IF(AND('Mapa final'!#REF!="Muy Alta",'Mapa final'!#REF!="Menor"),CONCATENATE("R8C",'Mapa final'!#REF!),"") -> #REF! | U13: =IF(AND('Mapa final'!#REF!="Muy Alta",'Mapa final'!#REF!="Menor"),CONCATENATE("R8C",'Mapa final'!#REF!),"") -> #REF! | V13: =IF(AND('Mapa final'!#REF!="Muy Alta",'Mapa final'!#REF!="Moderado"),CONCATENATE("R8C",'Mapa final'!#REF!),"") -> #REF! | W13: =IF(AND('Mapa final'!#REF!="Muy Alta",'Mapa final'!#REF!="Moderado"),CONCATENATE("R8C",'Mapa final'!#REF!),"") -> #REF! | X13: =IF(AND('Mapa final'!#REF!="Muy Alta",'Mapa final'!#REF!="Moderado"),CONCATENATE("R8C",'Mapa final'!#REF!),"") -> #REF! | Y13: =IF(AND('Mapa final'!#REF!="Muy Alta",'Mapa final'!#REF!="Moderado"),CONCATENATE("R8C",'Mapa final'!#REF!),"") -> #REF! | Z13: =IF(AND('Mapa final'!#REF!="Muy Alta",'Mapa final'!#REF!="Moderado"),CONCATENATE("R8C",'Mapa final'!#REF!),"") -> #REF! | AA13: =IF(AND('Mapa final'!#REF!="Muy Alta",'Mapa final'!#REF!="Moderado"),CONCATENATE("R8C",'Mapa final'!#REF!),"") -> #REF! | AB13: =IF(AND('Mapa final'!#REF!="Muy Alta",'Mapa final'!#REF!="Mayor"),CONCATENATE("R8C",'Mapa final'!#REF!),"") -> #REF! | AC13: =IF(AND('Mapa final'!#REF!="Muy Alta",'Mapa final'!#REF!="Mayor"),CONCATENATE("R8C",'Mapa final'!#REF!),"") -> #REF! | AD13: =IF(AND('Mapa final'!#REF!="Muy Alta",'Mapa final'!#REF!="Mayor"),CONCATENATE("R8C",'Mapa final'!#REF!),"") -> #REF! | AE13: =IF(AND('Mapa final'!#REF!="Muy Alta",'Mapa final'!#REF!="Mayor"),CONCATENATE("R8C",'Mapa final'!#REF!),"") -> #REF! | AF13: =IF(AND('Mapa final'!#REF!="Muy Alta",'Mapa final'!#REF!="Mayor"),CONCATENATE("R8C",'Mapa final'!#REF!),"") -> #REF! | AG13: =IF(AND('Mapa final'!#REF!="Muy Alta",'Mapa final'!#REF!="Mayor"),CONCATENATE("R8C",'Mapa final'!#REF!),"") -> #REF! | AH13: =IF(AND('Mapa final'!#REF!="Muy Alta",'Mapa final'!#REF!="Catastrófico"),CONCATENATE("R8C",'Mapa final'!#REF!),"") -> #REF! | AI13: =IF(AND('Mapa final'!#REF!="Muy Alta",'Mapa final'!#REF!="Catastrófico"),CONCATENATE("R8C",'Mapa final'!#REF!),"") -> #REF! | AJ13: =IF(AND('Mapa final'!#REF!="Muy Alta",'Mapa final'!#REF!="Catastrófico"),CONCATENATE("R8C",'Mapa final'!#REF!),"") -> #REF! | AK13: =IF(AND('Mapa final'!#REF!="Muy Alta",'Mapa final'!#REF!="Catastrófico"),CONCATENATE("R8C",'Mapa final'!#REF!),"") -> #REF! | AL13: =IF(AND('Mapa final'!#REF!="Muy Alta",'Mapa final'!#REF!="Catastrófico"),CONCATENATE("R8C",'Mapa final'!#REF!),"") -> #REF! | AM13: =IF(AND('Mapa final'!#REF!="Muy Alta",'Mapa final'!#REF!="Catastrófico"),CONCATENATE("R8C",'Mapa final'!#REF!),"") -> #REF!
J14: =IF(AND('Mapa final'!#REF!="Muy Alta",'Mapa final'!#REF!="Leve"),CONCATENATE("R9C",'Mapa final'!#REF!),"") -> #REF! | K14: =IF(AND('Mapa final'!#REF!="Muy Alta",'Mapa final'!#REF!="Leve"),CONCATENATE("R9C",'Mapa final'!#REF!),"") -> #REF! | L14: =IF(AND('Mapa final'!#REF!="Muy Alta",'Mapa final'!#REF!="Leve"),CONCATENATE("R9C",'Mapa final'!#REF!),"") -> #REF! | M14: =IF(AND('Mapa final'!#REF!="Muy Alta",'Mapa final'!#REF!="Leve"),CONCATENATE("R9C",'Mapa final'!#REF!),"") -> #REF! | N14: =IF(AND('Mapa final'!#REF!="Muy Alta",'Mapa final'!#REF!="Leve"),CONCATENATE("R9C",'Mapa final'!#REF!),"") -> #REF! | O14: =IF(AND('Mapa final'!#REF!="Muy Alta",'Mapa final'!#REF!="Leve"),CONCATENATE("R9C",'Mapa final'!#REF!),"") -> #REF! | P14: =IF(AND('Mapa final'!#REF!="Muy Alta",'Mapa final'!#REF!="Menor"),CONCATENATE("R9C",'Mapa final'!#REF!),"") -> #REF! | Q14: =IF(AND('Mapa final'!#REF!="Muy Alta",'Mapa final'!#REF!="Menor"),CONCATENATE("R9C",'Mapa final'!#REF!),"") -> #REF! | R14: =IF(AND('Mapa final'!#REF!="Muy Alta",'Mapa final'!#REF!="Menor"),CONCATENATE("R9C",'Mapa final'!#REF!),"") -> #REF! | S14: =IF(AND('Mapa final'!#REF!="Muy Alta",'Mapa final'!#REF!="Menor"),CONCATENATE("R9C",'Mapa final'!#REF!),"") -> #REF! | T14: =IF(AND('Mapa final'!#REF!="Muy Alta",'Mapa final'!#REF!="Menor"),CONCATENATE("R9C",'Mapa final'!#REF!),"") -> #REF! | U14: =IF(AND('Mapa final'!#REF!="Muy Alta",'Mapa final'!#REF!="Menor"),CONCATENATE("R9C",'Mapa final'!#REF!),"") -> #REF! | V14: =IF(AND('Mapa final'!#REF!="Muy Alta",'Mapa final'!#REF!="Moderado"),CONCATENATE("R9C",'Mapa final'!#REF!),"") -> #REF! | W14: =IF(AND('Mapa final'!#REF!="Muy Alta",'Mapa final'!#REF!="Moderado"),CONCATENATE("R9C",'Mapa final'!#REF!),"") -> #REF! | X14: =IF(AND('Mapa final'!#REF!="Muy Alta",'Mapa final'!#REF!="Moderado"),CONCATENATE("R9C",'Mapa final'!#REF!),"") -> #REF! | Y14: =IF(AND('Mapa final'!#REF!="Muy Alta",'Mapa final'!#REF!="Moderado"),CONCATENATE("R9C",'Mapa final'!#REF!),"") -> #REF! | Z14: =IF(AND('Mapa final'!#REF!="Muy Alta",'Mapa final'!#REF!="Moderado"),CONCATENATE("R9C",'Mapa final'!#REF!),"") -> #REF! | AA14: =IF(AND('Mapa final'!#REF!="Muy Alta",'Mapa final'!#REF!="Moderado"),CONCATENATE("R9C",'Mapa final'!#REF!),"") -> #REF! | AB14: =IF(AND('Mapa final'!#REF!="Muy Alta",'Mapa final'!#REF!="Mayor"),CONCATENATE("R9C",'Mapa final'!#REF!),"") -> #REF! | AC14: =IF(AND('Mapa final'!#REF!="Muy Alta",'Mapa final'!#REF!="Mayor"),CONCATENATE("R9C",'Mapa final'!#REF!),"") -> #REF! | AD14: =IF(AND('Mapa final'!#REF!="Muy Alta",'Mapa final'!#REF!="Mayor"),CONCATENATE("R9C",'Mapa final'!#REF!),"") -> #REF! | AE14: =IF(AND('Mapa final'!#REF!="Muy Alta",'Mapa final'!#REF!="Mayor"),CONCATENATE("R9C",'Mapa final'!#REF!),"") -> #REF! | AF14: =IF(AND('Mapa final'!#REF!="Muy Alta",'Mapa final'!#REF!="Mayor"),CONCATENATE("R9C",'Mapa final'!#REF!),"") -> #REF! | AG14: =IF(AND('Mapa final'!#REF!="Muy Alta",'Mapa final'!#REF!="Mayor"),CONCATENATE("R9C",'Mapa final'!#REF!),"") -> #REF! | AH14: =IF(AND('Mapa final'!#REF!="Muy Alta",'Mapa final'!#REF!="Catastrófico"),CONCATENATE("R9C",'Mapa final'!#REF!),"") -> #REF! | AI14: =IF(AND('Mapa final'!#REF!="Muy Alta",'Mapa final'!#REF!="Catastrófico"),CONCATENATE("R9C",'Mapa final'!#REF!),"") -> #REF! | AJ14: =IF(AND('Mapa final'!#REF!="Muy Alta",'Mapa final'!#REF!="Catastrófico"),CONCATENATE("R9C",'Mapa final'!#REF!),"") -> #REF! | AK14: =IF(AND('Mapa final'!#REF!="Muy Alta",'Mapa final'!#REF!="Catastrófico"),CONCATENATE("R9C",'Mapa final'!#REF!),"") -> #REF! | AL14: =IF(AND('Mapa final'!#REF!="Muy Alta",'Mapa final'!#REF!="Catastrófico"),CONCATENATE("R9C",'Mapa final'!#REF!),"") -> #REF! | AM14: =IF(AND('Mapa final'!#REF!="Muy Alta",'Mapa final'!#REF!="Catastrófico"),CONCATENATE("R9C",'Mapa final'!#REF!),"") -> #REF!
J15: =IF(AND('Mapa final'!#REF!="Muy Alta",'Mapa final'!#REF!="Leve"),CONCATENATE("R10C",'Mapa final'!#REF!),"") -> #REF! | K15: =IF(AND('Mapa final'!#REF!="Muy Alta",'Mapa final'!#REF!="Leve"),CONCATENATE("R10C",'Mapa final'!#REF!),"") -> #REF! | L15: =IF(AND('Mapa final'!#REF!="Muy Alta",'Mapa final'!#REF!="Leve"),CONCATENATE("R10C",'Mapa final'!#REF!),"") -> #REF! | M15: =IF(AND('Mapa final'!#REF!="Muy Alta",'Mapa final'!#REF!="Leve"),CONCATENATE("R10C",'Mapa final'!#REF!),"") -> #REF! | N15: =IF(AND('Mapa final'!#REF!="Muy Alta",'Mapa final'!#REF!="Leve"),CONCATENATE("R10C",'Mapa final'!#REF!),"") -> #REF! | O15: =IF(AND('Mapa final'!#REF!="Muy Alta",'Mapa final'!#REF!="Leve"),CONCATENATE("R10C",'Mapa final'!#REF!),"") -> #REF! | P15: =IF(AND('Mapa final'!#REF!="Muy Alta",'Mapa final'!#REF!="Menor"),CONCATENATE("R10C",'Mapa final'!#REF!),"") -> #REF! | Q15: =IF(AND('Mapa final'!#REF!="Muy Alta",'Mapa final'!#REF!="Menor"),CONCATENATE("R10C",'Mapa final'!#REF!),"") -> #REF! | R15: =IF(AND('Mapa final'!#REF!="Muy Alta",'Mapa final'!#REF!="Menor"),CONCATENATE("R10C",'Mapa final'!#REF!),"") -> #REF! | S15: =IF(AND('Mapa final'!#REF!="Muy Alta",'Mapa final'!#REF!="Menor"),CONCATENATE("R10C",'Mapa final'!#REF!),"") -> #REF! | T15: =IF(AND('Mapa final'!#REF!="Muy Alta",'Mapa final'!#REF!="Menor"),CONCATENATE("R10C",'Mapa final'!#REF!),"") -> #REF! | U15: =IF(AND('Mapa final'!#REF!="Muy Alta",'Mapa final'!#REF!="Menor"),CONCATENATE("R10C",'Mapa final'!#REF!),"") -> #REF! | V15: =IF(AND('Mapa final'!#REF!="Muy Alta",'Mapa final'!#REF!="Moderado"),CONCATENATE("R10C",'Mapa final'!#REF!),"") -> #REF! | W15: =IF(AND('Mapa final'!#REF!="Muy Alta",'Mapa final'!#REF!="Moderado"),CONCATENATE("R10C",'Mapa final'!#REF!),"") -> #REF! | X15: =IF(AND('Mapa final'!#REF!="Muy Alta",'Mapa final'!#REF!="Moderado"),CONCATENATE("R10C",'Mapa final'!#REF!),"") -> #REF! | Y15: =IF(AND('Mapa final'!#REF!="Muy Alta",'Mapa final'!#REF!="Moderado"),CONCATENATE("R10C",'Mapa final'!#REF!),"") -> #REF! | Z15: =IF(AND('Mapa final'!#REF!="Muy Alta",'Mapa final'!#REF!="Moderado"),CONCATENATE("R10C",'Mapa final'!#REF!),"") -> #REF! | AA15: =IF(AND('Mapa final'!#REF!="Muy Alta",'Mapa final'!#REF!="Moderado"),CONCATENATE("R10C",'Mapa final'!#REF!),"") -> #REF! | AB15: =IF(AND('Mapa final'!#REF!="Muy Alta",'Mapa final'!#REF!="Mayor"),CONCATENATE("R10C",'Mapa final'!#REF!),"") -> #REF! | AC15: =IF(AND('Mapa final'!#REF!="Muy Alta",'Mapa final'!#REF!="Mayor"),CONCATENATE("R10C",'Mapa final'!#REF!),"") -> #REF! | AD15: =IF(AND('Mapa final'!#REF!="Muy Alta",'Mapa final'!#REF!="Mayor"),CONCATENATE("R10C",'Mapa final'!#REF!),"") -> #REF! | AE15: =IF(AND('Mapa final'!#REF!="Muy Alta",'Mapa final'!#REF!="Mayor"),CONCATENATE("R10C",'Mapa final'!#REF!),"") -> #REF! | AF15: =IF(AND('Mapa final'!#REF!="Muy Alta",'Mapa final'!#REF!="Mayor"),CONCATENATE("R10C",'Mapa final'!#REF!),"") -> #REF! | AG15: =IF(AND('Mapa final'!#REF!="Muy Alta",'Mapa final'!#REF!="Mayor"),CONCATENATE("R10C",'Mapa final'!#REF!),"") -> #REF! | AH15: =IF(AND('Mapa final'!#REF!="Muy Alta",'Mapa final'!#REF!="Catastrófico"),CONCATENATE("R10C",'Mapa final'!#REF!),"") -> #REF! | AI15: =IF(AND('Mapa final'!#REF!="Muy Alta",'Mapa final'!#REF!="Catastrófico"),CONCATENATE("R10C",'Mapa final'!#REF!),"") -> #REF! | AJ15: =IF(AND('Mapa final'!#REF!="Muy Alta",'Mapa final'!#REF!="Catastrófico"),CONCATENATE("R10C",'Mapa final'!#REF!),"") -> #REF! | AK15: =IF(AND('Mapa final'!#REF!="Muy Alta",'Mapa final'!#REF!="Catastrófico"),CONCATENATE("R10C",'Mapa final'!#REF!),"") -> #REF! | AL15: =IF(AND('Mapa final'!#REF!="Muy Alta",'Mapa final'!#REF!="Catastrófico"),CONCATENATE("R10C",'Mapa final'!#REF!),"") -> #REF! | AM15: =IF(AND('Mapa final'!#REF!="Muy Alta",'Mapa final'!#REF!="Catastrófico"),CONCATENATE("R10C",'Mapa final'!#REF!),"") -> #REF!
E16: Alta 80% | J16: =IF(AND('Mapa final'!$Y$13="Alta",'Mapa final'!$AA$13="Leve"),CONCATENATE("R1C",'Mapa final'!$O$13),"") | K16: =IF(AND('Mapa final'!$Y$14="Alta",'Mapa final'!$AA$14="Leve"),CONCATENATE("R1C",'Mapa final'!$O$14),"") | L16: =IF(AND('Mapa final'!$Y$15="Alta",'Mapa final'!$AA$15="Leve"),CONCATENATE("R1C",'Mapa final'!$O$15),"") | M16: =IF(AND('Mapa final'!$Y$16="Alta",'Mapa final'!$AA$16="Leve"),CONCATENATE("R1C",'Mapa final'!$O$16),"") | N16: =IF(AND('Mapa final'!$Y$17="Alta",'Mapa final'!$AA$17="Leve"),CONCATENATE("R1C",'Mapa final'!$O$17),"") | O16: =IF(AND('Mapa final'!$Y$18="Alta",'Mapa final'!$AA$18="Leve"),CONCATENATE("R1C",'Mapa final'!$O$18),"") | P16: =IF(AND('Mapa final'!$Y$13="Alta",'Mapa final'!$AA$13="Menor"),CONCATENATE("R1C",'Mapa final'!$O$13),"") | Q16: =IF(AND('Mapa final'!$Y$14="Alta",'Mapa final'!$AA$14="Menor"),CONCATENATE("R1C",'Mapa final'!$O$14),"") | R16: =IF(AND('Mapa final'!$Y$15="Alta",'Mapa final'!$AA$15="Menor"),CONCATENATE("R1C",'Mapa final'!$O$15),"") | S16: =IF(AND('Mapa final'!$Y$16="Alta",'Mapa final'!$AA$16="Menor"),CONCATENATE("R1C",'Mapa final'!$O$16),"") | T16: =IF(AND('Mapa final'!$Y$17="Alta",'Mapa final'!$AA$17="Menor"),CONCATENATE("R1C",'Mapa final'!$O$17),"") | U16: =IF(AND('Mapa final'!$Y$18="Alta",'Mapa final'!$AA$18="Menor"),CONCATENATE("R1C",'Mapa final'!$O$18),"") | V16: =IF(AND('Mapa final'!$Y$13="Alta",'Mapa final'!$AA$13="Moderado"),CONCATENATE("R1C",'Mapa final'!$O$13),"") | W16: =IF(AND('Mapa final'!$Y$14="Alta",'Mapa final'!$AA$14="Moderado"),CONCATENATE("R1C",'Mapa final'!$O$14),"") | X16: =IF(AND('Mapa final'!$Y$15="Alta",'Mapa final'!$AA$15="Moderado"),CONCATENATE("R1C",'Mapa final'!$O$15),"") | Y16: =IF(AND('Mapa final'!$Y$16="Alta",'Mapa final'!$AA$16="Moderado"),CONCATENATE("R1C",'Mapa final'!$O$16),"") | Z16: =IF(AND('Mapa final'!$Y$17="Alta",'Mapa final'!$AA$17="Moderado"),CONCATENATE("R1C",'Mapa final'!$O$17),"") | AA16: =IF(AND('Mapa final'!$Y$18="Alta",'Mapa final'!$AA$18="Moderado"),CONCATENATE("R1C",'Mapa final'!$O$18),"") | AB16: =IF(AND('Mapa final'!$Y$13="Alta",'Mapa final'!$AA$13="Mayor"),CONCATENATE("R1C",'Mapa final'!$O$13),"") | AC16: =IF(AND('Mapa final'!$Y$14="Alta",'Mapa final'!$AA$14="Mayor"),CONCATENATE("R1C",'Mapa final'!$O$14),"") | AD16: =IF(AND('Mapa final'!$Y$15="Alta",'Mapa final'!$AA$15="Mayor"),CONCATENATE("R1C",'Mapa final'!$O$15),"") | AE16: =IF(AND('Mapa final'!$Y$16="Alta",'Mapa final'!$AA$16="Mayor"),CONCATENATE("R1C",'Mapa final'!$O$16),"") | AF16: =IF(AND('Mapa final'!$Y$17="Alta",'Mapa final'!$AA$17="Mayor"),CONCATENATE("R1C",'Mapa final'!$O$17),"") | AG16: =IF(AND('Mapa final'!$Y$18="Alta",'Mapa final'!$AA$18="Mayor"),CONCATENATE("R1C",'Mapa final'!$O$18),"") | AH16: =IF(AND('Mapa final'!$Y$13="Alta",'Mapa final'!$AA$13="Catastrófico"),CONCATENATE("R1C",'Mapa final'!$O$13),"") | AI16: =IF(AND('Mapa final'!$Y$14="Alta",'Mapa final'!$AA$14="Catastrófico"),CONCATENATE("R1C",'Mapa final'!$O$14),"") | AJ16: =IF(AND('Mapa final'!$Y$15="Alta",'Mapa final'!$AA$15="Catastrófico"),CONCATENATE("R1C",'Mapa final'!$O$15),"") | AK16: =IF(AND('Mapa final'!$Y$16="Alta",'Mapa final'!$AA$16="Catastrófico"),CONCATENATE("R1C",'Mapa final'!$O$16),"") | AL16: =IF(AND('Mapa final'!$Y$17="Alta",'Mapa final'!$AA$17="Catastrófico"),CONCATENATE("R1C",'Mapa final'!$O$17),"") | AM16: =IF(AND('Mapa final'!$Y$18="Alta",'Mapa final'!$AA$18="Catastrófico"),CONCATENATE("R1C",'Mapa final'!$O$18),"") | AO16: Alto
J17: =IF(AND('Mapa final'!#REF!="Alta",'Mapa final'!#REF!="Leve"),CONCATENATE("R2C",'Mapa final'!#REF!),"") -> #REF! | K17: =IF(AND('Mapa final'!#REF!="Alta",'Mapa final'!#REF!="Leve"),CONCATENATE("R2C",'Mapa final'!#REF!),"") -> #REF! | L17: =IF(AND('Mapa final'!#REF!="Alta",'Mapa final'!#REF!="Leve"),CONCATENATE("R2C",'Mapa final'!#REF!),"") -> #REF! | M17: =IF(AND('Mapa final'!#REF!="Alta",'Mapa final'!#REF!="Leve"),CONCATENATE("R2C",'Mapa final'!#REF!),"") -> #REF! | N17: =IF(AND('Mapa final'!#REF!="Alta",'Mapa final'!#REF!="Leve"),CONCATENATE("R2C",'Mapa final'!#REF!),"") -> #REF! | O17: =IF(AND('Mapa final'!#REF!="Alta",'Mapa final'!#REF!="Leve"),CONCATENATE("R2C",'Mapa final'!#REF!),"") -> #REF! | P17: =IF(AND('Mapa final'!#REF!="Alta",'Mapa final'!#REF!="Menor"),CONCATENATE("R2C",'Mapa final'!#REF!),"") -> #REF! | Q17: =IF(AND('Mapa final'!#REF!="Alta",'Mapa final'!#REF!="Menor"),CONCATENATE("R2C",'Mapa final'!#REF!),"") -> #REF! | R17: =IF(AND('Mapa final'!#REF!="Alta",'Mapa final'!#REF!="Menor"),CONCATENATE("R2C",'Mapa final'!#REF!),"") -> #REF! | S17: =IF(AND('Mapa final'!#REF!="Alta",'Mapa final'!#REF!="Menor"),CONCATENATE("R2C",'Mapa final'!#REF!),"") -> #REF! | T17: =IF(AND('Mapa final'!#REF!="Alta",'Mapa final'!#REF!="Menor"),CONCATENATE("R2C",'Mapa final'!#REF!),"") -> #REF! | U17: =IF(AND('Mapa final'!#REF!="Alta",'Mapa final'!#REF!="Menor"),CONCATENATE("R2C",'Mapa final'!#REF!),"") -> #REF! | V17: =IF(AND('Mapa final'!#REF!="Alta",'Mapa final'!#REF!="Moderado"),CONCATENATE("R2C",'Mapa final'!#REF!),"") -> #REF! | W17: =IF(AND('Mapa final'!#REF!="Alta",'Mapa final'!#REF!="Moderado"),CONCATENATE("R2C",'Mapa final'!#REF!),"") -> #REF! | X17: =IF(AND('Mapa final'!#REF!="Alta",'Mapa final'!#REF!="Moderado"),CONCATENATE("R2C",'Mapa final'!#REF!),"") -> #REF! | Y17: =IF(AND('Mapa final'!#REF!="Alta",'Mapa final'!#REF!="Moderado"),CONCATENATE("R2C",'Mapa final'!#REF!),"") -> #REF! | Z17: =IF(AND('Mapa final'!#REF!="Alta",'Mapa final'!#REF!="Moderado"),CONCATENATE("R2C",'Mapa final'!#REF!),"") -> #REF! | AA17: =IF(AND('Mapa final'!#REF!="Alta",'Mapa final'!#REF!="Moderado"),CONCATENATE("R2C",'Mapa final'!#REF!),"") -> #REF! | AB17: =IF(AND('Mapa final'!#REF!="Alta",'Mapa final'!#REF!="Mayor"),CONCATENATE("R2C",'Mapa final'!#REF!),"") -> #REF! | AC17: =IF(AND('Mapa final'!#REF!="Alta",'Mapa final'!#REF!="Mayor"),CONCATENATE("R2C",'Mapa final'!#REF!),"") -> #REF! | AD17: =IF(AND('Mapa final'!#REF!="Alta",'Mapa final'!#REF!="Mayor"),CONCATENATE("R2C",'Mapa final'!#REF!),"") -> #REF! | AE17: =IF(AND('Mapa final'!#REF!="Alta",'Mapa final'!#REF!="Mayor"),CONCATENATE("R2C",'Mapa final'!#REF!),"") -> #REF! | AF17: =IF(AND('Mapa final'!#REF!="Alta",'Mapa final'!#REF!="Mayor"),CONCATENATE("R2C",'Mapa final'!#REF!),"") -> #REF! | AG17: =IF(AND('Mapa final'!#REF!="Alta",'Mapa final'!#REF!="Mayor"),CONCATENATE("R2C",'Mapa final'!#REF!),"") -> #REF! | AH17: =IF(AND('Mapa final'!#REF!="Alta",'Mapa final'!#REF!="Catastrófico"),CONCATENATE("R2C",'Mapa final'!#REF!),"") -> #REF! | AI17: =IF(AND('Mapa final'!#REF!="Alta",'Mapa final'!#REF!="Catastrófico"),CONCATENATE("R2C",'Mapa final'!#REF!),"") -> #REF! | AJ17: =IF(AND('Mapa final'!#REF!="Alta",'Mapa final'!#REF!="Catastrófico"),CONCATENATE("R2C",'Mapa final'!#REF!),"") -> #REF! | AK17: =IF(AND('Mapa final'!#REF!="Alta",'Mapa final'!#REF!="Catastrófico"),CONCATENATE("R2C",'Mapa final'!#REF!),"") -> #REF! | AL17: =IF(AND('Mapa final'!#REF!="Alta",'Mapa final'!#REF!="Catastrófico"),CONCATENATE("R2C",'Mapa final'!#REF!),"") -> #REF! | AM17: =IF(AND('Mapa final'!#REF!="Alta",'Mapa final'!#REF!="Catastrófico"),CONCATENATE("R2C",'Mapa final'!#REF!),"") -> #REF!
J18: =IF(AND('Mapa final'!#REF!="Alta",'Mapa final'!#REF!="Leve"),CONCATENATE("R3C",'Mapa final'!#REF!),"") -> #REF! | K18: =IF(AND('Mapa final'!#REF!="Alta",'Mapa final'!#REF!="Leve"),CONCATENATE("R3C",'Mapa final'!#REF!),"") -> #REF! | L18: =IF(AND('Mapa final'!#REF!="Alta",'Mapa final'!#REF!="Leve"),CONCATENATE("R3C",'Mapa final'!#REF!),"") -> #REF! | M18: =IF(AND('Mapa final'!#REF!="Alta",'Mapa final'!#REF!="Leve"),CONCATENATE("R3C",'Mapa final'!#REF!),"") -> #REF! | N18: =IF(AND('Mapa final'!#REF!="Alta",'Mapa final'!#REF!="Leve"),CONCATENATE("R3C",'Mapa final'!#REF!),"") -> #REF! | O18: =IF(AND('Mapa final'!#REF!="Alta",'Mapa final'!#REF!="Leve"),CONCATENATE("R3C",'Mapa final'!#REF!),"") -> #REF! | P18: =IF(AND('Mapa final'!#REF!="Alta",'Mapa final'!#REF!="Menor"),CONCATENATE("R3C",'Mapa final'!#REF!),"") -> #REF! | Q18: =IF(AND('Mapa final'!#REF!="Alta",'Mapa final'!#REF!="Menor"),CONCATENATE("R3C",'Mapa final'!#REF!),"") -> #REF! | R18: =IF(AND('Mapa final'!#REF!="Alta",'Mapa final'!#REF!="Menor"),CONCATENATE("R3C",'Mapa final'!#REF!),"") -> #REF! | S18: =IF(AND('Mapa final'!#REF!="Alta",'Mapa final'!#REF!="Menor"),CONCATENATE("R3C",'Mapa final'!#REF!),"") -> #REF! | T18: =IF(AND('Mapa final'!#REF!="Alta",'Mapa final'!#REF!="Menor"),CONCATENATE("R3C",'Mapa final'!#REF!),"") -> #REF! | U18: =IF(AND('Mapa final'!#REF!="Alta",'Mapa final'!#REF!="Menor"),CONCATENATE("R3C",'Mapa final'!#REF!),"") -> #REF! | V18: =IF(AND('Mapa final'!#REF!="Alta",'Mapa final'!#REF!="Moderado"),CONCATENATE("R3C",'Mapa final'!#REF!),"") -> #REF! | W18: =IF(AND('Mapa final'!#REF!="Alta",'Mapa final'!#REF!="Moderado"),CONCATENATE("R3C",'Mapa final'!#REF!),"") -> #REF! | X18: =IF(AND('Mapa final'!#REF!="Alta",'Mapa final'!#REF!="Moderado"),CONCATENATE("R3C",'Mapa final'!#REF!),"") -> #REF! | Y18: =IF(AND('Mapa final'!#REF!="Alta",'Mapa final'!#REF!="Moderado"),CONCATENATE("R3C",'Mapa final'!#REF!),"") -> #REF! | Z18: =IF(AND('Mapa final'!#REF!="Alta",'Mapa final'!#REF!="Moderado"),CONCATENATE("R3C",'Mapa final'!#REF!),"") -> #REF! | AA18: =IF(AND('Mapa final'!#REF!="Alta",'Mapa final'!#REF!="Moderado"),CONCATENATE("R3C",'Mapa final'!#REF!),"") -> #REF! | AB18: =IF(AND('Mapa final'!#REF!="Alta",'Mapa final'!#REF!="Mayor"),CONCATENATE("R3C",'Mapa final'!#REF!),"") -> #REF! | AC18: =IF(AND('Mapa final'!#REF!="Alta",'Mapa final'!#REF!="Mayor"),CONCATENATE("R3C",'Mapa final'!#REF!),"") -> #REF! | AD18: =IF(AND('Mapa final'!#REF!="Alta",'Mapa final'!#REF!="Mayor"),CONCATENATE("R3C",'Mapa final'!#REF!),"") -> #REF! | AE18: =IF(AND('Mapa final'!#REF!="Alta",'Mapa final'!#REF!="Mayor"),CONCATENATE("R3C",'Mapa final'!#REF!),"") -> #REF! | AF18: =IF(AND('Mapa final'!#REF!="Alta",'Mapa final'!#REF!="Mayor"),CONCATENATE("R3C",'Mapa final'!#REF!),"") -> #REF! | AG18: =IF(AND('Mapa final'!#REF!="Alta",'Mapa final'!#REF!="Mayor"),CONCATENATE("R3C",'Mapa final'!#REF!),"") -> #REF! | AH18: =IF(AND('Mapa final'!#REF!="Alta",'Mapa final'!#REF!="Catastrófico"),CONCATENATE("R3C",'Mapa final'!#REF!),"") -> #REF! | AI18: =IF(AND('Mapa final'!#REF!="Alta",'Mapa final'!#REF!="Catastrófico"),CONCATENATE("R3C",'Mapa final'!#REF!),"") -> #REF! | AJ18: =IF(AND('Mapa final'!#REF!="Alta",'Mapa final'!#REF!="Catastrófico"),CONCATENATE("R3C",'Mapa final'!#REF!),"") -> #REF! | AK18: =IF(AND('Mapa final'!#REF!="Alta",'Mapa final'!#REF!="Catastrófico"),CONCATENATE("R3C",'Mapa final'!#REF!),"") -> #REF! | AL18: =IF(AND('Mapa final'!#REF!="Alta",'Mapa final'!#REF!="Catastrófico"),CONCATENATE("R3C",'Mapa final'!#REF!),"") -> #REF! | AM18: =IF(AND('Mapa final'!#REF!="Alta",'Mapa final'!#REF!="Catastrófico"),CONCATENATE("R3C",'Mapa final'!#REF!),"") -> #REF!
J19: =IF(AND('Mapa final'!#REF!="Alta",'Mapa final'!#REF!="Leve"),CONCATENATE("R4C",'Mapa final'!#REF!),"") -> #REF! | K19: =IF(AND('Mapa final'!#REF!="Alta",'Mapa final'!#REF!="Leve"),CONCATENATE("R4C",'Mapa final'!#REF!),"") -> #REF! | L19: =IF(AND('Mapa final'!#REF!="Alta",'Mapa final'!#REF!="Leve"),CONCATENATE("R4C",'Mapa final'!#REF!),"") -> #REF! | M19: =IF(AND('Mapa final'!#REF!="Alta",'Mapa final'!#REF!="Leve"),CONCATENATE("R4C",'Mapa final'!#REF!),"") -> #REF! | N19: =IF(AND('Mapa final'!#REF!="Alta",'Mapa final'!#REF!="Leve"),CONCATENATE("R4C",'Mapa final'!#REF!),"") -> #REF! | O19: =IF(AND('Mapa final'!#REF!="Alta",'Mapa final'!#REF!="Leve"),CONCATENATE("R4C",'Mapa final'!#REF!),"") -> #REF! | P19: =IF(AND('Mapa final'!#REF!="Alta",'Mapa final'!#REF!="Menor"),CONCATENATE("R4C",'Mapa final'!#REF!),"") -> #REF! | Q19: =IF(AND('Mapa final'!#REF!="Alta",'Mapa final'!#REF!="Menor"),CONCATENATE("R4C",'Mapa final'!#REF!),"") -> #REF! | R19: =IF(AND('Mapa final'!#REF!="Alta",'Mapa final'!#REF!="Menor"),CONCATENATE("R4C",'Mapa final'!#REF!),"") -> #REF! | S19: =IF(AND('Mapa final'!#REF!="Alta",'Mapa final'!#REF!="Menor"),CONCATENATE("R4C",'Mapa final'!#REF!),"") -> #REF! | T19: =IF(AND('Mapa final'!#REF!="Alta",'Mapa final'!#REF!="Menor"),CONCATENATE("R4C",'Mapa final'!#REF!),"") -> #REF! | U19: =IF(AND('Mapa final'!#REF!="Alta",'Mapa final'!#REF!="Menor"),CONCATENATE("R4C",'Mapa final'!#REF!),"") -> #REF! | V19: =IF(AND('Mapa final'!#REF!="Alta",'Mapa final'!#REF!="Moderado"),CONCATENATE("R4C",'Mapa final'!#REF!),"") -> #REF! | W19: =IF(AND('Mapa final'!#REF!="Alta",'Mapa final'!#REF!="Moderado"),CONCATENATE("R4C",'Mapa final'!#REF!),"") -> #REF! | X19: =IF(AND('Mapa final'!#REF!="Alta",'Mapa final'!#REF!="Moderado"),CONCATENATE("R4C",'Mapa final'!#REF!),"") -> #REF! | Y19: =IF(AND('Mapa final'!#REF!="Alta",'Mapa final'!#REF!="Moderado"),CONCATENATE("R4C",'Mapa final'!#REF!),"") -> #REF! | Z19: =IF(AND('Mapa final'!#REF!="Alta",'Mapa final'!#REF!="Moderado"),CONCATENATE("R4C",'Mapa final'!#REF!),"") -> #REF! | AA19: =IF(AND('Mapa final'!#REF!="Alta",'Mapa final'!#REF!="Moderado"),CONCATENATE("R4C",'Mapa final'!#REF!),"") -> #REF! | AB19: =IF(AND('Mapa final'!#REF!="Alta",'Mapa final'!#REF!="Mayor"),CONCATENATE("R4C",'Mapa final'!#REF!),"") -> #REF! | AC19: =IF(AND('Mapa final'!#REF!="Alta",'Mapa final'!#REF!="Mayor"),CONCATENATE("R4C",'Mapa final'!#REF!),"") -> #REF! | AD19: =IF(AND('Mapa final'!#REF!="Alta",'Mapa final'!#REF!="Mayor"),CONCATENATE("R4C",'Mapa final'!#REF!),"") -> #REF! | AE19: =IF(AND('Mapa final'!#REF!="Alta",'Mapa final'!#REF!="Mayor"),CONCATENATE("R4C",'Mapa final'!#REF!),"") -> #REF! | AF19: =IF(AND('Mapa final'!#REF!="Alta",'Mapa final'!#REF!="Mayor"),CONCATENATE("R4C",'Mapa final'!#REF!),"") -> #REF! | AG19: =IF(AND('Mapa final'!#REF!="Alta",'Mapa final'!#REF!="Mayor"),CONCATENATE("R4C",'Mapa final'!#REF!),"") -> #REF! | AH19: =IF(AND('Mapa final'!#REF!="Alta",'Mapa final'!#REF!="Catastrófico"),CONCATENATE("R4C",'Mapa final'!#REF!),"") -> #REF! | AI19: =IF(AND('Mapa final'!#REF!="Alta",'Mapa final'!#REF!="Catastrófico"),CONCATENATE("R4C",'Mapa final'!#REF!),"") -> #REF! | AJ19: =IF(AND('Mapa final'!#REF!="Alta",'Mapa final'!#REF!="Catastrófico"),CONCATENATE("R4C",'Mapa final'!#REF!),"") -> #REF! | AK19: =IF(AND('Mapa final'!#REF!="Alta",'Mapa final'!#REF!="Catastrófico"),CONCATENATE("R4C",'Mapa final'!#REF!),"") -> #REF! | AL19: =IF(AND('Mapa final'!#REF!="Alta",'Mapa final'!#REF!="Catastrófico"),CONCATENATE("R4C",'Mapa final'!#REF!),"") -> #REF! | AM19: =IF(AND('Mapa final'!#REF!="Alta",'Mapa final'!#REF!="Catastrófico"),CONCATENATE("R4C",'Mapa final'!#REF!),"") -> #REF!
J20: =IF(AND('Mapa final'!#REF!="Alta",'Mapa final'!#REF!="Leve"),CONCATENATE("R5C",'Mapa final'!#REF!),"") -> #REF! | K20: =IF(AND('Mapa final'!#REF!="Alta",'Mapa final'!#REF!="Leve"),CONCATENATE("R5C",'Mapa final'!#REF!),"") -> #REF! | L20: =IF(AND('Mapa final'!#REF!="Alta",'Mapa final'!#REF!="Leve"),CONCATENATE("R5C",'Mapa final'!#REF!),"") -> #REF! | M20: =IF(AND('Mapa final'!#REF!="Alta",'Mapa final'!#REF!="Leve"),CONCATENATE("R5C",'Mapa final'!#REF!),"") -> #REF! | N20: =IF(AND('Mapa final'!#REF!="Alta",'Mapa final'!#REF!="Leve"),CONCATENATE("R5C",'Mapa final'!#REF!),"") -> #REF! | O20: =IF(AND('Mapa final'!#REF!="Alta",'Mapa final'!#REF!="Leve"),CONCATENATE("R5C",'Mapa final'!#REF!),"") -> #REF! | P20: =IF(AND('Mapa final'!#REF!="Alta",'Mapa final'!#REF!="Menor"),CONCATENATE("R5C",'Mapa final'!#REF!),"") -> #REF! | Q20: =IF(AND('Mapa final'!#REF!="Alta",'Mapa final'!#REF!="Menor"),CONCATENATE("R5C",'Mapa final'!#REF!),"") -> #REF! | R20: =IF(AND('Mapa final'!#REF!="Alta",'Mapa final'!#REF!="Menor"),CONCATENATE("R5C",'Mapa final'!#REF!),"") -> #REF! | S20: =IF(AND('Mapa final'!#REF!="Alta",'Mapa final'!#REF!="Menor"),CONCATENATE("R5C",'Mapa final'!#REF!),"") -> #REF! | T20: =IF(AND('Mapa final'!#REF!="Alta",'Mapa final'!#REF!="Menor"),CONCATENATE("R5C",'Mapa final'!#REF!),"") -> #REF! | U20: =IF(AND('Mapa final'!#REF!="Alta",'Mapa final'!#REF!="Menor"),CONCATENATE("R5C",'Mapa final'!#REF!),"") -> #REF! | V20: =IF(AND('Mapa final'!#REF!="Alta",'Mapa final'!#REF!="Moderado"),CONCATENATE("R5C",'Mapa final'!#REF!),"") -> #REF! | W20: =IF(AND('Mapa final'!#REF!="Alta",'Mapa final'!#REF!="Moderado"),CONCATENATE("R5C",'Mapa final'!#REF!),"") -> #REF! | X20: =IF(AND('Mapa final'!#REF!="Alta",'Mapa final'!#REF!="Moderado"),CONCATENATE("R5C",'Mapa final'!#REF!),"") -> #REF! | Y20: =IF(AND('Mapa final'!#REF!="Alta",'Mapa final'!#REF!="Moderado"),CONCATENATE("R5C",'Mapa final'!#REF!),"") -> #REF! | Z20: =IF(AND('Mapa final'!#REF!="Alta",'Mapa final'!#REF!="Moderado"),CONCATENATE("R5C",'Mapa final'!#REF!),"") -> #REF! | AA20: =IF(AND('Mapa final'!#REF!="Alta",'Mapa final'!#REF!="Moderado"),CONCATENATE("R5C",'Mapa final'!#REF!),"") -> #REF! | AB20: =IF(AND('Mapa final'!#REF!="Alta",'Mapa final'!#REF!="Mayor"),CONCATENATE("R5C",'Mapa final'!#REF!),"") -> #REF! | AC20: =IF(AND('Mapa final'!#REF!="Alta",'Mapa final'!#REF!="Mayor"),CONCATENATE("R5C",'Mapa final'!#REF!),"") -> #REF! | AD20: =IF(AND('Mapa final'!#REF!="Alta",'Mapa final'!#REF!="Mayor"),CONCATENATE("R5C",'Mapa final'!#REF!),"") -> #REF! | AE20: =IF(AND('Mapa final'!#REF!="Alta",'Mapa final'!#REF!="Mayor"),CONCATENATE("R5C",'Mapa final'!#REF!),"") -> #REF! | AF20: =IF(AND('Mapa final'!#REF!="Alta",'Mapa final'!#REF!="Mayor"),CONCATENATE("R5C",'Mapa final'!#REF!),"") -> #REF! | AG20: =IF(AND('Mapa final'!#REF!="Alta",'Mapa final'!#REF!="Mayor"),CONCATENATE("R5C",'Mapa final'!#REF!),"") -> #REF! | AH20: =IF(AND('Mapa final'!#REF!="Alta",'Mapa final'!#REF!="Catastrófico"),CONCATENATE("R5C",'Mapa final'!#REF!),"") -> #REF! | AI20: =IF(AND('Mapa final'!#REF!="Alta",'Mapa final'!#REF!="Catastrófico"),CONCATENATE("R5C",'Mapa final'!#REF!),"") -> #REF! | AJ20: =IF(AND('Mapa final'!#REF!="Alta",'Mapa final'!#REF!="Catastrófico"),CONCATENATE("R5C",'Mapa final'!#REF!),"") -> #REF! | AK20: =IF(AND('Mapa final'!#REF!="Alta",'Mapa final'!#REF!="Catastrófico"),CONCATENATE("R5C",'Mapa final'!#REF!),"") -> #REF! | AL20: =IF(AND('Mapa final'!#REF!="Alta",'Mapa final'!#REF!="Catastrófico"),CONCATENATE("R5C",'Mapa final'!#REF!),"") -> #REF! | AM20: =IF(AND('Mapa final'!#REF!="Alta",'Mapa final'!#REF!="Catastrófico"),CONCATENATE("R5C",'Mapa final'!#REF!),"") -> #REF!
J21: =IF(AND('Mapa final'!#REF!="Alta",'Mapa final'!#REF!="Leve"),CONCATENATE("R6C",'Mapa final'!#REF!),"") -> #REF! | K21: =IF(AND('Mapa final'!#REF!="Alta",'Mapa final'!#REF!="Leve"),CONCATENATE("R6C",'Mapa final'!#REF!),"") -> #REF! | L21: =IF(AND('Mapa final'!#REF!="Alta",'Mapa final'!#REF!="Leve"),CONCATENATE("R6C",'Mapa final'!#REF!),"") -> #REF! | M21: =IF(AND('Mapa final'!#REF!="Alta",'Mapa final'!#REF!="Leve"),CONCATENATE("R6C",'Mapa final'!#REF!),"") -> #REF! | N21: =IF(AND('Mapa final'!#REF!="Alta",'Mapa final'!#REF!="Leve"),CONCATENATE("R6C",'Mapa final'!#REF!),"") -> #REF! | O21: =IF(AND('Mapa final'!#REF!="Alta",'Mapa final'!#REF!="Leve"),CONCATENATE("R6C",'Mapa final'!#REF!),"") -> #REF! | P21: =IF(AND('Mapa final'!#REF!="Alta",'Mapa final'!#REF!="Menor"),CONCATENATE("R6C",'Mapa final'!#REF!),"") -> #REF! | Q21: =IF(AND('Mapa final'!#REF!="Alta",'Mapa final'!#REF!="Menor"),CONCATENATE("R6C",'Mapa final'!#REF!),"") -> #REF! | R21: =IF(AND('Mapa final'!#REF!="Alta",'Mapa final'!#REF!="Menor"),CONCATENATE("R6C",'Mapa final'!#REF!),"") -> #REF! | S21: =IF(AND('Mapa final'!#REF!="Alta",'Mapa final'!#REF!="Menor"),CONCATENATE("R6C",'Mapa final'!#REF!),"") -> #REF! | T21: =IF(AND('Mapa final'!#REF!="Alta",'Mapa final'!#REF!="Menor"),CONCATENATE("R6C",'Mapa final'!#REF!),"") -> #REF! | U21: =IF(AND('Mapa final'!#REF!="Alta",'Mapa final'!#REF!="Menor"),CONCATENATE("R6C",'Mapa final'!#REF!),"") -> #REF! | V21: =IF(AND('Mapa final'!#REF!="Alta",'Mapa final'!#REF!="Moderado"),CONCATENATE("R6C",'Mapa final'!#REF!),"") -> #REF! | W21: =IF(AND('Mapa final'!#REF!="Alta",'Mapa final'!#REF!="Moderado"),CONCATENATE("R6C",'Mapa final'!#REF!),"") -> #REF! | X21: =IF(AND('Mapa final'!#REF!="Alta",'Mapa final'!#REF!="Moderado"),CONCATENATE("R6C",'Mapa final'!#REF!),"") -> #REF! | Y21: =IF(AND('Mapa final'!#REF!="Alta",'Mapa final'!#REF!="Moderado"),CONCATENATE("R6C",'Mapa final'!#REF!),"") -> #REF! | Z21: =IF(AND('Mapa final'!#REF!="Alta",'Mapa final'!#REF!="Moderado"),CONCATENATE("R6C",'Mapa final'!#REF!),"") -> #REF! | AA21: =IF(AND('Mapa final'!#REF!="Alta",'Mapa final'!#REF!="Moderado"),CONCATENATE("R6C",'Mapa final'!#REF!),"") -> #REF! | AB21: =IF(AND('Mapa final'!#REF!="Alta",'Mapa final'!#REF!="Mayor"),CONCATENATE("R6C",'Mapa final'!#REF!),"") -> #REF! | AC21: =IF(AND('Mapa final'!#REF!="Alta",'Mapa final'!#REF!="Mayor"),CONCATENATE("R6C",'Mapa final'!#REF!),"") -> #REF! | AD21: =IF(AND('Mapa final'!#REF!="Alta",'Mapa final'!#REF!="Mayor"),CONCATENATE("R6C",'Mapa final'!#REF!),"") -> #REF! | AE21: =IF(AND('Mapa final'!#REF!="Alta",'Mapa final'!#REF!="Mayor"),CONCATENATE("R6C",'Mapa final'!#REF!),"") -> #REF! | AF21: =IF(AND('Mapa final'!#REF!="Alta",'Mapa final'!#REF!="Mayor"),CONCATENATE("R6C",'Mapa final'!#REF!),"") -> #REF! | AG21: =IF(AND('Mapa final'!#REF!="Alta",'Mapa final'!#REF!="Mayor"),CONCATENATE("R6C",'Mapa final'!#REF!),"") -> #REF! | AH21: =IF(AND('Mapa final'!#REF!="Alta",'Mapa final'!#REF!="Catastrófico"),CONCATENATE("R6C",'Mapa final'!#REF!),"") -> #REF! | AI21: =IF(AND('Mapa final'!#REF!="Alta",'Mapa final'!#REF!="Catastrófico"),CONCATENATE("R6C",'Mapa final'!#REF!),"") -> #REF! | AJ21: =IF(AND('Mapa final'!#REF!="Alta",'Mapa final'!#REF!="Catastrófico"),CONCATENATE("R6C",'Mapa final'!#REF!),"") -> #REF! | AK21: =IF(AND('Mapa final'!#REF!="Alta",'Mapa final'!#REF!="Catastrófico"),CONCATENATE("R6C",'Mapa final'!#REF!),"") -> #REF! | AL21: =IF(AND('Mapa final'!#REF!="Alta",'Mapa final'!#REF!="Catastrófico"),CONCATENATE("R6C",'Mapa final'!#REF!),"") -> #REF! | AM21: =IF(AND('Mapa final'!#REF!="Alta",'Mapa final'!#REF!="Catastrófico"),CONCATENATE("R6C",'Mapa final'!#REF!),"") -> #REF!
J22: =IF(AND('Mapa final'!#REF!="Alta",'Mapa final'!#REF!="Leve"),CONCATENATE("R7C",'Mapa final'!#REF!),"") -> #REF! | K22: =IF(AND('Mapa final'!#REF!="Alta",'Mapa final'!#REF!="Leve"),CONCATENATE("R7C",'Mapa final'!#REF!),"") -> #REF! | L22: =IF(AND('Mapa final'!#REF!="Alta",'Mapa final'!#REF!="Leve"),CONCATENATE("R7C",'Mapa final'!#REF!),"") -> #REF! | M22: =IF(AND('Mapa final'!#REF!="Alta",'Mapa final'!#REF!="Leve"),CONCATENATE("R7C",'Mapa final'!#REF!),"") -> #REF! | N22: =IF(AND('Mapa final'!#REF!="Alta",'Mapa final'!#REF!="Leve"),CONCATENATE("R7C",'Mapa final'!#REF!),"") -> #REF! | O22: =IF(AND('Mapa final'!#REF!="Alta",'Mapa final'!#REF!="Leve"),CONCATENATE("R7C",'Mapa final'!#REF!),"") -> #REF! | P22: =IF(AND('Mapa final'!#REF!="Alta",'Mapa final'!#REF!="Menor"),CONCATENATE("R7C",'Mapa final'!#REF!),"") -> #REF! | Q22: =IF(AND('Mapa final'!#REF!="Alta",'Mapa final'!#REF!="Menor"),CONCATENATE("R7C",'Mapa final'!#REF!),"") -> #REF! | R22: =IF(AND('Mapa final'!#REF!="Alta",'Mapa final'!#REF!="Menor"),CONCATENATE("R7C",'Mapa final'!#REF!),"") -> #REF! | S22: =IF(AND('Mapa final'!#REF!="Alta",'Mapa final'!#REF!="Menor"),CONCATENATE("R7C",'Mapa final'!#REF!),"") -> #REF! | T22: =IF(AND('Mapa final'!#REF!="Alta",'Mapa final'!#REF!="Menor"),CONCATENATE("R7C",'Mapa final'!#REF!),"") -> #REF! | U22: =IF(AND('Mapa final'!#REF!="Alta",'Mapa final'!#REF!="Menor"),CONCATENATE("R7C",'Mapa final'!#REF!),"") -> #REF! | V22: =IF(AND('Mapa final'!#REF!="Alta",'Mapa final'!#REF!="Moderado"),CONCATENATE("R7C",'Mapa final'!#REF!),"") -> #REF! | W22: =IF(AND('Mapa final'!#REF!="Alta",'Mapa final'!#REF!="Moderado"),CONCATENATE("R7C",'Mapa final'!#REF!),"") -> #REF! | X22: =IF(AND('Mapa final'!#REF!="Alta",'Mapa final'!#REF!="Moderado"),CONCATENATE("R7C",'Mapa final'!#REF!),"") -> #REF! | Y22: =IF(AND('Mapa final'!#REF!="Alta",'Mapa final'!#REF!="Moderado"),CONCATENATE("R7C",'Mapa final'!#REF!),"") -> #REF! | Z22: =IF(AND('Mapa final'!#REF!="Alta",'Mapa final'!#REF!="Moderado"),CONCATENATE("R7C",'Mapa final'!#REF!),"") -> #REF! | AA22: =IF(AND('Mapa final'!#REF!="Alta",'Mapa final'!#REF!="Moderado"),CONCATENATE("R7C",'Mapa final'!#REF!),"") -> #REF! | AB22: =IF(AND('Mapa final'!#REF!="Alta",'Mapa final'!#REF!="Mayor"),CONCATENATE("R7C",'Mapa final'!#REF!),"") -> #REF! | AC22: =IF(AND('Mapa final'!#REF!="Alta",'Mapa final'!#REF!="Mayor"),CONCATENATE("R7C",'Mapa final'!#REF!),"") -> #REF! | AD22: =IF(AND('Mapa final'!#REF!="Alta",'Mapa final'!#REF!="Mayor"),CONCATENATE("R7C",'Mapa final'!#REF!),"") -> #REF! | AE22: =IF(AND('Mapa final'!#REF!="Alta",'Mapa final'!#REF!="Mayor"),CONCATENATE("R7C",'Mapa final'!#REF!),"") -> #REF! | AF22: =IF(AND('Mapa final'!#REF!="Alta",'Mapa final'!#REF!="Mayor"),CONCATENATE("R7C",'Mapa final'!#REF!),"") -> #REF! | AG22: =IF(AND('Mapa final'!#REF!="Alta",'Mapa final'!#REF!="Mayor"),CONCATENATE("R7C",'Mapa final'!#REF!),"") -> #REF! | AH22: =IF(AND('Mapa final'!#REF!="Alta",'Mapa final'!#REF!="Catastrófico"),CONCATENATE("R7C",'Mapa final'!#REF!),"") -> #REF! | AI22: =IF(AND('Mapa final'!#REF!="Alta",'Mapa final'!#REF!="Catastrófico"),CONCATENATE("R7C",'Mapa final'!#REF!),"") -> #REF! | AJ22: =IF(AND('Mapa final'!#REF!="Alta",'Mapa final'!#REF!="Catastrófico"),CONCATENATE("R7C",'Mapa final'!#REF!),"") -> #REF! | AK22: =IF(AND('Mapa final'!#REF!="Alta",'Mapa final'!#REF!="Catastrófico"),CONCATENATE("R7C",'Mapa final'!#REF!),"") -> #REF! | AL22: =IF(AND('Mapa final'!#REF!="Alta",'Mapa final'!#REF!="Catastrófico"),CONCATENATE("R7C",'Mapa final'!#REF!),"") -> #REF! | AM22: =IF(AND('Mapa final'!#REF!="Alta",'Mapa final'!#REF!="Catastrófico"),CONCATENATE("R7C",'Mapa final'!#REF!),"") -> #REF!
J23: =IF(AND('Mapa final'!#REF!="Alta",'Mapa final'!#REF!="Leve"),CONCATENATE("R8C",'Mapa final'!#REF!),"") -> #REF! | K23: =IF(AND('Mapa final'!#REF!="Alta",'Mapa final'!#REF!="Leve"),CONCATENATE("R8C",'Mapa final'!#REF!),"") -> #REF! | L23: =IF(AND('Mapa final'!#REF!="Alta",'Mapa final'!#REF!="Leve"),CONCATENATE("R8C",'Mapa final'!#REF!),"") -> #REF! | M23: =IF(AND('Mapa final'!#REF!="Alta",'Mapa final'!#REF!="Leve"),CONCATENATE("R8C",'Mapa final'!#REF!),"") -> #REF! | N23: =IF(AND('Mapa final'!#REF!="Alta",'Mapa final'!#REF!="Leve"),CONCATENATE("R8C",'Mapa final'!#REF!),"") -> #REF! | O23: =IF(AND('Mapa final'!#REF!="Alta",'Mapa final'!#REF!="Leve"),CONCATENATE("R8C",'Mapa final'!#REF!),"") -> #REF! | P23: =IF(AND('Mapa final'!#REF!="Alta",'Mapa final'!#REF!="Menor"),CONCATENATE("R8C",'Mapa final'!#REF!),"") -> #REF! | Q23: =IF(AND('Mapa final'!#REF!="Alta",'Mapa final'!#REF!="Menor"),CONCATENATE("R8C",'Mapa final'!#REF!),"") -> #REF! | R23: =IF(AND('Mapa final'!#REF!="Alta",'Mapa final'!#REF!="Menor"),CONCATENATE("R8C",'Mapa final'!#REF!),"") -> #REF! | S23: =IF(AND('Mapa final'!#REF!="Alta",'Mapa final'!#REF!="Menor"),CONCATENATE("R8C",'Mapa final'!#REF!),"") -> #REF! | T23: =IF(AND('Mapa final'!#REF!="Alta",'Mapa final'!#REF!="Menor"),CONCATENATE("R8C",'Mapa final'!#REF!),"") -> #REF! | U23: =IF(AND('Mapa final'!#REF!="Alta",'Mapa final'!#REF!="Menor"),CONCATENATE("R8C",'Mapa final'!#REF!),"") -> #REF! | V23: =IF(AND('Mapa final'!#REF!="Alta",'Mapa final'!#REF!="Moderado"),CONCATENATE("R8C",'Mapa final'!#REF!),"") -> #REF! | W23: =IF(AND('Mapa final'!#REF!="Alta",'Mapa final'!#REF!="Moderado"),CONCATENATE("R8C",'Mapa final'!#REF!),"") -> #REF! | X23: =IF(AND('Mapa final'!#REF!="Alta",'Mapa final'!#REF!="Moderado"),CONCATENATE("R8C",'Mapa final'!#REF!),"") -> #REF! | Y23: =IF(AND('Mapa final'!#REF!="Alta",'Mapa final'!#REF!="Moderado"),CONCATENATE("R8C",'Mapa final'!#REF!),"") -> #REF! | Z23: =IF(AND('Mapa final'!#REF!="Alta",'Mapa final'!#REF!="Moderado"),CONCATENATE("R8C",'Mapa final'!#REF!),"") -> #REF! | AA23: =IF(AND('Mapa final'!#REF!="Alta",'Mapa final'!#REF!="Moderado"),CONCATENATE("R8C",'Mapa final'!#REF!),"") -> #REF! | AB23: =IF(AND('Mapa final'!#REF!="Alta",'Mapa final'!#REF!="Mayor"),CONCATENATE("R8C",'Mapa final'!#REF!),"") -> #REF! | AC23: =IF(AND('Mapa final'!#REF!="Alta",'Mapa final'!#REF!="Mayor"),CONCATENATE("R8C",'Mapa final'!#REF!),"") -> #REF! | AD23: =IF(AND('Mapa final'!#REF!="Alta",'Mapa final'!#REF!="Mayor"),CONCATENATE("R8C",'Mapa final'!#REF!),"") -> #REF! | AE23: =IF(AND('Mapa final'!#REF!="Alta",'Mapa final'!#REF!="Mayor"),CONCATENATE("R8C",'Mapa final'!#REF!),"") -> #REF! | AF23: =IF(AND('Mapa final'!#REF!="Alta",'Mapa final'!#REF!="Mayor"),CONCATENATE("R8C",'Mapa final'!#REF!),"") -> #REF! | AG23: =IF(AND('Mapa final'!#REF!="Alta",'Mapa final'!#REF!="Mayor"),CONCATENATE("R8C",'Mapa final'!#REF!),"") -> #REF! | AH23: =IF(AND('Mapa final'!#REF!="Alta",'Mapa final'!#REF!="Catastrófico"),CONCATENATE("R8C",'Mapa final'!#REF!),"") -> #REF! | AI23: =IF(AND('Mapa final'!#REF!="Alta",'Mapa final'!#REF!="Catastrófico"),CONCATENATE("R8C",'Mapa final'!#REF!),"") -> #REF! | AJ23: =IF(AND('Mapa final'!#REF!="Alta",'Mapa final'!#REF!="Catastrófico"),CONCATENATE("R8C",'Mapa final'!#REF!),"") -> #REF! | AK23: =IF(AND('Mapa final'!#REF!="Alta",'Mapa final'!#REF!="Catastrófico"),CONCATENATE("R8C",'Mapa final'!#REF!),"") -> #REF! | AL23: =IF(AND('Mapa final'!#REF!="Alta",'Mapa final'!#REF!="Catastrófico"),CONCATENATE("R8C",'Mapa final'!#REF!),"") -> #REF! | AM23: =IF(AND('Mapa final'!#REF!="Alta",'Mapa final'!#REF!="Catastrófico"),CONCATENATE("R8C",'Mapa final'!#REF!),"") -> #REF!
J24: =IF(AND('Mapa final'!#REF!="Alta",'Mapa final'!#REF!="Leve"),CONCATENATE("R9C",'Mapa final'!#REF!),"") -> #REF! | K24: =IF(AND('Mapa final'!#REF!="Alta",'Mapa final'!#REF!="Leve"),CONCATENATE("R9C",'Mapa final'!#REF!),"") -> #REF! | L24: =IF(AND('Mapa final'!#REF!="Alta",'Mapa final'!#REF!="Leve"),CONCATENATE("R9C",'Mapa final'!#REF!),"") -> #REF! | M24: =IF(AND('Mapa final'!#REF!="Alta",'Mapa final'!#REF!="Leve"),CONCATENATE("R9C",'Mapa final'!#REF!),"") -> #REF! | N24: =IF(AND('Mapa final'!#REF!="Alta",'Mapa final'!#REF!="Leve"),CONCATENATE("R9C",'Mapa final'!#REF!),"") -> #REF! | O24: =IF(AND('Mapa final'!#REF!="Alta",'Mapa final'!#REF!="Leve"),CONCATENATE("R9C",'Mapa final'!#REF!),"") -> #REF! | P24: =IF(AND('Mapa final'!#REF!="Alta",'Mapa final'!#REF!="Menor"),CONCATENATE("R9C",'Mapa final'!#REF!),"") -> #REF! | Q24: =IF(AND('Mapa final'!#REF!="Alta",'Mapa final'!#REF!="Menor"),CONCATENATE("R9C",'Mapa final'!#REF!),"") -> #REF! | R24: =IF(AND('Mapa final'!#REF!="Alta",'Mapa final'!#REF!="Menor"),CONCATENATE("R9C",'Mapa final'!#REF!),"") -> #REF! | S24: =IF(AND('Mapa final'!#REF!="Alta",'Mapa final'!#REF!="Menor"),CONCATENATE("R9C",'Mapa final'!#REF!),"") -> #REF! | T24: =IF(AND('Mapa final'!#REF!="Alta",'Mapa final'!#REF!="Menor"),CONCATENATE("R9C",'Mapa final'!#REF!),"") -> #REF! | U24: =IF(AND('Mapa final'!#REF!="Alta",'Mapa final'!#REF!="Menor"),CONCATENATE("R9C",'Mapa final'!#REF!),"") -> #REF! | V24: =IF(AND('Mapa final'!#REF!="Alta",'Mapa final'!#REF!="Moderado"),CONCATENATE("R9C",'Mapa final'!#REF!),"") -> #REF! | W24: =IF(AND('Mapa final'!#REF!="Alta",'Mapa final'!#REF!="Moderado"),CONCATENATE("R9C",'Mapa final'!#REF!),"") -> #REF! | X24: =IF(AND('Mapa final'!#REF!="Alta",'Mapa final'!#REF!="Moderado"),CONCATENATE("R9C",'Mapa final'!#REF!),"") -> #REF! | Y24: =IF(AND('Mapa final'!#REF!="Alta",'Mapa final'!#REF!="Moderado"),CONCATENATE("R9C",'Mapa final'!#REF!),"") -> #REF! | Z24: =IF(AND('Mapa final'!#REF!="Alta",'Mapa final'!#REF!="Moderado"),CONCATENATE("R9C",'Mapa final'!#REF!),"") -> #REF! | AA24: =IF(AND('Mapa final'!#REF!="Alta",'Mapa final'!#REF!="Moderado"),CONCATENATE("R9C",'Mapa final'!#REF!),"") -> #REF! | AB24: =IF(AND('Mapa final'!#REF!="Alta",'Mapa final'!#REF!="Mayor"),CONCATENATE("R9C",'Mapa final'!#REF!),"") -> #REF! | AC24: =IF(AND('Mapa final'!#REF!="Alta",'Mapa final'!#REF!="Mayor"),CONCATENATE("R9C",'Mapa final'!#REF!),"") -> #REF! | AD24: =IF(AND('Mapa final'!#REF!="Alta",'Mapa final'!#REF!="Mayor"),CONCATENATE("R9C",'Mapa final'!#REF!),"") -> #REF! | AE24: =IF(AND('Mapa final'!#REF!="Alta",'Mapa final'!#REF!="Mayor"),CONCATENATE("R9C",'Mapa final'!#REF!),"") -> #REF! | AF24: =IF(AND('Mapa final'!#REF!="Alta",'Mapa final'!#REF!="Mayor"),CONCATENATE("R9C",'Mapa final'!#REF!),"") -> #REF! | AG24: =IF(AND('Mapa final'!#REF!="Alta",'Mapa final'!#REF!="Mayor"),CONCATENATE("R9C",'Mapa final'!#REF!),"") -> #REF! | AH24: =IF(AND('Mapa final'!#REF!="Alta",'Mapa final'!#REF!="Catastrófico"),CONCATENATE("R9C",'Mapa final'!#REF!),"") -> #REF! | AI24: =IF(AND('Mapa final'!#REF!="Alta",'Mapa final'!#REF!="Catastrófico"),CONCATENATE("R9C",'Mapa final'!#REF!),"") -> #REF! | AJ24: =IF(AND('Mapa final'!#REF!="Alta",'Mapa final'!#REF!="Catastrófico"),CONCATENATE("R9C",'Mapa final'!#REF!),"") -> #REF! | AK24: =IF(AND('Mapa final'!#REF!="Alta",'Mapa final'!#REF!="Catastrófico"),CONCATENATE("R9C",'Mapa final'!#REF!),"") -> #REF! | AL24: =IF(AND('Mapa final'!#REF!="Alta",'Mapa final'!#REF!="Catastrófico"),CONCATENATE("R9C",'Mapa final'!#REF!),"") -> #REF! | AM24: =IF(AND('Mapa final'!#REF!="Alta",'Mapa final'!#REF!="Catastrófico"),CONCATENATE("R9C",'Mapa final'!#REF!),"") -> #REF!
J25: =IF(AND('Mapa final'!#REF!="Alta",'Mapa final'!#REF!="Leve"),CONCATENATE("R10C",'Mapa final'!#REF!),"") -> #REF! | K25: =IF(AND('Mapa final'!#REF!="Alta",'Mapa final'!#REF!="Leve"),CONCATENATE("R10C",'Mapa final'!#REF!),"") -> #REF! | L25: =IF(AND('Mapa final'!#REF!="Alta",'Mapa final'!#REF!="Leve"),CONCATENATE("R10C",'Mapa final'!#REF!),"") -> #REF! | M25: =IF(AND('Mapa final'!#REF!="Alta",'Mapa final'!#REF!="Leve"),CONCATENATE("R10C",'Mapa final'!#REF!),"") -> #REF! | N25: =IF(AND('Mapa final'!#REF!="Alta",'Mapa final'!#REF!="Leve"),CONCATENATE("R10C",'Mapa final'!#REF!),"") -> #REF! | O25: =IF(AND('Mapa final'!#REF!="Alta",'Mapa final'!#REF!="Leve"),CONCATENATE("R10C",'Mapa final'!#REF!),"") -> #REF! | P25: =IF(AND('Mapa final'!#REF!="Alta",'Mapa final'!#REF!="Menor"),CONCATENATE("R10C",'Mapa final'!#REF!),"") -> #REF! | Q25: =IF(AND('Mapa final'!#REF!="Alta",'Mapa final'!#REF!="Menor"),CONCATENATE("R10C",'Mapa final'!#REF!),"") -> #REF! | R25: =IF(AND('Mapa final'!#REF!="Alta",'Mapa final'!#REF!="Menor"),CONCATENATE("R10C",'Mapa final'!#REF!),"") -> #REF! | S25: =IF(AND('Mapa final'!#REF!="Alta",'Mapa final'!#REF!="Menor"),CONCATENATE("R10C",'Mapa final'!#REF!),"") -> #REF! | T25: =IF(AND('Mapa final'!#REF!="Alta",'Mapa final'!#REF!="Menor"),CONCATENATE("R10C",'Mapa final'!#REF!),"") -> #REF! | U25: =IF(AND('Mapa final'!#REF!="Alta",'Mapa final'!#REF!="Menor"),CONCATENATE("R10C",'Mapa final'!#REF!),"") -> #REF! | V25: =IF(AND('Mapa final'!#REF!="Alta",'Mapa final'!#REF!="Moderado"),CONCATENATE("R10C",'Mapa final'!#REF!),"") -> #REF! | W25: =IF(AND('Mapa final'!#REF!="Alta",'Mapa final'!#REF!="Moderado"),CONCATENATE("R10C",'Mapa final'!#REF!),"") -> #REF! | X25: =IF(AND('Mapa final'!#REF!="Alta",'Mapa final'!#REF!="Moderado"),CONCATENATE("R10C",'Mapa final'!#REF!),"") -> #REF! | Y25: =IF(AND('Mapa final'!#REF!="Alta",'Mapa final'!#REF!="Moderado"),CONCATENATE("R10C",'Mapa final'!#REF!),"") -> #REF! | Z25: =IF(AND('Mapa final'!#REF!="Alta",'Mapa final'!#REF!="Moderado"),CONCATENATE("R10C",'Mapa final'!#REF!),"") -> #REF! | AA25: =IF(AND('Mapa final'!#REF!="Alta",'Mapa final'!#REF!="Moderado"),CONCATENATE("R10C",'Mapa final'!#REF!),"") -> #REF! | AB25: =IF(AND('Mapa final'!#REF!="Alta",'Mapa final'!#REF!="Mayor"),CONCATENATE("R10C",'Mapa final'!#REF!),"") -> #REF! | AC25: =IF(AND('Mapa final'!#REF!="Alta",'Mapa final'!#REF!="Mayor"),CONCATENATE("R10C",'Mapa final'!#REF!),"") -> #REF! | AD25: =IF(AND('Mapa final'!#REF!="Alta",'Mapa final'!#REF!="Mayor"),CONCATENATE("R10C",'Mapa final'!#REF!),"") -> #REF! | AE25: =IF(AND('Mapa final'!#REF!="Alta",'Mapa final'!#REF!="Mayor"),CONCATENATE("R10C",'Mapa final'!#REF!),"") -> #REF! | AF25: =IF(AND('Mapa final'!#REF!="Alta",'Mapa final'!#REF!="Mayor"),CONCATENATE("R10C",'Mapa final'!#REF!),"") -> #REF! | AG25: =IF(AND('Mapa final'!#REF!="Alta",'Mapa final'!#REF!="Mayor"),CONCATENATE("R10C",'Mapa final'!#REF!),"") -> #REF! | AH25: =IF(AND('Mapa final'!#REF!="Alta",'Mapa final'!#REF!="Catastrófico"),CONCATENATE("R10C",'Mapa final'!#REF!),"") -> #REF! | AI25: =IF(AND('Mapa final'!#REF!="Alta",'Mapa final'!#REF!="Catastrófico"),CONCATENATE("R10C",'Mapa final'!#REF!),"") -> #REF! | AJ25: =IF(AND('Mapa final'!#REF!="Alta",'Mapa final'!#REF!="Catastrófico"),CONCATENATE("R10C",'Mapa final'!#REF!),"") -> #REF! | AK25: =IF(AND('Mapa final'!#REF!="Alta",'Mapa final'!#REF!="Catastrófico"),CONCATENATE("R10C",'Mapa final'!#REF!),"") -> #REF! | AL25: =IF(AND('Mapa final'!#REF!="Alta",'Mapa final'!#REF!="Catastrófico"),CONCATENATE("R10C",'Mapa final'!#REF!),"") -> #REF! | AM25: =IF(AND('Mapa final'!#REF!="Alta",'Mapa final'!#REF!="Catastrófico"),CONCATENATE("R10C",'Mapa final'!#REF!),"") -> #REF!
E26: Media 60% | J26: =IF(AND('Mapa final'!$Y$13="Media",'Mapa final'!$AA$13="Leve"),CONCATENATE("R1C",'Mapa final'!$O$13),"") | K26: =IF(AND('Mapa final'!$Y$14="Media",'Mapa final'!$AA$14="Leve"),CONCATENATE("R1C",'Mapa final'!$O$14),"") | L26: =IF(AND('Mapa final'!$Y$15="Media",'Mapa final'!$AA$15="Leve"),CONCATENATE("R1C",'Mapa final'!$O$15),"") | M26: =IF(AND('Mapa final'!$Y$16="Media",'Mapa final'!$AA$16="Leve"),CONCATENATE("R1C",'Mapa final'!$O$16),"") | N26: =IF(AND('Mapa final'!$Y$17="Media",'Mapa final'!$AA$17="Leve"),CONCATENATE("R1C",'Mapa final'!$O$17),"") | O26: =IF(AND('Mapa final'!$Y$18="Media",'Mapa final'!$AA$18="Leve"),CONCATENATE("R1C",'Mapa final'!$O$18),"") | P26: =IF(AND('Mapa final'!$Y$13="Media",'Mapa final'!$AA$13="Menor"),CONCATENATE("R1C",'Mapa final'!$O$13),"") | Q26: =IF(AND('Mapa final'!$Y$14="Media",'Mapa final'!$AA$14="Menor"),CONCATENATE("R1C",'Mapa final'!$O$14),"") | R26: =IF(AND('Mapa final'!$Y$15="Media",'Mapa final'!$AA$15="Menor"),CONCATENATE("R1C",'Mapa final'!$O$15),"") | S26: =IF(AND('Mapa final'!$Y$16="Media",'Mapa final'!$AA$16="Menor"),CONCATENATE("R1C",'Mapa final'!$O$16),"") | T26: =IF(AND('Mapa final'!$Y$17="Media",'Mapa final'!$AA$17="Menor"),CONCATENATE("R1C",'Mapa final'!$O$17),"") | U26: =IF(AND('Mapa final'!$Y$18="Media",'Mapa final'!$AA$18="Menor"),CONCATENATE("R1C",'Mapa final'!$O$18),"") | V26: =IF(AND('Mapa final'!$Y$13="Media",'Mapa final'!$AA$13="Moderado"),CONCATENATE("R1C",'Mapa final'!$O$13),"") | W26: =IF(AND('Mapa final'!$Y$14="Media",'Mapa final'!$AA$14="Moderado"),CONCATENATE("R1C",'Mapa final'!$O$14),"") | X26: =IF(AND('Mapa final'!$Y$15="Media",'Mapa final'!$AA$15="Moderado"),CONCATENATE("R1C",'Mapa final'!$O$15),"") | Y26: =IF(AND('Mapa final'!$Y$16="Media",'Mapa final'!$AA$16="Moderado"),CONCATENATE("R1C",'Mapa final'!$O$16),"") | Z26: =IF(AND('Mapa final'!$Y$17="Media",'Mapa final'!$AA$17="Moderado"),CONCATENATE("R1C",'Mapa final'!$O$17),"") | AA26: =IF(AND('Mapa final'!$Y$18="Media",'Mapa final'!$AA$18="Moderado"),CONCATENATE("R1C",'Mapa final'!$O$18),"") | AB26: =IF(AND('Mapa final'!$Y$13="Media",'Mapa final'!$AA$13="Mayor"),CONCATENATE("R1C",'Mapa final'!$O$13),"") | AC26: =IF(AND('Mapa final'!$Y$14="Media",'Mapa final'!$AA$14="Mayor"),CONCATENATE("R1C",'Mapa final'!$O$14),"") | AD26: =IF(AND('Mapa final'!$Y$15="Media",'Mapa final'!$AA$15="Mayor"),CONCATENATE("R1C",'Mapa final'!$O$15),"") | AE26: =IF(AND('Mapa final'!$Y$16="Media",'Mapa final'!$AA$16="Mayor"),CONCATENATE("R1C",'Mapa final'!$O$16),"") | AF26: =IF(AND('Mapa final'!$Y$17="Media",'Mapa final'!$AA$17="Mayor"),CONCATENATE("R1C",'Mapa final'!$O$17),"") | AG26: =IF(AND('Mapa final'!$Y$18="Media",'Mapa final'!$AA$18="Mayor"),CONCATENATE("R1C",'Mapa final'!$O$18),"") | AH26: =IF(AND('Mapa final'!$Y$13="Media",'Mapa final'!$AA$13="Catastrófico"),CONCATENATE("R1C",'Mapa final'!$O$13),"") | AI26: =IF(AND('Mapa final'!$Y$14="Media",'Mapa final'!$AA$14="Catastrófico"),CONCATENATE("R1C",'Mapa final'!$O$14),"") | AJ26: =IF(AND('Mapa final'!$Y$15="Media",'Mapa final'!$AA$15="Catastrófico"),CONCATENATE("R1C",'Mapa final'!$O$15),"") | AK26: =IF(AND('Mapa final'!$Y$16="Media",'Mapa final'!$AA$16="Catastrófico"),CONCATENATE("R1C",'Mapa final'!$O$16),"") | AL26: =IF(AND('Mapa final'!$Y$17="Media",'Mapa final'!$AA$17="Catastrófico"),CONCATENATE("R1C",'Mapa final'!$O$17),"") | AM26: =IF(AND('Mapa final'!$Y$18="Media",'Mapa final'!$AA$18="Catastrófico"),CONCATENATE("R1C",'Mapa final'!$O$18),"") | AO26: Moderado
J27: =IF(AND('Mapa final'!#REF!="Media",'Mapa final'!#REF!="Leve"),CONCATENATE("R2C",'Mapa final'!#REF!),"") -> #REF! | K27: =IF(AND('Mapa final'!#REF!="Media",'Mapa final'!#REF!="Leve"),CONCATENATE("R2C",'Mapa final'!#REF!),"") -> #REF! | L27: =IF(AND('Mapa final'!#REF!="Media",'Mapa final'!#REF!="Leve"),CONCATENATE("R2C",'Mapa final'!#REF!),"") -> #REF! | M27: =IF(AND('Mapa final'!#REF!="Media",'Mapa final'!#REF!="Leve"),CONCATENATE("R2C",'Mapa final'!#REF!),"") -> #REF! | N27: =IF(AND('Mapa final'!#REF!="Media",'Mapa final'!#REF!="Leve"),CONCATENATE("R2C",'Mapa final'!#REF!),"") -> #REF! | O27: =IF(AND('Mapa final'!#REF!="Media",'Mapa final'!#REF!="Leve"),CONCATENATE("R2C",'Mapa final'!#REF!),"") -> #REF! | P27: =IF(AND('Mapa final'!#REF!="Media",'Mapa final'!#REF!="Menor"),CONCATENATE("R2C",'Mapa final'!#REF!),"") -> #REF! | Q27: =IF(AND('Mapa final'!#REF!="Media",'Mapa final'!#REF!="Menor"),CONCATENATE("R2C",'Mapa final'!#REF!),"") -> #REF! | R27: =IF(AND('Mapa final'!#REF!="Media",'Mapa final'!#REF!="Menor"),CONCATENATE("R2C",'Mapa final'!#REF!),"") -> #REF! | S27: =IF(AND('Mapa final'!#REF!="Media",'Mapa final'!#REF!="Menor"),CONCATENATE("R2C",'Mapa final'!#REF!),"") -> #REF! | T27: =IF(AND('Mapa final'!#REF!="Media",'Mapa final'!#REF!="Menor"),CONCATENATE("R2C",'Mapa final'!#REF!),"") -> #REF! | U27: =IF(AND('Mapa final'!#REF!="Media",'Mapa final'!#REF!="Menor"),CONCATENATE("R2C",'Mapa final'!#REF!),"") -> #REF! | V27: =IF(AND('Mapa final'!#REF!="Media",'Mapa final'!#REF!="Moderado"),CONCATENATE("R2C",'Mapa final'!#REF!),"") -> #REF! | W27: =IF(AND('Mapa final'!#REF!="Media",'Mapa final'!#REF!="Moderado"),CONCATENATE("R2C",'Mapa final'!#REF!),"") -> #REF! | X27: =IF(AND('Mapa final'!#REF!="Media",'Mapa final'!#REF!="Moderado"),CONCATENATE("R2C",'Mapa final'!#REF!),"") -> #REF! | Y27: =IF(AND('Mapa final'!#REF!="Media",'Mapa final'!#REF!="Moderado"),CONCATENATE("R2C",'Mapa final'!#REF!),"") -> #REF! | Z27: =IF(AND('Mapa final'!#REF!="Media",'Mapa final'!#REF!="Moderado"),CONCATENATE("R2C",'Mapa final'!#REF!),"") -> #REF! | AA27: =IF(AND('Mapa final'!#REF!="Media",'Mapa final'!#REF!="Moderado"),CONCATENATE("R2C",'Mapa final'!#REF!),"") -> #REF! | AB27: =IF(AND('Mapa final'!#REF!="Media",'Mapa final'!#REF!="Mayor"),CONCATENATE("R2C",'Mapa final'!#REF!),"") -> #REF! | AC27: =IF(AND('Mapa final'!#REF!="Media",'Mapa final'!#REF!="Mayor"),CONCATENATE("R2C",'Mapa final'!#REF!),"") -> #REF! | AD27: =IF(AND('Mapa final'!#REF!="Media",'Mapa final'!#REF!="Mayor"),CONCATENATE("R2C",'Mapa final'!#REF!),"") -> #REF! | AE27: =IF(AND('Mapa final'!#REF!="Media",'Mapa final'!#REF!="Mayor"),CONCATENATE("R2C",'Mapa final'!#REF!),"") -> #REF! | AF27: =IF(AND('Mapa final'!#REF!="Media",'Mapa final'!#REF!="Mayor"),CONCATENATE("R2C",'Mapa final'!#REF!),"") -> #REF! | AG27: =IF(AND('Mapa final'!#REF!="Media",'Mapa final'!#REF!="Mayor"),CONCATENATE("R2C",'Mapa final'!#REF!),"") -> #REF! | AH27: =IF(AND('Mapa final'!#REF!="Media",'Mapa final'!#REF!="Catastrófico"),CONCATENATE("R2C",'Mapa final'!#REF!),"") -> #REF! | AI27: =IF(AND('Mapa final'!#REF!="Media",'Mapa final'!#REF!="Catastrófico"),CONCATENATE("R2C",'Mapa final'!#REF!),"") -> #REF! | AJ27: =IF(AND('Mapa final'!#REF!="Media",'Mapa final'!#REF!="Catastrófico"),CONCATENATE("R2C",'Mapa final'!#REF!),"") -> #REF! | AK27: =IF(AND('Mapa final'!#REF!="Media",'Mapa final'!#REF!="Catastrófico"),CONCATENATE("R2C",'Mapa final'!#REF!),"") -> #REF! | AL27: =IF(AND('Mapa final'!#REF!="Media",'Mapa final'!#REF!="Catastrófico"),CONCATENATE("R2C",'Mapa final'!#REF!),"") -> #REF! | AM27: =IF(AND('Mapa final'!#REF!="Media",'Mapa final'!#REF!="Catastrófico"),CONCATENATE("R2C",'Mapa final'!#REF!),"") -> #REF!
J28: =IF(AND('Mapa final'!#REF!="Media",'Mapa final'!#REF!="Leve"),CONCATENATE("R3C",'Mapa final'!#REF!),"") -> #REF! | K28: =IF(AND('Mapa final'!#REF!="Media",'Mapa final'!#REF!="Leve"),CONCATENATE("R3C",'Mapa final'!#REF!),"") -> #REF! | L28: =IF(AND('Mapa final'!#REF!="Media",'Mapa final'!#REF!="Leve"),CONCATENATE("R3C",'Mapa final'!#REF!),"") -> #REF! | M28: =IF(AND('Mapa final'!#REF!="Media",'Mapa final'!#REF!="Leve"),CONCATENATE("R3C",'Mapa final'!#REF!),"") -> #REF! | N28: =IF(AND('Mapa final'!#REF!="Media",'Mapa final'!#REF!="Leve"),CONCATENATE("R3C",'Mapa final'!#REF!),"") -> #REF! | O28: =IF(AND('Mapa final'!#REF!="Media",'Mapa final'!#REF!="Leve"),CONCATENATE("R3C",'Mapa final'!#REF!),"") -> #REF! | P28: =IF(AND('Mapa final'!#REF!="Media",'Mapa final'!#REF!="Menor"),CONCATENATE("R3C",'Mapa final'!#REF!),"") -> #REF! | Q28: =IF(AND('Mapa final'!#REF!="Media",'Mapa final'!#REF!="Menor"),CONCATENATE("R3C",'Mapa final'!#REF!),"") -> #REF! | R28: =IF(AND('Mapa final'!#REF!="Media",'Mapa final'!#REF!="Menor"),CONCATENATE("R3C",'Mapa final'!#REF!),"") -> #REF! | S28: =IF(AND('Mapa final'!#REF!="Media",'Mapa final'!#REF!="Menor"),CONCATENATE("R3C",'Mapa final'!#REF!),"") -> #REF! | T28: =IF(AND('Mapa final'!#REF!="Media",'Mapa final'!#REF!="Menor"),CONCATENATE("R3C",'Mapa final'!#REF!),"") -> #REF! | U28: =IF(AND('Mapa final'!#REF!="Media",'Mapa final'!#REF!="Menor"),CONCATENATE("R3C",'Mapa final'!#REF!),"") -> #REF! | V28: =IF(AND('Mapa final'!#REF!="Media",'Mapa final'!#REF!="Moderado"),CONCATENATE("R3C",'Mapa final'!#REF!),"") -> #REF! | W28: =IF(AND('Mapa final'!#REF!="Media",'Mapa final'!#REF!="Moderado"),CONCATENATE("R3C",'Mapa final'!#REF!),"") -> #REF! | X28: =IF(AND('Mapa final'!#REF!="Media",'Mapa final'!#REF!="Moderado"),CONCATENATE("R3C",'Mapa final'!#REF!),"") -> #REF! | Y28: =IF(AND('Mapa final'!#REF!="Media",'Mapa final'!#REF!="Moderado"),CONCATENATE("R3C",'Mapa final'!#REF!),"") -> #REF! | Z28: =IF(AND('Mapa final'!#REF!="Media",'Mapa final'!#REF!="Moderado"),CONCATENATE("R3C",'Mapa final'!#REF!),"") -> #REF! | AA28: =IF(AND('Mapa final'!#REF!="Media",'Mapa final'!#REF!="Moderado"),CONCATENATE("R3C",'Mapa final'!#REF!),"") -> #REF! | AB28: =IF(AND('Mapa final'!#REF!="Media",'Mapa final'!#REF!="Mayor"),CONCATENATE("R3C",'Mapa final'!#REF!),"") -> #REF! | AC28: =IF(AND('Mapa final'!#REF!="Media",'Mapa final'!#REF!="Mayor"),CONCATENATE("R3C",'Mapa final'!#REF!),"") -> #REF! | AD28: =IF(AND('Mapa final'!#REF!="Media",'Mapa final'!#REF!="Mayor"),CONCATENATE("R3C",'Mapa final'!#REF!),"") -> #REF! | AE28: =IF(AND('Mapa final'!#REF!="Media",'Mapa final'!#REF!="Mayor"),CONCATENATE("R3C",'Mapa final'!#REF!),"") -> #REF! | AF28: =IF(AND('Mapa final'!#REF!="Media",'Mapa final'!#REF!="Mayor"),CONCATENATE("R3C",'Mapa final'!#REF!),"") -> #REF! | AG28: =IF(AND('Mapa final'!#REF!="Media",'Mapa final'!#REF!="Mayor"),CONCATENATE("R3C",'Mapa final'!#REF!),"") -> #REF! | AH28: =IF(AND('Mapa final'!#REF!="Media",'Mapa final'!#REF!="Catastrófico"),CONCATENATE("R3C",'Mapa final'!#REF!),"") -> #REF! | AI28: =IF(AND('Mapa final'!#REF!="Media",'Mapa final'!#REF!="Catastrófico"),CONCATENATE("R3C",'Mapa final'!#REF!),"") -> #REF! | AJ28: =IF(AND('Mapa final'!#REF!="Media",'Mapa final'!#REF!="Catastrófico"),CONCATENATE("R3C",'Mapa final'!#REF!),"") -> #REF! | AK28: =IF(AND('Mapa final'!#REF!="Media",'Mapa final'!#REF!="Catastrófico"),CONCATENATE("R3C",'Mapa final'!#REF!),"") -> #REF! | AL28: =IF(AND('Mapa final'!#REF!="Media",'Mapa final'!#REF!="Catastrófico"),CONCATENATE("R3C",'Mapa final'!#REF!),"") -> #REF! | AM28: =IF(AND('Mapa final'!#REF!="Media",'Mapa final'!#REF!="Catastrófico"),CONCATENATE("R3C",'Mapa final'!#REF!),"") -> #REF!
J29: =IF(AND('Mapa final'!#REF!="Media",'Mapa final'!#REF!="Leve"),CONCATENATE("R4C",'Mapa final'!#REF!),"") -> #REF! | K29: =IF(AND('Mapa final'!#REF!="Media",'Mapa final'!#REF!="Leve"),CONCATENATE("R4C",'Mapa final'!#REF!),"") -> #REF! | L29: =IF(AND('Mapa final'!#REF!="Media",'Mapa final'!#REF!="Leve"),CONCATENATE("R4C",'Mapa final'!#REF!),"") -> #REF! | M29: =IF(AND('Mapa final'!#REF!="Media",'Mapa final'!#REF!="Leve"),CONCATENATE("R4C",'Mapa final'!#REF!),"") -> #REF! | N29: =IF(AND('Mapa final'!#REF!="Media",'Mapa final'!#REF!="Leve"),CONCATENATE("R4C",'Mapa final'!#REF!),"") -> #REF! | O29: =IF(AND('Mapa final'!#REF!="Media",'Mapa final'!#REF!="Leve"),CONCATENATE("R4C",'Mapa final'!#REF!),"") -> #REF! | P29: =IF(AND('Mapa final'!#REF!="Media",'Mapa final'!#REF!="Menor"),CONCATENATE("R4C",'Mapa final'!#REF!),"") -> #REF! | Q29: =IF(AND('Mapa final'!#REF!="Media",'Mapa final'!#REF!="Menor"),CONCATENATE("R4C",'Mapa final'!#REF!),"") -> #REF! | R29: =IF(AND('Mapa final'!#REF!="Media",'Mapa final'!#REF!="Menor"),CONCATENATE("R4C",'Mapa final'!#REF!),"") -> #REF! | S29: =IF(AND('Mapa final'!#REF!="Media",'Mapa final'!#REF!="Menor"),CONCATENATE("R4C",'Mapa final'!#REF!),"") -> #REF! | T29: =IF(AND('Mapa final'!#REF!="Media",'Mapa final'!#REF!="Menor"),CONCATENATE("R4C",'Mapa final'!#REF!),"") -> #REF! | U29: =IF(AND('Mapa final'!#REF!="Media",'Mapa final'!#REF!="Menor"),CONCATENATE("R4C",'Mapa final'!#REF!),"") -> #REF! | V29: =IF(AND('Mapa final'!#REF!="Media",'Mapa final'!#REF!="Moderado"),CONCATENATE("R4C",'Mapa final'!#REF!),"") -> #REF! | W29: =IF(AND('Mapa final'!#REF!="Media",'Mapa final'!#REF!="Moderado"),CONCATENATE("R4C",'Mapa final'!#REF!),"") -> #REF! | X29: =IF(AND('Mapa final'!#REF!="Media",'Mapa final'!#REF!="Moderado"),CONCATENATE("R4C",'Mapa final'!#REF!),"") -> #REF! | Y29: =IF(AND('Mapa final'!#REF!="Media",'Mapa final'!#REF!="Moderado"),CONCATENATE("R4C",'Mapa final'!#REF!),"") -> #REF! | Z29: =IF(AND('Mapa final'!#REF!="Media",'Mapa final'!#REF!="Moderado"),CONCATENATE("R4C",'Mapa final'!#REF!),"") -> #REF! | AA29: =IF(AND('Mapa final'!#REF!="Media",'Mapa final'!#REF!="Moderado"),CONCATENATE("R4C",'Mapa final'!#REF!),"") -> #REF! | AB29: =IF(AND('Mapa final'!#REF!="Media",'Mapa final'!#REF!="Mayor"),CONCATENATE("R4C",'Mapa final'!#REF!),"") -> #REF! | AC29: =IF(AND('Mapa final'!#REF!="Media",'Mapa final'!#REF!="Mayor"),CONCATENATE("R4C",'Mapa final'!#REF!),"") -> #REF! | AD29: =IF(AND('Mapa final'!#REF!="Media",'Mapa final'!#REF!="Mayor"),CONCATENATE("R4C",'Mapa final'!#REF!),"") -> #REF! | AE29: =IF(AND('Mapa final'!#REF!="Media",'Mapa final'!#REF!="Mayor"),CONCATENATE("R4C",'Mapa final'!#REF!),"") -> #REF! | AF29: =IF(AND('Mapa final'!#REF!="Media",'Mapa final'!#REF!="Mayor"),CONCATENATE("R4C",'Mapa final'!#REF!),"") -> #REF! | AG29: =IF(AND('Mapa final'!#REF!="Media",'Mapa final'!#REF!="Mayor"),CONCATENATE("R4C",'Mapa final'!#REF!),"") -> #REF! | AH29: =IF(AND('Mapa final'!#REF!="Media",'Mapa final'!#REF!="Catastrófico"),CONCATENATE("R4C",'Mapa final'!#REF!),"") -> #REF! | AI29: =IF(AND('Mapa final'!#REF!="Media",'Mapa final'!#REF!="Catastrófico"),CONCATENATE("R4C",'Mapa final'!#REF!),"") -> #REF! | AJ29: =IF(AND('Mapa final'!#REF!="Media",'Mapa final'!#REF!="Catastrófico"),CONCATENATE("R4C",'Mapa final'!#REF!),"") -> #REF! | AK29: =IF(AND('Mapa final'!#REF!="Media",'Mapa final'!#REF!="Catastrófico"),CONCATENATE("R4C",'Mapa final'!#REF!),"") -> #REF! | AL29: =IF(AND('Mapa final'!#REF!="Media",'Mapa final'!#REF!="Catastrófico"),CONCATENATE("R4C",'Mapa final'!#REF!),"") -> #REF! | AM29: =IF(AND('Mapa final'!#REF!="Media",'Mapa final'!#REF!="Catastrófico"),CONCATENATE("R4C",'Mapa final'!#REF!),"") -> #REF!
J30: =IF(AND('Mapa final'!#REF!="Media",'Mapa final'!#REF!="Leve"),CONCATENATE("R5C",'Mapa final'!#REF!),"") -> #REF! | K30: =IF(AND('Mapa final'!#REF!="Media",'Mapa final'!#REF!="Leve"),CONCATENATE("R5C",'Mapa final'!#REF!),"") -> #REF! | L30: =IF(AND('Mapa final'!#REF!="Media",'Mapa final'!#REF!="Leve"),CONCATENATE("R5C",'Mapa final'!#REF!),"") -> #REF! | M30: =IF(AND('Mapa final'!#REF!="Media",'Mapa final'!#REF!="Leve"),CONCATENATE("R5C",'Mapa final'!#REF!),"") -> #REF! | N30: =IF(AND('Mapa final'!#REF!="Media",'Mapa final'!#REF!="Leve"),CONCATENATE("R5C",'Mapa final'!#REF!),"") -> #REF! | O30: =IF(AND('Mapa final'!#REF!="Media",'Mapa final'!#REF!="Leve"),CONCATENATE("R5C",'Mapa final'!#REF!),"") -> #REF! | P30: =IF(AND('Mapa final'!#REF!="Media",'Mapa final'!#REF!="Menor"),CONCATENATE("R5C",'Mapa final'!#REF!),"") -> #REF! | Q30: =IF(AND('Mapa final'!#REF!="Media",'Mapa final'!#REF!="Menor"),CONCATENATE("R5C",'Mapa final'!#REF!),"") -> #REF! | R30: =IF(AND('Mapa final'!#REF!="Media",'Mapa final'!#REF!="Menor"),CONCATENATE("R5C",'Mapa final'!#REF!),"") -> #REF! | S30: =IF(AND('Mapa final'!#REF!="Media",'Mapa final'!#REF!="Menor"),CONCATENATE("R5C",'Mapa final'!#REF!),"") -> #REF! | T30: =IF(AND('Mapa final'!#REF!="Media",'Mapa final'!#REF!="Menor"),CONCATENATE("R5C",'Mapa final'!#REF!),"") -> #REF! | U30: =IF(AND('Mapa final'!#REF!="Media",'Mapa final'!#REF!="Menor"),CONCATENATE("R5C",'Mapa final'!#REF!),"") -> #REF! | V30: =IF(AND('Mapa final'!#REF!="Media",'Mapa final'!#REF!="Moderado"),CONCATENATE("R5C",'Mapa final'!#REF!),"") -> #REF! | W30: =IF(AND('Mapa final'!#REF!="Media",'Mapa final'!#REF!="Moderado"),CONCATENATE("R5C",'Mapa final'!#REF!),"") -> #REF! | X30: =IF(AND('Mapa final'!#REF!="Media",'Mapa final'!#REF!="Moderado"),CONCATENATE("R5C",'Mapa final'!#REF!),"") -> #REF! | Y30: =IF(AND('Mapa final'!#REF!="Media",'Mapa final'!#REF!="Moderado"),CONCATENATE("R5C",'Mapa final'!#REF!),"") -> #REF! | Z30: =IF(AND('Mapa final'!#REF!="Media",'Mapa final'!#REF!="Moderado"),CONCATENATE("R5C",'Mapa final'!#REF!),"") -> #REF! | AA30: =IF(AND('Mapa final'!#REF!="Media",'Mapa final'!#REF!="Moderado"),CONCATENATE("R5C",'Mapa final'!#REF!),"") -> #REF! | AB30: =IF(AND('Mapa final'!#REF!="Media",'Mapa final'!#REF!="Mayor"),CONCATENATE("R5C",'Mapa final'!#REF!),"") -> #REF! | AC30: =IF(AND('Mapa final'!#REF!="Media",'Mapa final'!#REF!="Mayor"),CONCATENATE("R5C",'Mapa final'!#REF!),"") -> #REF! | AD30: =IF(AND('Mapa final'!#REF!="Media",'Mapa final'!#REF!="Mayor"),CONCATENATE("R5C",'Mapa final'!#REF!),"") -> #REF! | AE30: =IF(AND('Mapa final'!#REF!="Media",'Mapa final'!#REF!="Mayor"),CONCATENATE("R5C",'Mapa final'!#REF!),"") -> #REF! | AF30: =IF(AND('Mapa final'!#REF!="Media",'Mapa final'!#REF!="Mayor"),CONCATENATE("R5C",'Mapa final'!#REF!),"") -> #REF! | AG30: =IF(AND('Mapa final'!#REF!="Media",'Mapa final'!#REF!="Mayor"),CONCATENATE("R5C",'Mapa final'!#REF!),"") -> #REF! | AH30: =IF(AND('Mapa final'!#REF!="Media",'Mapa final'!#REF!="Catastrófico"),CONCATENATE("R5C",'Mapa final'!#REF!),"") -> #REF! | AI30: =IF(AND('Mapa final'!#REF!="Media",'Mapa final'!#REF!="Catastrófico"),CONCATENATE("R5C",'Mapa final'!#REF!),"") -> #REF! | AJ30: =IF(AND('Mapa final'!#REF!="Media",'Mapa final'!#REF!="Catastrófico"),CONCATENATE("R5C",'Mapa final'!#REF!),"") -> #REF! | AK30: =IF(AND('Mapa final'!#REF!="Media",'Mapa final'!#REF!="Catastrófico"),CONCATENATE("R5C",'Mapa final'!#REF!),"") -> #REF! | AL30: =IF(AND('Mapa final'!#REF!="Media",'Mapa final'!#REF!="Catastrófico"),CONCATENATE("R5C",'Mapa final'!#REF!),"") -> #REF! | AM30: =IF(AND('Mapa final'!#REF!="Media",'Mapa final'!#REF!="Catastrófico"),CONCATENATE("R5C",'Mapa final'!#REF!),"") -> #REF!
J31: =IF(AND('Mapa final'!#REF!="Media",'Mapa final'!#REF!="Leve"),CONCATENATE("R6C",'Mapa final'!#REF!),"") -> #REF! | K31: =IF(AND('Mapa final'!#REF!="Media",'Mapa final'!#REF!="Leve"),CONCATENATE("R6C",'Mapa final'!#REF!),"") -> #REF! | L31: =IF(AND('Mapa final'!#REF!="Media",'Mapa final'!#REF!="Leve"),CONCATENATE("R6C",'Mapa final'!#REF!),"") -> #REF! | M31: =IF(AND('Mapa final'!#REF!="Media",'Mapa final'!#REF!="Leve"),CONCATENATE("R6C",'Mapa final'!#REF!),"") -> #REF! | N31: =IF(AND('Mapa final'!#REF!="Media",'Mapa final'!#REF!="Leve"),CONCATENATE("R6C",'Mapa final'!#REF!),"") -> #REF! | O31: =IF(AND('Mapa final'!#REF!="Media",'Mapa final'!#REF!="Leve"),CONCATENATE("R6C",'Mapa final'!#REF!),"") -> #REF! | P31: =IF(AND('Mapa final'!#REF!="Media",'Mapa final'!#REF!="Menor"),CONCATENATE("R6C",'Mapa final'!#REF!),"") -> #REF! | Q31: =IF(AND('Mapa final'!#REF!="Media",'Mapa final'!#REF!="Menor"),CONCATENATE("R6C",'Mapa final'!#REF!),"") -> #REF! | R31: =IF(AND('Mapa final'!#REF!="Media",'Mapa final'!#REF!="Menor"),CONCATENATE("R6C",'Mapa final'!#REF!),"") -> #REF! | S31: =IF(AND('Mapa final'!#REF!="Media",'Mapa final'!#REF!="Menor"),CONCATENATE("R6C",'Mapa final'!#REF!),"") -> #REF! | T31: =IF(AND('Mapa final'!#REF!="Media",'Mapa final'!#REF!="Menor"),CONCATENATE("R6C",'Mapa final'!#REF!),"") -> #REF! | U31: =IF(AND('Mapa final'!#REF!="Media",'Mapa final'!#REF!="Menor"),CONCATENATE("R6C",'Mapa final'!#REF!),"") -> #REF! | V31: =IF(AND('Mapa final'!#REF!="Media",'Mapa final'!#REF!="Moderado"),CONCATENATE("R6C",'Mapa final'!#REF!),"") -> #REF! | W31: =IF(AND('Mapa final'!#REF!="Media",'Mapa final'!#REF!="Moderado"),CONCATENATE("R6C",'Mapa final'!#REF!),"") -> #REF! | X31: =IF(AND('Mapa final'!#REF!="Media",'Mapa final'!#REF!="Moderado"),CONCATENATE("R6C",'Mapa final'!#REF!),"") -> #REF! | Y31: =IF(AND('Mapa final'!#REF!="Media",'Mapa final'!#REF!="Moderado"),CONCATENATE("R6C",'Mapa final'!#REF!),"") -> #REF! | Z31: =IF(AND('Mapa final'!#REF!="Media",'Mapa final'!#REF!="Moderado"),CONCATENATE("R6C",'Mapa final'!#REF!),"") -> #REF! | AA31: =IF(AND('Mapa final'!#REF!="Media",'Mapa final'!#REF!="Moderado"),CONCATENATE("R6C",'Mapa final'!#REF!),"") -> #REF! | AB31: =IF(AND('Mapa final'!#REF!="Media",'Mapa final'!#REF!="Mayor"),CONCATENATE("R6C",'Mapa final'!#REF!),"") -> #REF! | AC31: =IF(AND('Mapa final'!#REF!="Media",'Mapa final'!#REF!="Mayor"),CONCATENATE("R6C",'Mapa final'!#REF!),"") -> #REF! | AD31: =IF(AND('Mapa final'!#REF!="Media",'Mapa final'!#REF!="Mayor"),CONCATENATE("R6C",'Mapa final'!#REF!),"") -> #REF! | AE31: =IF(AND('Mapa final'!#REF!="Media",'Mapa final'!#REF!="Mayor"),CONCATENATE("R6C",'Mapa final'!#REF!),"") -> #REF! | AF31: =IF(AND('Mapa final'!#REF!="Media",'Mapa final'!#REF!="Mayor"),CONCATENATE("R6C",'Mapa final'!#REF!),"") -> #REF! | AG31: =IF(AND('Mapa final'!#REF!="Media",'Mapa final'!#REF!="Mayor"),CONCATENATE("R6C",'Mapa final'!#REF!),"") -> #REF! | AH31: =IF(AND('Mapa final'!#REF!="Media",'Mapa final'!#REF!="Catastrófico"),CONCATENATE("R6C",'Mapa final'!#REF!),"") -> #REF! | AI31: =IF(AND('Mapa final'!#REF!="Media",'Mapa final'!#REF!="Catastrófico"),CONCATENATE("R6C",'Mapa final'!#REF!),"") -> #REF! | AJ31: =IF(AND('Mapa final'!#REF!="Media",'Mapa final'!#REF!="Catastrófico"),CONCATENATE("R6C",'Mapa final'!#REF!),"") -> #REF! | AK31: =IF(AND('Mapa final'!#REF!="Media",'Mapa final'!#REF!="Catastrófico"),CONCATENATE("R6C",'Mapa final'!#REF!),"") -> #REF! | AL31: =IF(AND('Mapa final'!#REF!="Media",'Mapa final'!#REF!="Catastrófico"),CONCATENATE("R6C",'Mapa final'!#REF!),"") -> #REF! | AM31: =IF(AND('Mapa final'!#REF!="Media",'Mapa final'!#REF!="Catastrófico"),CONCATENATE("R6C",'Mapa final'!#REF!),"") -> #REF!
J32: =IF(AND('Mapa final'!#REF!="Media",'Mapa final'!#REF!="Leve"),CONCATENATE("R7C",'Mapa final'!#REF!),"") -> #REF! | K32: =IF(AND('Mapa final'!#REF!="Media",'Mapa final'!#REF!="Leve"),CONCATENATE("R7C",'Mapa final'!#REF!),"") -> #REF! | L32: =IF(AND('Mapa final'!#REF!="Media",'Mapa final'!#REF!="Leve"),CONCATENATE("R7C",'Mapa final'!#REF!),"") -> #REF! | M32: =IF(AND('Mapa final'!#REF!="Media",'Mapa final'!#REF!="Leve"),CONCATENATE("R7C",'Mapa final'!#REF!),"") -> #REF! | N32: =IF(AND('Mapa final'!#REF!="Media",'Mapa final'!#REF!="Leve"),CONCATENATE("R7C",'Mapa final'!#REF!),"") -> #REF! | O32: =IF(AND('Mapa final'!#REF!="Media",'Mapa final'!#REF!="Leve"),CONCATENATE("R7C",'Mapa final'!#REF!),"") -> #REF! | P32: =IF(AND('Mapa final'!#REF!="Media",'Mapa final'!#REF!="Menor"),CONCATENATE("R7C",'Mapa final'!#REF!),"") -> #REF! | Q32: =IF(AND('Mapa final'!#REF!="Media",'Mapa final'!#REF!="Menor"),CONCATENATE("R7C",'Mapa final'!#REF!),"") -> #REF! | R32: =IF(AND('Mapa final'!#REF!="Media",'Mapa final'!#REF!="Menor"),CONCATENATE("R7C",'Mapa final'!#REF!),"") -> #REF! | S32: =IF(AND('Mapa final'!#REF!="Media",'Mapa final'!#REF!="Menor"),CONCATENATE("R7C",'Mapa final'!#REF!),"") -> #REF! | T32: =IF(AND('Mapa final'!#REF!="Media",'Mapa final'!#REF!="Menor"),CONCATENATE("R7C",'Mapa final'!#REF!),"") -> #REF! | U32: =IF(AND('Mapa final'!#REF!="Media",'Mapa final'!#REF!="Menor"),CONCATENATE("R7C",'Mapa final'!#REF!),"") -> #REF! | V32: =IF(AND('Mapa final'!#REF!="Media",'Mapa final'!#REF!="Moderado"),CONCATENATE("R7C",'Mapa final'!#REF!),"") -> #REF! | W32: =IF(AND('Mapa final'!#REF!="Media",'Mapa final'!#REF!="Moderado"),CONCATENATE("R7C",'Mapa final'!#REF!),"") -> #REF! | X32: =IF(AND('Mapa final'!#REF!="Media",'Mapa final'!#REF!="Moderado"),CONCATENATE("R7C",'Mapa final'!#REF!),"") -> #REF! | Y32: =IF(AND('Mapa final'!#REF!="Media",'Mapa final'!#REF!="Moderado"),CONCATENATE("R7C",'Mapa final'!#REF!),"") -> #REF! | Z32: =IF(AND('Mapa final'!#REF!="Media",'Mapa final'!#REF!="Moderado"),CONCATENATE("R7C",'Mapa final'!#REF!),"") -> #REF! | AA32: =IF(AND('Mapa final'!#REF!="Media",'Mapa final'!#REF!="Moderado"),CONCATENATE("R7C",'Mapa final'!#REF!),"") -> #REF! | AB32: =IF(AND('Mapa final'!#REF!="Media",'Mapa final'!#REF!="Mayor"),CONCATENATE("R7C",'Mapa final'!#REF!),"") -> #REF! | AC32: =IF(AND('Mapa final'!#REF!="Media",'Mapa final'!#REF!="Mayor"),CONCATENATE("R7C",'Mapa final'!#REF!),"") -> #REF! | AD32: =IF(AND('Mapa final'!#REF!="Media",'Mapa final'!#REF!="Mayor"),CONCATENATE("R7C",'Mapa final'!#REF!),"") -> #REF! | AE32: =IF(AND('Mapa final'!#REF!="Media",'Mapa final'!#REF!="Mayor"),CONCATENATE("R7C",'Mapa final'!#REF!),"") -> #REF! | AF32: =IF(AND('Mapa final'!#REF!="Media",'Mapa final'!#REF!="Mayor"),CONCATENATE("R7C",'Mapa final'!#REF!),"") -> #REF! | AG32: =IF(AND('Mapa final'!#REF!="Media",'Mapa final'!#REF!="Mayor"),CONCATENATE("R7C",'Mapa final'!#REF!),"") -> #REF! | AH32: =IF(AND('Mapa final'!#REF!="Media",'Mapa final'!#REF!="Catastrófico"),CONCATENATE("R7C",'Mapa final'!#REF!),"") -> #REF! | AI32: =IF(AND('Mapa final'!#REF!="Media",'Mapa final'!#REF!="Catastrófico"),CONCATENATE("R7C",'Mapa final'!#REF!),"") -> #REF! | AJ32: =IF(AND('Mapa final'!#REF!="Media",'Mapa final'!#REF!="Catastrófico"),CONCATENATE("R7C",'Mapa final'!#REF!),"") -> #REF! | AK32: =IF(AND('Mapa final'!#REF!="Media",'Mapa final'!#REF!="Catastrófico"),CONCATENATE("R7C",'Mapa final'!#REF!),"") -> #REF! | AL32: =IF(AND('Mapa final'!#REF!="Media",'Mapa final'!#REF!="Catastrófico"),CONCATENATE("R7C",'Mapa final'!#REF!),"") -> #REF! | AM32: =IF(AND('Mapa final'!#REF!="Media",'Mapa final'!#REF!="Catastrófico"),CONCATENATE("R7C",'Mapa final'!#REF!),"") -> #REF!
J33: =IF(AND('Mapa final'!#REF!="Media",'Mapa final'!#REF!="Leve"),CONCATENATE("R8C",'Mapa final'!#REF!),"") -> #REF! | K33: =IF(AND('Mapa final'!#REF!="Media",'Mapa final'!#REF!="Leve"),CONCATENATE("R8C",'Mapa final'!#REF!),"") -> #REF! | L33: =IF(AND('Mapa final'!#REF!="Media",'Mapa final'!#REF!="Leve"),CONCATENATE("R8C",'Mapa final'!#REF!),"") -> #REF! | M33: =IF(AND('Mapa final'!#REF!="Media",'Mapa final'!#REF!="Leve"),CONCATENATE("R8C",'Mapa final'!#REF!),"") -> #REF! | N33: =IF(AND('Mapa final'!#REF!="Media",'Mapa final'!#REF!="Leve"),CONCATENATE("R8C",'Mapa final'!#REF!),"") -> #REF! | O33: =IF(AND('Mapa final'!#REF!="Media",'Mapa final'!#REF!="Leve"),CONCATENATE("R8C",'Mapa final'!#REF!),"") -> #REF! | P33: =IF(AND('Mapa final'!#REF!="Media",'Mapa final'!#REF!="Menor"),CONCATENATE("R8C",'Mapa final'!#REF!),"") -> #REF! | Q33: =IF(AND('Mapa final'!#REF!="Media",'Mapa final'!#REF!="Menor"),CONCATENATE("R8C",'Mapa final'!#REF!),"") -> #REF! | R33: =IF(AND('Mapa final'!#REF!="Media",'Mapa final'!#REF!="Menor"),CONCATENATE("R8C",'Mapa final'!#REF!),"") -> #REF! | S33: =IF(AND('Mapa final'!#REF!="Media",'Mapa final'!#REF!="Menor"),CONCATENATE("R8C",'Mapa final'!#REF!),"") -> #REF! | T33: =IF(AND('Mapa final'!#REF!="Media",'Mapa final'!#REF!="Menor"),CONCATENATE("R8C",'Mapa final'!#REF!),"") -> #REF! | U33: =IF(AND('Mapa final'!#REF!="Media",'Mapa final'!#REF!="Menor"),CONCATENATE("R8C",'Mapa final'!#REF!),"") -> #REF! | V33: =IF(AND('Mapa final'!#REF!="Media",'Mapa final'!#REF!="Moderado"),CONCATENATE("R8C",'Mapa final'!#REF!),"") -> #REF! | W33: =IF(AND('Mapa final'!#REF!="Media",'Mapa final'!#REF!="Moderado"),CONCATENATE("R8C",'Mapa final'!#REF!),"") -> #REF! | X33: =IF(AND('Mapa final'!#REF!="Media",'Mapa final'!#REF!="Moderado"),CONCATENATE("R8C",'Mapa final'!#REF!),"") -> #REF! | Y33: =IF(AND('Mapa final'!#REF!="Media",'Mapa final'!#REF!="Moderado"),CONCATENATE("R8C",'Mapa final'!#REF!),"") -> #REF! | Z33: =IF(AND('Mapa final'!#REF!="Media",'Mapa final'!#REF!="Moderado"),CONCATENATE("R8C",'Mapa final'!#REF!),"") -> #REF! | AA33: =IF(AND('Mapa final'!#REF!="Media",'Mapa final'!#REF!="Moderado"),CONCATENATE("R8C",'Mapa final'!#REF!),"") -> #REF! | AB33: =IF(AND('Mapa final'!#REF!="Media",'Mapa final'!#REF!="Mayor"),CONCATENATE("R8C",'Mapa final'!#REF!),"") -> #REF! | AC33: =IF(AND('Mapa final'!#REF!="Media",'Mapa final'!#REF!="Mayor"),CONCATENATE("R8C",'Mapa final'!#REF!),"") -> #REF! | AD33: =IF(AND('Mapa final'!#REF!="Media",'Mapa final'!#REF!="Mayor"),CONCATENATE("R8C",'Mapa final'!#REF!),"") -> #REF! | AE33: =IF(AND('Mapa final'!#REF!="Media",'Mapa final'!#REF!="Mayor"),CONCATENATE("R8C",'Mapa final'!#REF!),"") -> #REF! | AF33: =IF(AND('Mapa final'!#REF!="Media",'Mapa final'!#REF!="Mayor"),CONCATENATE("R8C",'Mapa final'!#REF!),"") -> #REF! | AG33: =IF(AND('Mapa final'!#REF!="Media",'Mapa final'!#REF!="Mayor"),CONCATENATE("R8C",'Mapa final'!#REF!),"") -> #REF! | AH33: =IF(AND('Mapa final'!#REF!="Media",'Mapa final'!#REF!="Catastrófico"),CONCATENATE("R8C",'Mapa final'!#REF!),"") -> #REF! | AI33: =IF(AND('Mapa final'!#REF!="Media",'Mapa final'!#REF!="Catastrófico"),CONCATENATE("R8C",'Mapa final'!#REF!),"") -> #REF! | AJ33: =IF(AND('Mapa final'!#REF!="Media",'Mapa final'!#REF!="Catastrófico"),CONCATENATE("R8C",'Mapa final'!#REF!),"") -> #REF! | AK33: =IF(AND('Mapa final'!#REF!="Media",'Mapa final'!#REF!="Catastrófico"),CONCATENATE("R8C",'Mapa final'!#REF!),"") -> #REF! | AL33: =IF(AND('Mapa final'!#REF!="Media",'Mapa final'!#REF!="Catastrófico"),CONCATENATE("R8C",'Mapa final'!#REF!),"") -> #REF! | AM33: =IF(AND('Mapa final'!#REF!="Media",'Mapa final'!#REF!="Catastrófico"),CONCATENATE("R8C",'Mapa final'!#REF!),"") -> #REF!
J34: =IF(AND('Mapa final'!#REF!="Media",'Mapa final'!#REF!="Leve"),CONCATENATE("R9C",'Mapa final'!#REF!),"") -> #REF! | K34: =IF(AND('Mapa final'!#REF!="Media",'Mapa final'!#REF!="Leve"),CONCATENATE("R9C",'Mapa final'!#REF!),"") -> #REF! | L34: =IF(AND('Mapa final'!#REF!="Media",'Mapa final'!#REF!="Leve"),CONCATENATE("R9C",'Mapa final'!#REF!),"") -> #REF! | M34: =IF(AND('Mapa final'!#REF!="Media",'Mapa final'!#REF!="Leve"),CONCATENATE("R9C",'Mapa final'!#REF!),"") -> #REF! | N34: =IF(AND('Mapa final'!#REF!="Media",'Mapa final'!#REF!="Leve"),CONCATENATE("R9C",'Mapa final'!#REF!),"") -> #REF! | O34: =IF(AND('Mapa final'!#REF!="Media",'Mapa final'!#REF!="Leve"),CONCATENATE("R9C",'Mapa final'!#REF!),"") -> #REF! | P34: =IF(AND('Mapa final'!#REF!="Media",'Mapa final'!#REF!="Menor"),CONCATENATE("R9C",'Mapa final'!#REF!),"") -> #REF! | Q34: =IF(AND('Mapa final'!#REF!="Media",'Mapa final'!#REF!="Menor"),CONCATENATE("R9C",'Mapa final'!#REF!),"") -> #REF! | R34: =IF(AND('Mapa final'!#REF!="Media",'Mapa final'!#REF!="Menor"),CONCATENATE("R9C",'Mapa final'!#REF!),"") -> #REF! | S34: =IF(AND('Mapa final'!#REF!="Media",'Mapa final'!#REF!="Menor"),CONCATENATE("R9C",'Mapa final'!#REF!),"") -> #REF! | T34: =IF(AND('Mapa final'!#REF!="Media",'Mapa final'!#REF!="Menor"),CONCATENATE("R9C",'Mapa final'!#REF!),"") -> #REF! | U34: =IF(AND('Mapa final'!#REF!="Media",'Mapa final'!#REF!="Menor"),CONCATENATE("R9C",'Mapa final'!#REF!),"") -> #REF! | V34: =IF(AND('Mapa final'!#REF!="Media",'Mapa final'!#REF!="Moderado"),CONCATENATE("R9C",'Mapa final'!#REF!),"") -> #REF! | W34: =IF(AND('Mapa final'!#REF!="Media",'Mapa final'!#REF!="Moderado"),CONCATENATE("R9C",'Mapa final'!#REF!),"") -> #REF! | X34: =IF(AND('Mapa final'!#REF!="Media",'Mapa final'!#REF!="Moderado"),CONCATENATE("R9C",'Mapa final'!#REF!),"") -> #REF! | Y34: =IF(AND('Mapa final'!#REF!="Media",'Mapa final'!#REF!="Moderado"),CONCATENATE("R9C",'Mapa final'!#REF!),"") -> #REF! | Z34: =IF(AND('Mapa final'!#REF!="Media",'Mapa final'!#REF!="Moderado"),CONCATENATE("R9C",'Mapa final'!#REF!),"") -> #REF! | AA34: =IF(AND('Mapa final'!#REF!="Media",'Mapa final'!#REF!="Moderado"),CONCATENATE("R9C",'Mapa final'!#REF!),"") -> #REF! | AB34: =IF(AND('Mapa final'!#REF!="Media",'Mapa final'!#REF!="Mayor"),CONCATENATE("R9C",'Mapa final'!#REF!),"") -> #REF! | AC34: =IF(AND('Mapa final'!#REF!="Media",'Mapa final'!#REF!="Mayor"),CONCATENATE("R9C",'Mapa final'!#REF!),"") -> #REF! | AD34: =IF(AND('Mapa final'!#REF!="Media",'Mapa final'!#REF!="Mayor"),CONCATENATE("R9C",'Mapa final'!#REF!),"") -> #REF! | AE34: =IF(AND('Mapa final'!#REF!="Media",'Mapa final'!#REF!="Mayor"),CONCATENATE("R9C",'Mapa final'!#REF!),"") -> #REF! | AF34: =IF(AND('Mapa final'!#REF!="Media",'Mapa final'!#REF!="Mayor"),CONCATENATE("R9C",'Mapa final'!#REF!),"") -> #REF! | AG34: =IF(AND('Mapa final'!#REF!="Media",'Mapa final'!#REF!="Mayor"),CONCATENATE("R9C",'Mapa final'!#REF!),"") -> #REF! | AH34: =IF(AND('Mapa final'!#REF!="Media",'Mapa final'!#REF!="Catastrófico"),CONCATENATE("R9C",'Mapa final'!#REF!),"") -> #REF! | AI34: =IF(AND('Mapa final'!#REF!="Media",'Mapa final'!#REF!="Catastrófico"),CONCATENATE("R9C",'Mapa final'!#REF!),"") -> #REF! | AJ34: =IF(AND('Mapa final'!#REF!="Media",'Mapa final'!#REF!="Catastrófico"),CONCATENATE("R9C",'Mapa final'!#REF!),"") -> #REF! | AK34: =IF(AND('Mapa final'!#REF!="Media",'Mapa final'!#REF!="Catastrófico"),CONCATENATE("R9C",'Mapa final'!#REF!),"") -> #REF! | AL34: =IF(AND('Mapa final'!#REF!="Media",'Mapa final'!#REF!="Catastrófico"),CONCATENATE("R9C",'Mapa final'!#REF!),"") -> #REF! | AM34: =IF(AND('Mapa final'!#REF!="Media",'Mapa final'!#REF!="Catastrófico"),CONCATENATE("R9C",'Mapa final'!#REF!),"") -> #REF!
J35: =IF(AND('Mapa final'!#REF!="Media",'Mapa final'!#REF!="Leve"),CONCATENATE("R10C",'Mapa final'!#REF!),"") -> #REF! | K35: =IF(AND('Mapa final'!#REF!="Media",'Mapa final'!#REF!="Leve"),CONCATENATE("R10C",'Mapa final'!#REF!),"") -> #REF! | L35: =IF(AND('Mapa final'!#REF!="Media",'Mapa final'!#REF!="Leve"),CONCATENATE("R10C",'Mapa final'!#REF!),"") -> #REF! | M35: =IF(AND('Mapa final'!#REF!="Media",'Mapa final'!#REF!="Leve"),CONCATENATE("R10C",'Mapa final'!#REF!),"") -> #REF! | N35: =IF(AND('Mapa final'!#REF!="Media",'Mapa final'!#REF!="Leve"),CONCATENATE("R10C",'Mapa final'!#REF!),"") -> #REF! | O35: =IF(AND('Mapa final'!#REF!="Media",'Mapa final'!#REF!="Leve"),CONCATENATE("R10C",'Mapa final'!#REF!),"") -> #REF! | P35: =IF(AND('Mapa final'!#REF!="Media",'Mapa final'!#REF!="Menor"),CONCATENATE("R10C",'Mapa final'!#REF!),"") -> #REF! | Q35: =IF(AND('Mapa final'!#REF!="Media",'Mapa final'!#REF!="Menor"),CONCATENATE("R10C",'Mapa final'!#REF!),"") -> #REF! | R35: =IF(AND('Mapa final'!#REF!="Media",'Mapa final'!#REF!="Menor"),CONCATENATE("R10C",'Mapa final'!#REF!),"") -> #REF! | S35: =IF(AND('Mapa final'!#REF!="Media",'Mapa final'!#REF!="Menor"),CONCATENATE("R10C",'Mapa final'!#REF!),"") -> #REF! | T35: =IF(AND('Mapa final'!#REF!="Media",'Mapa final'!#REF!="Menor"),CONCATENATE("R10C",'Mapa final'!#REF!),"") -> #REF! | U35: =IF(AND('Mapa final'!#REF!="Media",'Mapa final'!#REF!="Menor"),CONCATENATE("R10C",'Mapa final'!#REF!),"") -> #REF! | V35: =IF(AND('Mapa final'!#REF!="Media",'Mapa final'!#REF!="Moderado"),CONCATENATE("R10C",'Mapa final'!#REF!),"") -> #REF! | W35: =IF(AND('Mapa final'!#REF!="Media",'Mapa final'!#REF!="Moderado"),CONCATENATE("R10C",'Mapa final'!#REF!),"") -> #REF! | X35: =IF(AND('Mapa final'!#REF!="Media",'Mapa final'!#REF!="Moderado"),CONCATENATE("R10C",'Mapa final'!#REF!),"") -> #REF! | Y35: =IF(AND('Mapa final'!#REF!="Media",'Mapa final'!#REF!="Moderado"),CONCATENATE("R10C",'Mapa final'!#REF!),"") -> #REF! | Z35: =IF(AND('Mapa final'!#REF!="Media",'Mapa final'!#REF!="Moderado"),CONCATENATE("R10C",'Mapa final'!#REF!),"") -> #REF! | AA35: =IF(AND('Mapa final'!#REF!="Media",'Mapa final'!#REF!="Moderado"),CONCATENATE("R10C",'Mapa final'!#REF!),"") -> #REF! | AB35: =IF(AND('Mapa final'!#REF!="Media",'Mapa final'!#REF!="Mayor"),CONCATENATE("R10C",'Mapa final'!#REF!),"") -> #REF! | AC35: =IF(AND('Mapa final'!#REF!="Media",'Mapa final'!#REF!="Mayor"),CONCATENATE("R10C",'Mapa final'!#REF!),"") -> #REF! | AD35: =IF(AND('Mapa final'!#REF!="Media",'Mapa final'!#REF!="Mayor"),CONCATENATE("R10C",'Mapa final'!#REF!),"") -> #REF! | AE35: =IF(AND('Mapa final'!#REF!="Media",'Mapa final'!#REF!="Mayor"),CONCATENATE("R10C",'Mapa final'!#REF!),"") -> #REF! | AF35: =IF(AND('Mapa final'!#REF!="Media",'Mapa final'!#REF!="Mayor"),CONCATENATE("R10C",'Mapa final'!#REF!),"") -> #REF! | AG35: =IF(AND('Mapa final'!#REF!="Media",'Mapa final'!#REF!="Mayor"),CONCATENATE("R10C",'Mapa final'!#REF!),"") -> #REF! | AH35: =IF(AND('Mapa final'!#REF!="Media",'Mapa final'!#REF!="Catastrófico"),CONCATENATE("R10C",'Mapa final'!#REF!),"") -> #REF! | AI35: =IF(AND('Mapa final'!#REF!="Media",'Mapa final'!#REF!="Catastrófico"),CONCATENATE("R10C",'Mapa final'!#REF!),"") -> #REF! | AJ35: =IF(AND('Mapa final'!#REF!="Media",'Mapa final'!#REF!="Catastrófico"),CONCATENATE("R10C",'Mapa final'!#REF!),"") -> #REF! | AK35: =IF(AND('Mapa final'!#REF!="Media",'Mapa final'!#REF!="Catastrófico"),CONCATENATE("R10C",'Mapa final'!#REF!),"") -> #REF! | AL35: =IF(AND('Mapa final'!#REF!="Media",'Mapa final'!#REF!="Catastrófico"),CONCATENATE("R10C",'Mapa final'!#REF!),"") -> #REF! | AM35: =IF(AND('Mapa final'!#REF!="Media",'Mapa final'!#REF!="Catastrófico"),CONCATENATE("R10C",'Mapa final'!#REF!),"") -> #REF!
E36: Baja 40% | J36: =IF(AND('Mapa final'!$Y$13="Baja",'Mapa final'!$AA$13="Leve"),CONCATENATE("R1C",'Mapa final'!$O$13),"") -> R1C1 | K36: =IF(AND('Mapa final'!$Y$14="Baja",'Mapa final'!$AA$14="Leve"),CONCATENATE("R1C",'Mapa final'!$O$14),"") | L36: =IF(AND('Mapa final'!$Y$15="Baja",'Mapa final'!$AA$15="Leve"),CONCATENATE("R1C",'Mapa final'!$O$15),"") | M36: =IF(AND('Mapa final'!$Y$16="Baja",'Mapa final'!$AA$16="Leve"),CONCATENATE("R1C",'Mapa final'!$O$16),"") | N36: =IF(AND('Mapa final'!$Y$17="Baja",'Mapa final'!$AA$17="Leve"),CONCATENATE("R1C",'Mapa final'!$O$17),"") | O36: =IF(AND('Mapa final'!$Y$18="Baja",'Mapa final'!$AA$18="Leve"),CONCATENATE("R1C",'Mapa final'!$O$18),"") | P36: =IF(AND('Mapa final'!$Y$13="Baja",'Mapa final'!$AA$13="Menor"),CONCATENATE("R1C",'Mapa final'!$O$13),"") | Q36: =IF(AND('Mapa final'!$Y$14="Baja",'Mapa final'!$AA$14="Menor"),CONCATENATE("R1C",'Mapa final'!$O$14),"") | R36: =IF(AND('Mapa final'!$Y$15="Baja",'Mapa final'!$AA$15="Menor"),CONCATENATE("R1C",'Mapa final'!$O$15),"") | S36: =IF(AND('Mapa final'!$Y$16="Baja",'Mapa final'!$AA$16="Menor"),CONCATENATE("R1C",'Mapa final'!$O$16),"") | T36: =IF(AND('Mapa final'!$Y$17="Baja",'Mapa final'!$AA$17="Menor"),CONCATENATE("R1C",'Mapa final'!$O$17),"") | U36: =IF(AND('Mapa final'!$Y$18="Baja",'Mapa final'!$AA$18="Menor"),CONCATENATE("R1C",'Mapa final'!$O$18),"") | V36: =IF(AND('Mapa final'!$Y$13="Baja",'Mapa final'!$AA$13="Moderado"),CONCATENATE("R1C",'Mapa final'!$O$13),"") | W36: =IF(AND('Mapa final'!$Y$14="Baja",'Mapa final'!$AA$14="Moderado"),CONCATENATE("R1C",'Mapa final'!$O$14),"") | X36: =IF(AND('Mapa final'!$Y$15="Baja",'Mapa final'!$AA$15="Moderado"),CONCATENATE("R1C",'Mapa final'!$O$15),"") | Y36: =IF(AND('Mapa final'!$Y$16="Baja",'Mapa final'!$AA$16="Moderado"),CONCATENATE("R1C",'Mapa final'!$O$16),"") | Z36: =IF(AND('Mapa final'!$Y$17="Baja",'Mapa final'!$AA$17="Moderado"),CONCATENATE("R1C",'Mapa final'!$O$17),"") | AA36: =IF(AND('Mapa final'!$Y$18="Baja",'Mapa final'!$AA$18="Moderado"),CONCATENATE("R1C",'Mapa final'!$O$18),"") | AB36: =IF(AND('Mapa final'!$Y$13="Baja",'Mapa final'!$AA$13="Mayor"),CONCATENATE("R1C",'Mapa final'!$O$13),"") | AC36: =IF(AND('Mapa final'!$Y$14="Baja",'Mapa final'!$AA$14="Mayor"),CONCATENATE("R1C",'Mapa final'!$O$14),"") | AD36: =IF(AND('Mapa final'!$Y$15="Baja",'Mapa final'!$AA$15="Mayor"),CONCATENATE("R1C",'Mapa final'!$O$15),"") | AE36: =IF(AND('Mapa final'!$Y$16="Baja",'Mapa final'!$AA$16="Mayor"),CONCATENATE("R1C",'Mapa final'!$O$16),"") | AF36: =IF(AND('Mapa final'!$Y$17="Baja",'Mapa final'!$AA$17="Mayor"),CONCATENATE("R1C",'Mapa final'!$O$17),"") | AG36: =IF(AND('Mapa final'!$Y$18="Baja",'Mapa final'!$AA$18="Mayor"),CONCATENATE("R1C",'Mapa final'!$O$18),"") | AH36: =IF(AND('Mapa final'!$Y$13="Baja",'Mapa final'!$AA$13="Catastrófico"),CONCATENATE("R1C",'Mapa final'!$O$13),"") | AI36: =IF(AND('Mapa final'!$Y$14="Baja",'Mapa final'!$AA$14="Catastrófico"),CONCATENATE("R1C",'Mapa final'!$O$14),"") | AJ36: =IF(AND('Mapa final'!$Y$15="Baja",'Mapa final'!$AA$15="Catastrófico"),CONCATENATE("R1C",'Mapa final'!$O$15),"") | AK36: =IF(AND('Mapa final'!$Y$16="Baja",'Mapa final'!$AA$16="Catastrófico"),CONCATENATE("R1C",'Mapa final'!$O$16),"") | AL36: =IF(AND('Mapa final'!$Y$17="Baja",'Mapa final'!$AA$17="Catastrófico"),CONCATENATE("R1C",'Mapa final'!$O$17),"") | AM36: =IF(AND('Mapa final'!$Y$18="Baja",'Mapa final'!$AA$18="Catastrófico"),CONCATENATE("R1C",'Mapa final'!$O$18),"") | AO36: Bajo
J37: =IF(AND('Mapa final'!#REF!="Baja",'Mapa final'!#REF!="Leve"),CONCATENATE("R2C",'Mapa final'!#REF!),"") -> #REF! | K37: =IF(AND('Mapa final'!#REF!="Baja",'Mapa final'!#REF!="Leve"),CONCATENATE("R2C",'Mapa final'!#REF!),"") -> #REF! | L37: =IF(AND('Mapa final'!#REF!="Baja",'Mapa final'!#REF!="Leve"),CONCATENATE("R2C",'Mapa final'!#REF!),"") -> #REF! | M37: =IF(AND('Mapa final'!#REF!="Baja",'Mapa final'!#REF!="Leve"),CONCATENATE("R2C",'Mapa final'!#REF!),"") -> #REF! | N37: =IF(AND('Mapa final'!#REF!="Baja",'Mapa final'!#REF!="Leve"),CONCATENATE("R2C",'Mapa final'!#REF!),"") -> #REF! | O37: =IF(AND('Mapa final'!#REF!="Baja",'Mapa final'!#REF!="Leve"),CONCATENATE("R2C",'Mapa final'!#REF!),"") -> #REF! | P37: =IF(AND('Mapa final'!#REF!="Baja",'Mapa final'!#REF!="Menor"),CONCATENATE("R2C",'Mapa final'!#REF!),"") -> #REF! | Q37: =IF(AND('Mapa final'!#REF!="Baja",'Mapa final'!#REF!="Menor"),CONCATENATE("R2C",'Mapa final'!#REF!),"") -> #REF! | R37: =IF(AND('Mapa final'!#REF!="Baja",'Mapa final'!#REF!="Menor"),CONCATENATE("R2C",'Mapa final'!#REF!),"") -> #REF! | S37: =IF(AND('Mapa final'!#REF!="Baja",'Mapa final'!#REF!="Menor"),CONCATENATE("R2C",'Mapa final'!#REF!),"") -> #REF! | T37: =IF(AND('Mapa final'!#REF!="Baja",'Mapa final'!#REF!="Menor"),CONCATENATE("R2C",'Mapa final'!#REF!),"") -> #REF! | U37: =IF(AND('Mapa final'!#REF!="Baja",'Mapa final'!#REF!="Menor"),CONCATENATE("R2C",'Mapa final'!#REF!),"") -> #REF! | V37: =IF(AND('Mapa final'!#REF!="Baja",'Mapa final'!#REF!="Moderado"),CONCATENATE("R2C",'Mapa final'!#REF!),"") -> #REF! | W37: =IF(AND('Mapa final'!#REF!="Baja",'Mapa final'!#REF!="Moderado"),CONCATENATE("R2C",'Mapa final'!#REF!),"") -> #REF! | X37: =IF(AND('Mapa final'!#REF!="Baja",'Mapa final'!#REF!="Moderado"),CONCATENATE("R2C",'Mapa final'!#REF!),"") -> #REF! | Y37: =IF(AND('Mapa final'!#REF!="Baja",'Mapa final'!#REF!="Moderado"),CONCATENATE("R2C",'Mapa final'!#REF!),"") -> #REF! | Z37: =IF(AND('Mapa final'!#REF!="Baja",'Mapa final'!#REF!="Moderado"),CONCATENATE("R2C",'Mapa final'!#REF!),"") -> #REF! | AA37: =IF(AND('Mapa final'!#REF!="Baja",'Mapa final'!#REF!="Moderado"),CONCATENATE("R2C",'Mapa final'!#REF!),"") -> #REF! | AB37: =IF(AND('Mapa final'!#REF!="Baja",'Mapa final'!#REF!="Mayor"),CONCATENATE("R2C",'Mapa final'!#REF!),"") -> #REF! | AC37: =IF(AND('Mapa final'!#REF!="Baja",'Mapa final'!#REF!="Mayor"),CONCATENATE("R2C",'Mapa final'!#REF!),"") -> #REF! | AD37: =IF(AND('Mapa final'!#REF!="Baja",'Mapa final'!#REF!="Mayor"),CONCATENATE("R2C",'Mapa final'!#REF!),"") -> #REF! | AE37: =IF(AND('Mapa final'!#REF!="Baja",'Mapa final'!#REF!="Mayor"),CONCATENATE("R2C",'Mapa final'!#REF!),"") -> #REF! | AF37: =IF(AND('Mapa final'!#REF!="Baja",'Mapa final'!#REF!="Mayor"),CONCATENATE("R2C",'Mapa final'!#REF!),"") -> #REF! | AG37: =IF(AND('Mapa final'!#REF!="Baja",'Mapa final'!#REF!="Mayor"),CONCATENATE("R2C",'Mapa final'!#REF!),"") -> #REF! | AH37: =IF(AND('Mapa final'!#REF!="Baja",'Mapa final'!#REF!="Catastrófico"),CONCATENATE("R2C",'Mapa final'!#REF!),"") -> #REF! | AI37: =IF(AND('Mapa final'!#REF!="Baja",'Mapa final'!#REF!="Catastrófico"),CONCATENATE("R2C",'Mapa final'!#REF!),"") -> #REF! | AJ37: =IF(AND('Mapa final'!#REF!="Baja",'Mapa final'!#REF!="Catastrófico"),CONCATENATE("R2C",'Mapa final'!#REF!),"") -> #REF! | AK37: =IF(AND('Mapa final'!#REF!="Baja",'Mapa final'!#REF!="Catastrófico"),CONCATENATE("R2C",'Mapa final'!#REF!),"") -> #REF! | AL37: =IF(AND('Mapa final'!#REF!="Baja",'Mapa final'!#REF!="Catastrófico"),CONCATENATE("R2C",'Mapa final'!#REF!),"") -> #REF! | AM37: =IF(AND('Mapa final'!#REF!="Baja",'Mapa final'!#REF!="Catastrófico"),CONCATENATE("R2C",'Mapa final'!#REF!),"") -> #REF!
